Workbook
Name enum_ExchangeRateMethod: importDropDownContent!$A$2:$A$3
Name enum_gl_standard_import_voucher_status: importDropDownContent!$B$2:$B$5
Name refer_finbd.bd_allaccbodyref0: 参照!$C$3:$C$63
Name refer_fiepub.fiepub_accountbooktreeref1: 参照!$G$3:$G$61
Name refer_fiepub.epub_vouchertype_ref2: 参照!$K$3:$K$6
Name refer_bip_usercenter.bip_user_ref3: 参照!$O$3:$O$95
Name refer_ucfbasedoc.bd_currencytenantref4: 参照!$S$3:$S$3
Name refer_ucfbasedoc.bd_exchangeratetyperef5: 参照!$W$3:$W$4
Name refer_productcenter.aa_productunit6: 参照!$AA$3:$AA$37
Name refer_productcenter.aa_settlemethodref7: 参照!$AE$3:$AE$9

Sheet ReadMe
A1: Excel模板使用指南： 模板格式：请严格遵守表格中既定字段顺序，不得擅自调整或增减表头字段，以确保模板合法性。 数据类型：单元格内请输入文本格式的数据，以确保数值不会因excel软件转换丢失精度。 必填标识：带星号（*）的字段为必须填写项，请确保不遗漏。 引用档案：黄色背景字段为引用档案（参照），请填写参照名称或编码。 日期格式：建议使用“YYYY-MM-DD”格式（例如：2021-06-06）来输入日期，确保日期信息的标准化。 特殊字段说明：浅绿色背景字段用于确保数据的唯一性。若无特定业务唯一性要求，则默认使用系统生成的ID（手工码）。若子孙表中有浅蓝色背景的手工码，它是用于关联主表与子表数据的关联标识。 导入过滤：“✓”标记用于指示该行数据在导入过程中将被忽略。此标识常见于业务说明、属性说明或错误明细文件中，以避免重复或错误数据的导入。 国际化格式支持：下载模板时，若启用了“我的首选”功能，下载的模板将自动应用“首选项”的时区、数值、时间等格式设置。在导入数据时，系统将依据这些设置进行自动转换与存储。 总结：请遵循上述指南，以确保数据导入的顺利进行和结果的准确性。

Sheet 亿企凭证
B1: 日期 | C1: 凭证字号 | D1: 摘要 | E1: 科目 | F1: 借方金额 | G1: 贷方金额 | H1: 一级科目编码 | I1: 科目编码 | J1: 一级科目 | K1: 二级科目 | L1: 三级科目 | M1: 对应用友科目编码 | N1: 对应辅助核算类型 | O1: 对应辅助核算 | P1: *(单据头)账簿#编码 | Q1: (单据头)账簿#名称 | R1: *(单据头)日期 | S1: (单据头)期间 | T1: *(单据头)凭证字#编码 | U1: (单据头)凭证字#名称 | V1: *(单据头)凭证号 | W1: *系统码 | X1: *会计主体 | Y1: *账簿 | Z1: 账簿名称 | AA1: *会计期间 | AB1: *制单日期 | AC1: *凭证类型 | AD1: 凭证号 | AE1: 凭证摘要 | AF1: 制单人 | AG1: 制单人名称 | AH1: 附单据数 | AI1: 凭证标识 | AJ1: 结转标识 | AK1: 编码 | AL1: 系统码 | AM1: 分录号 | AN1: *科目 | AO1: 科目名称 | AP1: *摘要 | AQ1: *币种 | AR1: 借方原币金额 | AS1: 贷方原币金额 | AT1: 本币汇率类型 | AU1: 本币汇率折算方式 | AV1: 本币汇率 | AW1: 借方本币金额 | AX1: 贷方本币金额 | AY1: 计量单位 | AZ1: 计量单位名称 | BA1: 单价 | BB1: 借方数量 | BC1: 贷方数量 | BD1: 业务日期 | BE1: 结算方式 | BF1: 票据号 | BG1: 票据日期 | BH1: 银行对账码 | BI1: 核销号 | BJ1: 内部单位 | BK1: 现金流量主表项编码 | BL1: 现金流量附表项编码 | BM1: 现金流量项原币金额 | BN1: 现金流量项本币金额 | BO1: 部门_编码 | BP1: 部门_名称 | BQ1: 项目_编码 | BR1: 项目_名称 | BS1: 人员_编码 | BT1: 人员_名称 | BU1: 供应商_编码 | BV1: 供应商_名称 | BW1: 客户_编码 | BX1: 客户_名称 | BY1: 物料_编码 | BZ1: 物料_名称 | CA1: 物料分类_编码 | CB1: 物料分类_名称 | CC1: 成本中心_编码 | CD1: 成本中心_名称 | CE1: 业务伙伴_编码 | CF1: 业务伙伴_名称 | CG1: 利润中心_编码 | CH1: 利润中心_名称 | CI1: 业务活动类型_编码 | CJ1: 业务活动类型_名称 | CK1: 业务组织_编码 | CL1: 业务组织_名称 | CM1: 土地_编码 | CN1: 土地_名称 | CO1: 员工_编码 | CP1: 员工_名称 | CQ1: 会计商品_编码 | CR1: 会计商品_名称 | CS1: 内部核算单元_编码 | CT1: 内部核算单元_名称 | CU1: 费用项目_编码 | CV1: 费用项目_名称 | CW1: 银行账户_编码 | CX1: 银行账户_名称
A2: 昌邑泓澄水业有限公司 | B2: 2026-04-20 | C2: 记-001 | D2: 往来款,昌邑市城市建设发展投资集团有限公司 | E2: 100201 银行存款-工商银行3066 | F2: 390000 | H2: =LEFT(E2,4) -> 1002 | I2: =IFERROR(LEFT(E2,FIND(" ",E2)-1),E2) -> 100201 | J2: =LEFT(MID(E2,FIND(" ",E2)+1,LEN(E2)),FIND("-",MID(E2,FIND(" ",E2)+1,LEN(E2))&"-")-1) -> 银行存款 | K2: =IFERROR(MID(MID(E2,FIND(" ",E2)+1,LEN(E2)),FIND("-",MID(E2,FIND(" ",E2)+1,LEN(E2)))+1,IFERROR(FIND("-",MID(E2,FIND(" ",E2)+1,LEN(E2)),FIND("-",MID(E2,FIND(" ",E2)+1,LEN(E2)))+1),LEN(MID(E2,FIND(" ",E2)+1,LEN(E2)))+1)-FIND("-",MID(E2,FIND(" ",E2)+1,LEN(E2)))-1),"") -> 工商银行3066 | L2: =IFERROR(MID(MID(E2,FIND(" ",E2)+1,LEN(E2)),FIND("-",MID(E2,FIND(" ",E2)+1,LEN(E2)),FIND("-",MID(E2,FIND(" ",E2)+1,LEN(E2)))+1)+1,LEN(E2)),"") | M2: =IF(H2="1002",1002,VLOOKUP(I2,亿企科目!A:H,6,0)) -> 1002 | N2: =IFERROR(IF(H2="1002","银行账户",IF(H2="1123","供应商",VLOOKUP(I2,亿企科目!A:H,8,0))),"") -> 银行账户 | O2: =IF(N2=0,IF(M2="1002",K2,""),_xlfn.TEXTAFTER(E2,"-",-1)) -> 工商银行3066 | P2: =VLOOKUP(A2,账簿!B:C,2,0) -> 002022 | Q2: =VLOOKUP(P2,账簿!A:B,2,0) -> 昌邑泓澄水业有限公司 | W2: =X2&AB2&AD2 -> 0020222026-04-201 | X2: =P2 -> 002022 | Y2: =X2 -> 002022 | Z2: =Q2 -> 昌邑泓澄水业有限公司 | AA2: =LEFT(B2,7) -> 2026-04 | AB2: =B2 -> 2026-04-20 | AC2: 记 | AD2: =VALUE(_xlfn.TEXTAFTER(C2,"-")) -> 1 | AE2: =D2 -> 往来款,昌邑市城市建设发展投资集团有限公司 | AF2: 谭雅心 | AG2: 谭雅心 | AN2: =M2 -> 1002 | AP2: =D2 -> 往来款,昌邑市城市建设发展投资集团有限公司 | AQ2: CNY | AR2: =F2 -> 390000 | AS2: =G2 | AT2: 01 | AU2: * | AV2: 1 | AW2: =AR2 -> 390000 | AX2: =AS2 | BQ2: =IF(N2="项目",VLOOKUP(O2,项目!B:C,2,0),IF(K2="空项目",VLOOKUP(K2,项目!B:C,2,0),"")) | BR2: =IFERROR(VLOOKUP(BQ2,项目!A:B,2,0),"") | BU2: =IF(N2="供应商",VLOOKUP(O2,供应商!B:C,2,0),"") | BV2: =IFERROR(VLOOKUP(BU2,供应商!A:B,2,0),"") | BW2: =IF(N2="客户",VLOOKUP(O2,客户!B:C,2,0),"") | BX2: =IFERROR(VLOOKUP(BW2,客户!A:B,2,0),"") | CU2: =IF(N2="费用项目",VLOOKUP(O2,费用项目!B:C,2,0),"") | CV2: =IFERROR(VLOOKUP(CU2,费用项目!A:B,2,0),"") | CW2: =IF(N2="银行账户",VLOOKUP(O2,银行变二级!B:C,2,0),"") -> 工商银行3066 | CX2: =IFERROR(VLOOKUP(O2,银行变二级!A:B,2,0),"") -> 工商银行3066
A3: 昌邑泓澄水业有限公司 | B3: 2026-04-20 | C3: 记-001 | D3: 往来款,昌邑市城市建设发展投资集团有限公司 | E3: 122108 其他应收款-单位-昌邑市城市建设发展投资集团有限公司 | G3: 390000 | H3: =LEFT(E3,4) -> 1221 | I3: =IFERROR(LEFT(E3,FIND(" ",E3)-1),E3) -> 122108 | J3: =LEFT(MID(E3,FIND(" ",E3)+1,LEN(E3)),FIND("-",MID(E3,FIND(" ",E3)+1,LEN(E3))&"-")-1) -> 其他应收款 | K3: =IFERROR(MID(MID(E3,FIND(" ",E3)+1,LEN(E3)),FIND("-",MID(E3,FIND(" ",E3)+1,LEN(E3)))+1,IFERROR(FIND("-",MID(E3,FIND(" ",E3)+1,LEN(E3)),FIND("-",MID(E3,FIND(" ",E3)+1,LEN(E3)))+1),LEN(MID(E3,FIND(" ",E3)+1,LEN(E3)))+1)-FIND("-",MID(E3,FIND(" ",E3)+1,LEN(E3)))-1),"") -> 单位 | L3: =IFERROR(MID(MID(E3,FIND(" ",E3)+1,LEN(E3)),FIND("-",MID(E3,FIND(" ",E3)+1,LEN(E3)),FIND("-",MID(E3,FIND(" ",E3)+1,LEN(E3)))+1)+1,LEN(E3)),"") -> 昌邑市城市建设发展投资集团有限公司 | M3: =IFERROR(IF(H3="1002",1002,VLOOKUP(I3,亿企科目!A:H,6,0)),VLOOKUP(H3,亿企科目!A:G,6,0)) -> 122102 | N3: =IFERROR(IF(H3="1002","银行账户",IF(H3="1123","供应商",VLOOKUP(I3,亿企科目!A:H,8,0))),"") -> 客户 | O3: =IF(N3=0,IF(M3="1002",K3,""),_xlfn.TEXTAFTER(E3,"-",-1)) -> 昌邑市城市建设发展投资集团有限公司 | P3: =VLOOKUP(A3,账簿!B:C,2,0) -> 002022 | Q3: =VLOOKUP(P3,账簿!A:B,2,0) -> 昌邑泓澄水业有限公司 | W3: =X3&AB3&AD3 -> 0020222026-04-201 | X3: =P3 -> 002022 | Y3: =X3 -> 002022 | Z3: =Q3 -> 昌邑泓澄水业有限公司 | AA3: =LEFT(B3,7) -> 2026-04 | AB3: =B3 -> 2026-04-20 | AC3: 记 | AD3: =VALUE(_xlfn.TEXTAFTER(C3,"-")) -> 1 | AE3: =D3 -> 往来款,昌邑市城市建设发展投资集团有限公司 | AF3: 谭雅心 | AG3: 谭雅心 | AN3: =M3 -> 122102 | AP3: =D3 -> 往来款,昌邑市城市建设发展投资集团有限公司 | AQ3: CNY | AR3: =F3 | AS3: =G3 -> 390000 | AT3: 01 | AU3: * | AV3: 1 | AW3: =AR3 | AX3: =AS3 -> 390000 | BQ3: =IF(N3="项目",VLOOKUP(O3,项目!B:C,2,0),IF(K3="空项目",VLOOKUP(K3,项目!B:C,2,0),"")) | BR3: =IFERROR(VLOOKUP(BQ3,项目!A:B,2,0),"") | BU3: =IF(N3="供应商",VLOOKUP(O3,供应商!B:C,2,0),"") | BV3: =IFERROR(VLOOKUP(BU3,供应商!A:B,2,0),"") | BW3: =IF(N3="客户",VLOOKUP(O3,客户!B:C,2,0),"") -> 002 | BX3: =IFERROR(VLOOKUP(BW3,客户!A:B,2,0),"") -> 昌邑市城市建设发展投资集团有限公司 | CU3: =IF(N3="费用项目",VLOOKUP(O3,费用项目!B:C,2,0),"") | CV3: =IFERROR(VLOOKUP(CU3,费用项目!A:B,2,0),"") | CW3: =IF(N3="银行账户",VLOOKUP(O3,银行变二级!B:C,2,0),"") | CX3: =IFERROR(VLOOKUP(O3,银行变二级!A:B,2,0),"")
A4: 昌邑泓澄水业有限公司 | B4: 2026-04-20 | C4: 记-002 | D4: 往来款,昌邑市昌宜投资有限公司 | E4: 100201 银行存款-工商银行3066 | F4: 20000000 | H4: =LEFT(E4,4) -> 1002 | I4: =IFERROR(LEFT(E4,FIND(" ",E4)-1),E4) -> 100201 | J4: =LEFT(MID(E4,FIND(" ",E4)+1,LEN(E4)),FIND("-",MID(E4,FIND(" ",E4)+1,LEN(E4))&"-")-1) -> 银行存款 | K4: =IFERROR(MID(MID(E4,FIND(" ",E4)+1,LEN(E4)),FIND("-",MID(E4,FIND(" ",E4)+1,LEN(E4)))+1,IFERROR(FIND("-",MID(E4,FIND(" ",E4)+1,LEN(E4)),FIND("-",MID(E4,FIND(" ",E4)+1,LEN(E4)))+1),LEN(MID(E4,FIND(" ",E4)+1,LEN(E4)))+1)-FIND("-",MID(E4,FIND(" ",E4)+1,LEN(E4)))-1),"") -> 工商银行3066 | L4: =IFERROR(MID(MID(E4,FIND(" ",E4)+1,LEN(E4)),FIND("-",MID(E4,FIND(" ",E4)+1,LEN(E4)),FIND("-",MID(E4,FIND(" ",E4)+1,LEN(E4)))+1)+1,LEN(E4)),"") | M4: =IFERROR(IF(H4="1002",1002,VLOOKUP(I4,亿企科目!A:H,6,0)),VLOOKUP(H4,亿企科目!A:G,6,0)) -> 1002 | N4: =IFERROR(IF(H4="1002","银行账户",IF(H4="1123","供应商",VLOOKUP(I4,亿企科目!A:H,8,0))),"") -> 银行账户 | O4: =IF(N4=0,IF(M4="1002",K4,""),_xlfn.TEXTAFTER(E4,"-",-1)) -> 工商银行3066 | P4: =VLOOKUP(A4,账簿!B:C,2,0) -> 002022 | Q4: =VLOOKUP(P4,账簿!A:B,2,0) -> 昌邑泓澄水业有限公司 | W4: =X4&AB4&AD4 -> 0020222026-04-202 | X4: =P4 -> 002022 | Y4: =X4 -> 002022 | Z4: =Q4 -> 昌邑泓澄水业有限公司 | AA4: =LEFT(B4,7) -> 2026-04 | AB4: =B4 -> 2026-04-20 | AC4: 记 | AD4: =VALUE(_xlfn.TEXTAFTER(C4,"-")) -> 2 | AE4: =D4 -> 往来款,昌邑市昌宜投资有限公司 | AF4: 谭雅心 | AG4: 谭雅心 | AN4: =M4 -> 1002 | AP4: =D4 -> 往来款,昌邑市昌宜投资有限公司 | AQ4: CNY | AR4: =F4 -> 20000000 | AS4: =G4 | AT4: 01 | AU4: * | AV4: 1 | AW4: =AR4 -> 20000000 | AX4: =AS4 | BQ4: =IF(N4="项目",VLOOKUP(O4,项目!B:C,2,0),IF(K4="空项目",VLOOKUP(K4,项目!B:C,2,0),"")) | BR4: =IFERROR(VLOOKUP(BQ4,项目!A:B,2,0),"") | BU4: =IF(N4="供应商",VLOOKUP(O4,供应商!B:C,2,0),"") | BV4: =IFERROR(VLOOKUP(BU4,供应商!A:B,2,0),"") | BW4: =IF(N4="客户",VLOOKUP(O4,客户!B:C,2,0),"") | BX4: =IFERROR(VLOOKUP(BW4,客户!A:B,2,0),"") | CU4: =IF(N4="费用项目",VLOOKUP(O4,费用项目!B:C,2,0),"") | CV4: =IFERROR(VLOOKUP(CU4,费用项目!A:B,2,0),"") | CW4: =IF(N4="银行账户",VLOOKUP(O4,银行变二级!B:C,2,0),"") -> 工商银行3066 | CX4: =IFERROR(VLOOKUP(O4,银行变二级!A:B,2,0),"") -> 工商银行3066
A5: 昌邑泓澄水业有限公司 | B5: 2026-04-20 | C5: 记-002 | D5: 往来款,昌邑市昌宜投资有限公司 | E5: 122108 其他应收款-单位-昌邑市昌宜投资有限公司 | G5: 20000000 | H5: =LEFT(E5,4) -> 1221 | I5: =IFERROR(LEFT(E5,FIND(" ",E5)-1),E5) -> 122108 | J5: =LEFT(MID(E5,FIND(" ",E5)+1,LEN(E5)),FIND("-",MID(E5,FIND(" ",E5)+1,LEN(E5))&"-")-1) -> 其他应收款 | K5: =IFERROR(MID(MID(E5,FIND(" ",E5)+1,LEN(E5)),FIND("-",MID(E5,FIND(" ",E5)+1,LEN(E5)))+1,IFERROR(FIND("-",MID(E5,FIND(" ",E5)+1,LEN(E5)),FIND("-",MID(E5,FIND(" ",E5)+1,LEN(E5)))+1),LEN(MID(E5,FIND(" ",E5)+1,LEN(E5)))+1)-FIND("-",MID(E5,FIND(" ",E5)+1,LEN(E5)))-1),"") -> 单位 | L5: =IFERROR(MID(MID(E5,FIND(" ",E5)+1,LEN(E5)),FIND("-",MID(E5,FIND(" ",E5)+1,LEN(E5)),FIND("-",MID(E5,FIND(" ",E5)+1,LEN(E5)))+1)+1,LEN(E5)),"") -> 昌邑市昌宜投资有限公司 | M5: =IFERROR(IF(H5="1002",1002,VLOOKUP(I5,亿企科目!A:H,6,0)),VLOOKUP(H5,亿企科目!A:G,6,0)) -> 122102 | N5: =IFERROR(IF(H5="1002","银行账户",IF(H5="1123","供应商",VLOOKUP(I5,亿企科目!A:H,8,0))),"") -> 客户 | O5: =IF(N5=0,IF(M5="1002",K5,""),_xlfn.TEXTAFTER(E5,"-",-1)) -> 昌邑市昌宜投资有限公司 | P5: =VLOOKUP(A5,账簿!B:C,2,0) -> 002022 | Q5: =VLOOKUP(P5,账簿!A:B,2,0) -> 昌邑泓澄水业有限公司 | W5: =X5&AB5&AD5 -> 0020222026-04-202 | X5: =P5 -> 002022 | Y5: =X5 -> 002022 | Z5: =Q5 -> 昌邑泓澄水业有限公司 | AA5: =LEFT(B5,7) -> 2026-04 | AB5: =B5 -> 2026-04-20 | AC5: 记 | AD5: =VALUE(_xlfn.TEXTAFTER(C5,"-")) -> 2 | AE5: =D5 -> 往来款,昌邑市昌宜投资有限公司 | AF5: 谭雅心 | AG5: 谭雅心 | AN5: =M5 -> 122102 | AP5: =D5 -> 往来款,昌邑市昌宜投资有限公司 | AQ5: CNY | AR5: =F5 | AS5: =G5 -> 20000000 | AT5: 01 | AU5: * | AV5: 1 | AW5: =AR5 | AX5: =AS5 -> 20000000 | BQ5: =IF(N5="项目",VLOOKUP(O5,项目!B:C,2,0),IF(K5="空项目",VLOOKUP(K5,项目!B:C,2,0),"")) | BR5: =IFERROR(VLOOKUP(BQ5,项目!A:B,2,0),"") | BU5: =IF(N5="供应商",VLOOKUP(O5,供应商!B:C,2,0),"") | BV5: =IFERROR(VLOOKUP(BU5,供应商!A:B,2,0),"") | BW5: =IF(N5="客户",VLOOKUP(O5,客户!B:C,2,0),"") -> 003019 | BX5: =IFERROR(VLOOKUP(BW5,客户!A:B,2,0),"") -> 昌邑市昌宜投资有限公司 | CU5: =IF(N5="费用项目",VLOOKUP(O5,费用项目!B:C,2,0),"") | CV5: =IFERROR(VLOOKUP(CU5,费用项目!A:B,2,0),"") | CW5: =IF(N5="银行账户",VLOOKUP(O5,银行变二级!B:C,2,0),"") | CX5: =IFERROR(VLOOKUP(O5,银行变二级!A:B,2,0),"")
A6: 昌邑泓澄水业有限公司 | B6: 2026-04-20 | C6: 记-003 | D6: 海洋水业公司并购,青岛天合易辉贸易有限公司 | E6: 151101 长期股权投资-投资成本-青岛天合易辉贸易有限公司 | F6: 14285900 | H6: =LEFT(E6,4) -> 1511 | I6: =IFERROR(LEFT(E6,FIND(" ",E6)-1),E6) -> 151101 | J6: =LEFT(MID(E6,FIND(" ",E6)+1,LEN(E6)),FIND("-",MID(E6,FIND(" ",E6)+1,LEN(E6))&"-")-1) -> 长期股权投资 | K6: =IFERROR(MID(MID(E6,FIND(" ",E6)+1,LEN(E6)),FIND("-",MID(E6,FIND(" ",E6)+1,LEN(E6)))+1,IFERROR(FIND("-",MID(E6,FIND(" ",E6)+1,LEN(E6)),FIND("-",MID(E6,FIND(" ",E6)+1,LEN(E6)))+1),LEN(MID(E6,FIND(" ",E6)+1,LEN(E6)))+1)-FIND("-",MID(E6,FIND(" ",E6)+1,LEN(E6)))-1),"") -> 投资成本 | L6: =IFERROR(MID(MID(E6,FIND(" ",E6)+1,LEN(E6)),FIND("-",MID(E6,FIND(" ",E6)+1,LEN(E6)),FIND("-",MID(E6,FIND(" ",E6)+1,LEN(E6)))+1)+1,LEN(E6)),"") -> 青岛天合易辉贸易有限公司 | M6: =IFERROR(IF(H6="1002",1002,VLOOKUP(I6,亿企科目!A:H,6,0)),VLOOKUP(H6,亿企科目!A:G,6,0)) -> 151101 | N6: =IFERROR(IF(H6="1002","银行账户",IF(H6="1123","供应商",VLOOKUP(I6,亿企科目!A:H,8,0))),"") -> 客户 | O6: =IF(N6=0,IF(M6="1002",K6,""),_xlfn.TEXTAFTER(E6,"-",-1)) -> 青岛天合易辉贸易有限公司 | P6: =VLOOKUP(A6,账簿!B:C,2,0) -> 002022 | Q6: =VLOOKUP(P6,账簿!A:B,2,0) -> 昌邑泓澄水业有限公司 | W6: =X6&AB6&AD6 -> 0020222026-04-203 | X6: =P6 -> 002022 | Y6: =X6 -> 002022 | Z6: =Q6 -> 昌邑泓澄水业有限公司 | AA6: =LEFT(B6,7) -> 2026-04 | AB6: =B6 -> 2026-04-20 | AC6: 记 | AD6: =VALUE(_xlfn.TEXTAFTER(C6,"-")) -> 3 | AE6: =D6 -> 海洋水业公司并购,青岛天合易辉贸易有限公司 | AF6: 谭雅心 | AG6: 谭雅心 | AN6: =M6 -> 151101 | AP6: =D6 -> 海洋水业公司并购,青岛天合易辉贸易有限公司 | AQ6: CNY | AR6: =F6 -> 14285900 | AS6: =G6 | AT6: 01 | AU6: * | AV6: 1 | AW6: =AR6 -> 14285900 | AX6: =AS6 | BQ6: =IF(N6="项目",VLOOKUP(O6,项目!B:C,2,0),IF(K6="空项目",VLOOKUP(K6,项目!B:C,2,0),"")) | BR6: =IFERROR(VLOOKUP(BQ6,项目!A:B,2,0),"") | BU6: =IF(N6="供应商",VLOOKUP(O6,供应商!B:C,2,0),"") | BV6: =IFERROR(VLOOKUP(BU6,供应商!A:B,2,0),"") | BW6: =IF(N6="客户",VLOOKUP(O6,客户!B:C,2,0),"") -> 0020006 | BX6: =IFERROR(VLOOKUP(BW6,客户!A:B,2,0),"") -> 青岛天合易辉贸易有限公司 | CU6: =IF(N6="费用项目",VLOOKUP(O6,费用项目!B:C,2,0),"") | CV6: =IFERROR(VLOOKUP(CU6,费用项目!A:B,2,0),"") | CW6: =IF(N6="银行账户",VLOOKUP(O6,银行变二级!B:C,2,0),"") | CX6: =IFERROR(VLOOKUP(O6,银行变二级!A:B,2,0),"")
A7: 昌邑泓澄水业有限公司 | B7: 2026-04-20 | C7: 记-003 | D7: 海洋水业公司并购,青岛天合易辉贸易有限公司 | E7: 100201 银行存款-工商银行3066 | G7: 14285900 | H7: =LEFT(E7,4) -> 1002 | I7: =IFERROR(LEFT(E7,FIND(" ",E7)-1),E7) -> 100201 | J7: =LEFT(MID(E7,FIND(" ",E7)+1,LEN(E7)),FIND("-",MID(E7,FIND(" ",E7)+1,LEN(E7))&"-")-1) -> 银行存款 | K7: =IFERROR(MID(MID(E7,FIND(" ",E7)+1,LEN(E7)),FIND("-",MID(E7,FIND(" ",E7)+1,LEN(E7)))+1,IFERROR(FIND("-",MID(E7,FIND(" ",E7)+1,LEN(E7)),FIND("-",MID(E7,FIND(" ",E7)+1,LEN(E7)))+1),LEN(MID(E7,FIND(" ",E7)+1,LEN(E7)))+1)-FIND("-",MID(E7,FIND(" ",E7)+1,LEN(E7)))-1),"") -> 工商银行3066 | L7: =IFERROR(MID(MID(E7,FIND(" ",E7)+1,LEN(E7)),FIND("-",MID(E7,FIND(" ",E7)+1,LEN(E7)),FIND("-",MID(E7,FIND(" ",E7)+1,LEN(E7)))+1)+1,LEN(E7)),"") | M7: =IFERROR(IF(H7="1002",1002,VLOOKUP(I7,亿企科目!A:H,6,0)),VLOOKUP(H7,亿企科目!A:G,6,0)) -> 1002 | N7: =IFERROR(IF(H7="1002","银行账户",IF(H7="1123","供应商",VLOOKUP(I7,亿企科目!A:H,8,0))),"") -> 银行账户 | O7: =IF(N7=0,IF(M7="1002",K7,""),_xlfn.TEXTAFTER(E7,"-",-1)) -> 工商银行3066 | P7: =VLOOKUP(A7,账簿!B:C,2,0) -> 002022 | Q7: =VLOOKUP(P7,账簿!A:B,2,0) -> 昌邑泓澄水业有限公司 | W7: =X7&AB7&AD7 -> 0020222026-04-203 | X7: =P7 -> 002022 | Y7: =X7 -> 002022 | Z7: =Q7 -> 昌邑泓澄水业有限公司 | AA7: =LEFT(B7,7) -> 2026-04 | AB7: =B7 -> 2026-04-20 | AC7: 记 | AD7: =VALUE(_xlfn.TEXTAFTER(C7,"-")) -> 3 | AE7: =D7 -> 海洋水业公司并购,青岛天合易辉贸易有限公司 | AF7: 谭雅心 | AG7: 谭雅心 | AN7: =M7 -> 1002 | AP7: =D7 -> 海洋水业公司并购,青岛天合易辉贸易有限公司 | AQ7: CNY | AR7: =F7 | AS7: =G7 -> 14285900 | AT7: 01 | AU7: * | AV7: 1 | AW7: =AR7 | AX7: =AS7 -> 14285900 | BQ7: =IF(N7="项目",VLOOKUP(O7,项目!B:C,2,0),IF(K7="空项目",VLOOKUP(K7,项目!B:C,2,0),"")) | BR7: =IFERROR(VLOOKUP(BQ7,项目!A:B,2,0),"") | BU7: =IF(N7="供应商",VLOOKUP(O7,供应商!B:C,2,0),"") | BV7: =IFERROR(VLOOKUP(BU7,供应商!A:B,2,0),"") | BW7: =IF(N7="客户",VLOOKUP(O7,客户!B:C,2,0),"") | BX7: =IFERROR(VLOOKUP(BW7,客户!A:B,2,0),"") | CU7: =IF(N7="费用项目",VLOOKUP(O7,费用项目!B:C,2,0),"") | CV7: =IFERROR(VLOOKUP(CU7,费用项目!A:B,2,0),"") | CW7: =IF(N7="银行账户",VLOOKUP(O7,银行变二级!B:C,2,0),"") -> 工商银行3066 | CX7: =IFERROR(VLOOKUP(O7,银行变二级!A:B,2,0),"") -> 工商银行3066
A8: 昌邑泓澄水业有限公司 | B8: 2026-04-20 | C8: 记-004 | D8: 海洋水业公司并购,范光华 | E8: 151101 长期股权投资-投资成本-范光华 | F8: 5714100 | H8: =LEFT(E8,4) -> 1511 | I8: =IFERROR(LEFT(E8,FIND(" ",E8)-1),E8) -> 151101 | J8: =LEFT(MID(E8,FIND(" ",E8)+1,LEN(E8)),FIND("-",MID(E8,FIND(" ",E8)+1,LEN(E8))&"-")-1) -> 长期股权投资 | K8: =IFERROR(MID(MID(E8,FIND(" ",E8)+1,LEN(E8)),FIND("-",MID(E8,FIND(" ",E8)+1,LEN(E8)))+1,IFERROR(FIND("-",MID(E8,FIND(" ",E8)+1,LEN(E8)),FIND("-",MID(E8,FIND(" ",E8)+1,LEN(E8)))+1),LEN(MID(E8,FIND(" ",E8)+1,LEN(E8)))+1)-FIND("-",MID(E8,FIND(" ",E8)+1,LEN(E8)))-1),"") -> 投资成本 | L8: =IFERROR(MID(MID(E8,FIND(" ",E8)+1,LEN(E8)),FIND("-",MID(E8,FIND(" ",E8)+1,LEN(E8)),FIND("-",MID(E8,FIND(" ",E8)+1,LEN(E8)))+1)+1,LEN(E8)),"") -> 范光华 | M8: =IFERROR(IF(H8="1002",1002,VLOOKUP(I8,亿企科目!A:H,6,0)),VLOOKUP(H8,亿企科目!A:G,6,0)) -> 151101 | N8: =IFERROR(IF(H8="1002","银行账户",IF(H8="1123","供应商",VLOOKUP(I8,亿企科目!A:H,8,0))),"") -> 客户 | O8: =IF(N8=0,IF(M8="1002",K8,""),_xlfn.TEXTAFTER(E8,"-",-1)) -> 范光华 | P8: =VLOOKUP(A8,账簿!B:C,2,0) -> 002022 | Q8: =VLOOKUP(P8,账簿!A:B,2,0) -> 昌邑泓澄水业有限公司 | W8: =X8&AB8&AD8 -> 0020222026-04-204 | X8: =P8 -> 002022 | Y8: =X8 -> 002022 | Z8: =Q8 -> 昌邑泓澄水业有限公司 | AA8: =LEFT(B8,7) -> 2026-04 | AB8: =B8 -> 2026-04-20 | AC8: 记 | AD8: =VALUE(_xlfn.TEXTAFTER(C8,"-")) -> 4 | AE8: =D8 -> 海洋水业公司并购,范光华 | AF8: 谭雅心 | AG8: 谭雅心 | AN8: =M8 -> 151101 | AP8: =D8 -> 海洋水业公司并购,范光华 | AQ8: CNY | AR8: =F8 -> 5714100 | AS8: =G8 | AT8: 01 | AU8: * | AV8: 1 | AW8: =AR8 -> 5714100 | AX8: =AS8 | BQ8: =IF(N8="项目",VLOOKUP(O8,项目!B:C,2,0),IF(K8="空项目",VLOOKUP(K8,项目!B:C,2,0),"")) | BR8: =IFERROR(VLOOKUP(BQ8,项目!A:B,2,0),"") | BU8: =IF(N8="供应商",VLOOKUP(O8,供应商!B:C,2,0),"") | BV8: =IFERROR(VLOOKUP(BU8,供应商!A:B,2,0),"") | BW8: =IF(N8="客户",VLOOKUP(O8,客户!B:C,2,0),"") -> 0030001 | BX8: =IFERROR(VLOOKUP(BW8,客户!A:B,2,0),"") -> 范光华 | CU8: =IF(N8="费用项目",VLOOKUP(O8,费用项目!B:C,2,0),"") | CV8: =IFERROR(VLOOKUP(CU8,费用项目!A:B,2,0),"") | CW8: =IF(N8="银行账户",VLOOKUP(O8,银行变二级!B:C,2,0),"") | CX8: =IFERROR(VLOOKUP(O8,银行变二级!A:B,2,0),"")
A9: 昌邑泓澄水业有限公司 | B9: 2026-04-20 | C9: 记-004 | D9: 海洋水业公司并购,范光华 | E9: 100201 银行存款-工商银行3066 | G9: 5714100 | H9: =LEFT(E9,4) -> 1002 | I9: =IFERROR(LEFT(E9,FIND(" ",E9)-1),E9) -> 100201 | J9: =LEFT(MID(E9,FIND(" ",E9)+1,LEN(E9)),FIND("-",MID(E9,FIND(" ",E9)+1,LEN(E9))&"-")-1) -> 银行存款 | K9: =IFERROR(MID(MID(E9,FIND(" ",E9)+1,LEN(E9)),FIND("-",MID(E9,FIND(" ",E9)+1,LEN(E9)))+1,IFERROR(FIND("-",MID(E9,FIND(" ",E9)+1,LEN(E9)),FIND("-",MID(E9,FIND(" ",E9)+1,LEN(E9)))+1),LEN(MID(E9,FIND(" ",E9)+1,LEN(E9)))+1)-FIND("-",MID(E9,FIND(" ",E9)+1,LEN(E9)))-1),"") -> 工商银行3066 | L9: =IFERROR(MID(MID(E9,FIND(" ",E9)+1,LEN(E9)),FIND("-",MID(E9,FIND(" ",E9)+1,LEN(E9)),FIND("-",MID(E9,FIND(" ",E9)+1,LEN(E9)))+1)+1,LEN(E9)),"") | M9: =IFERROR(IF(H9="1002",1002,VLOOKUP(I9,亿企科目!A:H,6,0)),VLOOKUP(H9,亿企科目!A:G,6,0)) -> 1002 | N9: =IFERROR(IF(H9="1002","银行账户",IF(H9="1123","供应商",VLOOKUP(I9,亿企科目!A:H,8,0))),"") -> 银行账户 | O9: =IF(N9=0,IF(M9="1002",K9,""),_xlfn.TEXTAFTER(E9,"-",-1)) -> 工商银行3066 | P9: =VLOOKUP(A9,账簿!B:C,2,0) -> 002022 | Q9: =VLOOKUP(P9,账簿!A:B,2,0) -> 昌邑泓澄水业有限公司 | W9: =X9&AB9&AD9 -> 0020222026-04-204 | X9: =P9 -> 002022 | Y9: =X9 -> 002022 | Z9: =Q9 -> 昌邑泓澄水业有限公司 | AA9: =LEFT(B9,7) -> 2026-04 | AB9: =B9 -> 2026-04-20 | AC9: 记 | AD9: =VALUE(_xlfn.TEXTAFTER(C9,"-")) -> 4 | AE9: =D9 -> 海洋水业公司并购,范光华 | AF9: 谭雅心 | AG9: 谭雅心 | AN9: =M9 -> 1002 | AP9: =D9 -> 海洋水业公司并购,范光华 | AQ9: CNY | AR9: =F9 | AS9: =G9 -> 5714100 | AT9: 01 | AU9: * | AV9: 1 | AW9: =AR9 | AX9: =AS9 -> 5714100 | BQ9: =IF(N9="项目",VLOOKUP(O9,项目!B:C,2,0),IF(K9="空项目",VLOOKUP(K9,项目!B:C,2,0),"")) | BR9: =IFERROR(VLOOKUP(BQ9,项目!A:B,2,0),"") | BU9: =IF(N9="供应商",VLOOKUP(O9,供应商!B:C,2,0),"") | BV9: =IFERROR(VLOOKUP(BU9,供应商!A:B,2,0),"") | BW9: =IF(N9="客户",VLOOKUP(O9,客户!B:C,2,0),"") | BX9: =IFERROR(VLOOKUP(BW9,客户!A:B,2,0),"") | CU9: =IF(N9="费用项目",VLOOKUP(O9,费用项目!B:C,2,0),"") | CV9: =IFERROR(VLOOKUP(CU9,费用项目!A:B,2,0),"") | CW9: =IF(N9="银行账户",VLOOKUP(O9,银行变二级!B:C,2,0),"") -> 工商银行3066 | CX9: =IFERROR(VLOOKUP(O9,银行变二级!A:B,2,0),"") -> 工商银行3066
A10: 昌邑泓澄水业有限公司 | B10: 2026-04-21 | C10: 记-005 | D10: 对公贷款利息支付,中长期并购贷款利息收入 | E10: 6603 财务费用-利息支出 | F10: 370500.01 | H10: =LEFT(E10,4) -> 6603 | I10: =IFERROR(LEFT(E10,FIND(" ",E10)-1),E10) -> 6603 | J10: =LEFT(MID(E10,FIND(" ",E10)+1,LEN(E10)),FIND("-",MID(E10,FIND(" ",E10)+1,LEN(E10))&"-")-1) -> 财务费用 | K10: =IFERROR(MID(MID(E10,FIND(" ",E10)+1,LEN(E10)),FIND("-",MID(E10,FIND(" ",E10)+1,LEN(E10)))+1,IFERROR(FIND("-",MID(E10,FIND(" ",E10)+1,LEN(E10)),FIND("-",MID(E10,FIND(" ",E10)+1,LEN(E10)))+1),LEN(MID(E10,FIND(" ",E10)+1,LEN(E10)))+1)-FIND("-",MID(E10,FIND(" ",E10)+1,LEN(E10)))-1),"") -> 利息支出 | L10: =IFERROR(MID(MID(E10,FIND(" ",E10)+1,LEN(E10)),FIND("-",MID(E10,FIND(" ",E10)+1,LEN(E10)),FIND("-",MID(E10,FIND(" ",E10)+1,LEN(E10)))+1)+1,LEN(E10)),"") | M10: =IFERROR(IF(H10="1002",1002,VLOOKUP(I10,亿企科目!A:H,6,0)),VLOOKUP(H10,亿企科目!A:G,6,0)) -> 6603 | N10: =IFERROR(IF(H10="1002","银行账户",IF(H10="1123","供应商",VLOOKUP(I10,亿企科目!A:H,8,0))),"") -> 费用项目 | O10: =IF(N10=0,IF(M10="1002",K10,""),_xlfn.TEXTAFTER(E10,"-",-1)) -> 利息支出 | P10: =VLOOKUP(A10,账簿!B:C,2,0) -> 002022 | Q10: =VLOOKUP(P10,账簿!A:B,2,0) -> 昌邑泓澄水业有限公司 | W10: =X10&AB10&AD10 -> 0020222026-04-215 | X10: =P10 -> 002022 | Y10: =X10 -> 002022 | Z10: =Q10 -> 昌邑泓澄水业有限公司 | AA10: =LEFT(B10,7) -> 2026-04 | AB10: =B10 -> 2026-04-21 | AC10: 记 | AD10: =VALUE(_xlfn.TEXTAFTER(C10,"-")) -> 5 | AE10: =D10 -> 对公贷款利息支付,中长期并购贷款利息收入 | AF10: 谭雅心 | AG10: 谭雅心 | AN10: =M10 -> 6603 | AP10: =D10 -> 对公贷款利息支付,中长期并购贷款利息收入 | AQ10: CNY | AR10: =F10 -> 370500.01 | AS10: =G10 | AT10: 01 | AU10: * | AV10: 1 | AW10: =AR10 -> 370500.01 | AX10: =AS10 | BQ10: =IF(N10="项目",VLOOKUP(O10,项目!B:C,2,0),IF(K10="空项目",VLOOKUP(K10,项目!B:C,2,0),"")) | BR10: =IFERROR(VLOOKUP(BQ10,项目!A:B,2,0),"") | BU10: =IF(N10="供应商",VLOOKUP(O10,供应商!B:C,2,0),"") | BV10: =IFERROR(VLOOKUP(BU10,供应商!A:B,2,0),"") | BW10: =IF(N10="客户",VLOOKUP(O10,客户!B:C,2,0),"") | BX10: =IFERROR(VLOOKUP(BW10,客户!A:B,2,0),"") | CU10: =IF(N10="费用项目",VLOOKUP(O10,费用项目!B:C,2,0),"") -> 660302 | CV10: =IFERROR(VLOOKUP(CU10,费用项目!A:B,2,0),"") -> 利息支出 | CW10: =IF(N10="银行账户",VLOOKUP(O10,银行变二级!B:C,2,0),"") | CX10: =IFERROR(VLOOKUP(O10,银行变二级!A:B,2,0),"")
A11: 昌邑泓澄水业有限公司 | B11: 2026-04-21 | C11: 记-005 | D11: 对公贷款利息支付,中长期并购贷款利息收入 | E11: 100201 银行存款-工商银行3066 | G11: 370500.01 | H11: =LEFT(E11,4) -> 1002 | I11: =IFERROR(LEFT(E11,FIND(" ",E11)-1),E11) -> 100201 | J11: =LEFT(MID(E11,FIND(" ",E11)+1,LEN(E11)),FIND("-",MID(E11,FIND(" ",E11)+1,LEN(E11))&"-")-1) -> 银行存款 | K11: =IFERROR(MID(MID(E11,FIND(" ",E11)+1,LEN(E11)),FIND("-",MID(E11,FIND(" ",E11)+1,LEN(E11)))+1,IFERROR(FIND("-",MID(E11,FIND(" ",E11)+1,LEN(E11)),FIND("-",MID(E11,FIND(" ",E11)+1,LEN(E11)))+1),LEN(MID(E11,FIND(" ",E11)+1,LEN(E11)))+1)-FIND("-",MID(E11,FIND(" ",E11)+1,LEN(E11)))-1),"") -> 工商银行3066 | L11: =IFERROR(MID(MID(E11,FIND(" ",E11)+1,LEN(E11)),FIND("-",MID(E11,FIND(" ",E11)+1,LEN(E11)),FIND("-",MID(E11,FIND(" ",E11)+1,LEN(E11)))+1)+1,LEN(E11)),"") | M11: =IFERROR(IF(H11="1002",1002,VLOOKUP(I11,亿企科目!A:H,6,0)),VLOOKUP(H11,亿企科目!A:G,6,0)) -> 1002 | N11: =IFERROR(IF(H11="1002","银行账户",IF(H11="1123","供应商",VLOOKUP(I11,亿企科目!A:H,8,0))),"") -> 银行账户 | O11: =IF(N11=0,IF(M11="1002",K11,""),_xlfn.TEXTAFTER(E11,"-",-1)) -> 工商银行3066 | P11: =VLOOKUP(A11,账簿!B:C,2,0) -> 002022 | Q11: =VLOOKUP(P11,账簿!A:B,2,0) -> 昌邑泓澄水业有限公司 | W11: =X11&AB11&AD11 -> 0020222026-04-215 | X11: =P11 -> 002022 | Y11: =X11 -> 002022 | Z11: =Q11 -> 昌邑泓澄水业有限公司 | AA11: =LEFT(B11,7) -> 2026-04 | AB11: =B11 -> 2026-04-21 | AC11: 记 | AD11: =VALUE(_xlfn.TEXTAFTER(C11,"-")) -> 5 | AE11: =D11 -> 对公贷款利息支付,中长期并购贷款利息收入 | AF11: 谭雅心 | AG11: 谭雅心 | AN11: =M11 -> 1002 | AP11: =D11 -> 对公贷款利息支付,中长期并购贷款利息收入 | AQ11: CNY | AR11: =F11 | AS11: =G11 -> 370500.01 | AT11: 01 | AU11: * | AV11: 1 | AW11: =AR11 | AX11: =AS11 -> 370500.01 | BQ11: =IF(N11="项目",VLOOKUP(O11,项目!B:C,2,0),IF(K11="空项目",VLOOKUP(K11,项目!B:C,2,0),"")) | BR11: =IFERROR(VLOOKUP(BQ11,项目!A:B,2,0),"") | BU11: =IF(N11="供应商",VLOOKUP(O11,供应商!B:C,2,0),"") | BV11: =IFERROR(VLOOKUP(BU11,供应商!A:B,2,0),"") | BW11: =IF(N11="客户",VLOOKUP(O11,客户!B:C,2,0),"") | BX11: =IFERROR(VLOOKUP(BW11,客户!A:B,2,0),"") | CU11: =IF(N11="费用项目",VLOOKUP(O11,费用项目!B:C,2,0),"") | CV11: =IFERROR(VLOOKUP(CU11,费用项目!A:B,2,0),"") | CW11: =IF(N11="银行账户",VLOOKUP(O11,银行变二级!B:C,2,0),"") -> 工商银行3066 | CX11: =IFERROR(VLOOKUP(O11,银行变二级!A:B,2,0),"") -> 工商银行3066
A12: 昌邑泓澄水业有限公司 | B12: 2026-04-21 | C12: 记-006 | D12: 跨行汇款手续费 | E12: 6603 财务费用-手续费 | F12: 314.28 | H12: =LEFT(E12,4) -> 6603 | I12: =IFERROR(LEFT(E12,FIND(" ",E12)-1),E12) -> 6603 | J12: =LEFT(MID(E12,FIND(" ",E12)+1,LEN(E12)),FIND("-",MID(E12,FIND(" ",E12)+1,LEN(E12))&"-")-1) -> 财务费用 | K12: =IFERROR(MID(MID(E12,FIND(" ",E12)+1,LEN(E12)),FIND("-",MID(E12,FIND(" ",E12)+1,LEN(E12)))+1,IFERROR(FIND("-",MID(E12,FIND(" ",E12)+1,LEN(E12)),FIND("-",MID(E12,FIND(" ",E12)+1,LEN(E12)))+1),LEN(MID(E12,FIND(" ",E12)+1,LEN(E12)))+1)-FIND("-",MID(E12,FIND(" ",E12)+1,LEN(E12)))-1),"") -> 手续费 | L12: =IFERROR(MID(MID(E12,FIND(" ",E12)+1,LEN(E12)),FIND("-",MID(E12,FIND(" ",E12)+1,LEN(E12)),FIND("-",MID(E12,FIND(" ",E12)+1,LEN(E12)))+1)+1,LEN(E12)),"") | M12: =IFERROR(IF(H12="1002",1002,VLOOKUP(I12,亿企科目!A:H,6,0)),VLOOKUP(H12,亿企科目!A:G,6,0)) -> 6603 | N12: =IFERROR(IF(H12="1002","银行账户",IF(H12="1123","供应商",VLOOKUP(I12,亿企科目!A:H,8,0))),"") -> 费用项目 | O12: =IF(N12=0,IF(M12="1002",K12,""),_xlfn.TEXTAFTER(E12,"-",-1)) -> 手续费 | P12: =VLOOKUP(A12,账簿!B:C,2,0) -> 002022 | Q12: =VLOOKUP(P12,账簿!A:B,2,0) -> 昌邑泓澄水业有限公司 | W12: =X12&AB12&AD12 -> 0020222026-04-216 | X12: =P12 -> 002022 | Y12: =X12 -> 002022 | Z12: =Q12 -> 昌邑泓澄水业有限公司 | AA12: =LEFT(B12,7) -> 2026-04 | AB12: =B12 -> 2026-04-21 | AC12: 记 | AD12: =VALUE(_xlfn.TEXTAFTER(C12,"-")) -> 6 | AE12: =D12 -> 跨行汇款手续费 | AF12: 谭雅心 | AG12: 谭雅心 | AN12: =M12 -> 6603 | AP12: =D12 -> 跨行汇款手续费 | AQ12: CNY | AR12: =F12 -> 314.28 | AS12: =G12 | AT12: 01 | AU12: * | AV12: 1 | AW12: =AR12 -> 314.28 | AX12: =AS12 | BQ12: =IF(N12="项目",VLOOKUP(O12,项目!B:C,2,0),IF(K12="空项目",VLOOKUP(K12,项目!B:C,2,0),"")) | BR12: =IFERROR(VLOOKUP(BQ12,项目!A:B,2,0),"") | BU12: =IF(N12="供应商",VLOOKUP(O12,供应商!B:C,2,0),"") | BV12: =IFERROR(VLOOKUP(BU12,供应商!A:B,2,0),"") | BW12: =IF(N12="客户",VLOOKUP(O12,客户!B:C,2,0),"") | BX12: =IFERROR(VLOOKUP(BW12,客户!A:B,2,0),"") | CU12: =IF(N12="费用项目",VLOOKUP(O12,费用项目!B:C,2,0),"") -> 660304 | CV12: =IFERROR(VLOOKUP(CU12,费用项目!A:B,2,0),"") -> 手续费 | CW12: =IF(N12="银行账户",VLOOKUP(O12,银行变二级!B:C,2,0),"") | CX12: =IFERROR(VLOOKUP(O12,银行变二级!A:B,2,0),"")
A13: 昌邑泓澄水业有限公司 | B13: 2026-04-21 | C13: 记-006 | D13: 跨行汇款手续费 | E13: 100201 银行存款-工商银行3066 | G13: 314.28 | H13: =LEFT(E13,4) -> 1002 | I13: =IFERROR(LEFT(E13,FIND(" ",E13)-1),E13) -> 100201 | J13: =LEFT(MID(E13,FIND(" ",E13)+1,LEN(E13)),FIND("-",MID(E13,FIND(" ",E13)+1,LEN(E13))&"-")-1) -> 银行存款 | K13: =IFERROR(MID(MID(E13,FIND(" ",E13)+1,LEN(E13)),FIND("-",MID(E13,FIND(" ",E13)+1,LEN(E13)))+1,IFERROR(FIND("-",MID(E13,FIND(" ",E13)+1,LEN(E13)),FIND("-",MID(E13,FIND(" ",E13)+1,LEN(E13)))+1),LEN(MID(E13,FIND(" ",E13)+1,LEN(E13)))+1)-FIND("-",MID(E13,FIND(" ",E13)+1,LEN(E13)))-1),"") -> 工商银行3066 | L13: =IFERROR(MID(MID(E13,FIND(" ",E13)+1,LEN(E13)),FIND("-",MID(E13,FIND(" ",E13)+1,LEN(E13)),FIND("-",MID(E13,FIND(" ",E13)+1,LEN(E13)))+1)+1,LEN(E13)),"") | M13: =IFERROR(IF(H13="1002",1002,VLOOKUP(I13,亿企科目!A:H,6,0)),VLOOKUP(H13,亿企科目!A:G,6,0)) -> 1002 | N13: =IFERROR(IF(H13="1002","银行账户",IF(H13="1123","供应商",VLOOKUP(I13,亿企科目!A:H,8,0))),"") -> 银行账户 | O13: =IF(N13=0,IF(M13="1002",K13,""),_xlfn.TEXTAFTER(E13,"-",-1)) -> 工商银行3066 | P13: =VLOOKUP(A13,账簿!B:C,2,0) -> 002022 | Q13: =VLOOKUP(P13,账簿!A:B,2,0) -> 昌邑泓澄水业有限公司 | W13: =X13&AB13&AD13 -> 0020222026-04-216 | X13: =P13 -> 002022 | Y13: =X13 -> 002022 | Z13: =Q13 -> 昌邑泓澄水业有限公司 | AA13: =LEFT(B13,7) -> 2026-04 | AB13: =B13 -> 2026-04-21 | AC13: 记 | AD13: =VALUE(_xlfn.TEXTAFTER(C13,"-")) -> 6 | AE13: =D13 -> 跨行汇款手续费 | AF13: 谭雅心 | AG13: 谭雅心 | AN13: =M13 -> 1002 | AP13: =D13 -> 跨行汇款手续费 | AQ13: CNY | AR13: =F13 | AS13: =G13 -> 314.28 | AT13: 01 | AU13: * | AV13: 1 | AW13: =AR13 | AX13: =AS13 -> 314.28 | BQ13: =IF(N13="项目",VLOOKUP(O13,项目!B:C,2,0),IF(K13="空项目",VLOOKUP(K13,项目!B:C,2,0),"")) | BR13: =IFERROR(VLOOKUP(BQ13,项目!A:B,2,0),"") | BU13: =IF(N13="供应商",VLOOKUP(O13,供应商!B:C,2,0),"") | BV13: =IFERROR(VLOOKUP(BU13,供应商!A:B,2,0),"") | BW13: =IF(N13="客户",VLOOKUP(O13,客户!B:C,2,0),"") | BX13: =IFERROR(VLOOKUP(BW13,客户!A:B,2,0),"") | CU13: =IF(N13="费用项目",VLOOKUP(O13,费用项目!B:C,2,0),"") | CV13: =IFERROR(VLOOKUP(CU13,费用项目!A:B,2,0),"") | CW13: =IF(N13="银行账户",VLOOKUP(O13,银行变二级!B:C,2,0),"") -> 工商银行3066 | CX13: =IFERROR(VLOOKUP(O13,银行变二级!A:B,2,0),"") -> 工商银行3066
A14: 昌邑泓澄水业有限公司 | B14: 2026-04-30 | C14: 记-007 | D14: 往来款,昌邑市城投股权投资管理有限公司 | E14: 122108 其他应收款-单位-昌邑市城投股权投资管理有限公司 | F14: 26000000 | H14: =LEFT(E14,4) -> 1221 | I14: =IFERROR(LEFT(E14,FIND(" ",E14)-1),E14) -> 122108 | J14: =LEFT(MID(E14,FIND(" ",E14)+1,LEN(E14)),FIND("-",MID(E14,FIND(" ",E14)+1,LEN(E14))&"-")-1) -> 其他应收款 | K14: =IFERROR(MID(MID(E14,FIND(" ",E14)+1,LEN(E14)),FIND("-",MID(E14,FIND(" ",E14)+1,LEN(E14)))+1,IFERROR(FIND("-",MID(E14,FIND(" ",E14)+1,LEN(E14)),FIND("-",MID(E14,FIND(" ",E14)+1,LEN(E14)))+1),LEN(MID(E14,FIND(" ",E14)+1,LEN(E14)))+1)-FIND("-",MID(E14,FIND(" ",E14)+1,LEN(E14)))-1),"") -> 单位 | L14: =IFERROR(MID(MID(E14,FIND(" ",E14)+1,LEN(E14)),FIND("-",MID(E14,FIND(" ",E14)+1,LEN(E14)),FIND("-",MID(E14,FIND(" ",E14)+1,LEN(E14)))+1)+1,LEN(E14)),"") -> 昌邑市城投股权投资管理有限公司 | M14: =IFERROR(IF(H14="1002",1002,VLOOKUP(I14,亿企科目!A:H,6,0)),VLOOKUP(H14,亿企科目!A:G,6,0)) -> 122102 | N14: =IFERROR(IF(H14="1002","银行账户",IF(H14="1123","供应商",VLOOKUP(I14,亿企科目!A:H,8,0))),"") -> 客户 | O14: =IF(N14=0,IF(M14="1002",K14,""),_xlfn.TEXTAFTER(E14,"-",-1)) -> 昌邑市城投股权投资管理有限公司 | P14: =VLOOKUP(A14,账簿!B:C,2,0) -> 002022 | Q14: =VLOOKUP(P14,账簿!A:B,2,0) -> 昌邑泓澄水业有限公司 | W14: =X14&AB14&AD14 -> 0020222026-04-307 | X14: =P14 -> 002022 | Y14: =X14 -> 002022 | Z14: =Q14 -> 昌邑泓澄水业有限公司 | AA14: =LEFT(B14,7) -> 2026-04 | AB14: =B14 -> 2026-04-30 | AC14: 记 | AD14: =VALUE(_xlfn.TEXTAFTER(C14,"-")) -> 7 | AE14: =D14 -> 往来款,昌邑市城投股权投资管理有限公司 | AF14: 谭雅心 | AG14: 谭雅心 | AN14: =M14 -> 122102 | AP14: =D14 -> 往来款,昌邑市城投股权投资管理有限公司 | AQ14: CNY | AR14: =F14 -> 26000000 | AS14: =G14 | AT14: 01 | AU14: * | AV14: 1 | AW14: =AR14 -> 26000000 | AX14: =AS14 | BQ14: =IF(N14="项目",VLOOKUP(O14,项目!B:C,2,0),IF(K14="空项目",VLOOKUP(K14,项目!B:C,2,0),"")) | BR14: =IFERROR(VLOOKUP(BQ14,项目!A:B,2,0),"") | BU14: =IF(N14="供应商",VLOOKUP(O14,供应商!B:C,2,0),"") | BV14: =IFERROR(VLOOKUP(BU14,供应商!A:B,2,0),"") | BW14: =IF(N14="客户",VLOOKUP(O14,客户!B:C,2,0),"") -> 002008 | BX14: =IFERROR(VLOOKUP(BW14,客户!A:B,2,0),"") -> 昌邑市城投股权投资管理有限公司 | CU14: =IF(N14="费用项目",VLOOKUP(O14,费用项目!B:C,2,0),"") | CV14: =IFERROR(VLOOKUP(CU14,费用项目!A:B,2,0),"") | CW14: =IF(N14="银行账户",VLOOKUP(O14,银行变二级!B:C,2,0),"") | CX14: =IFERROR(VLOOKUP(O14,银行变二级!A:B,2,0),"")
A15: 昌邑泓澄水业有限公司 | B15: 2026-04-30 | C15: 记-007 | D15: 往来款,昌邑市城投股权投资管理有限公司 | E15: 100201 银行存款-工商银行3066 | G15: 26000000 | H15: =LEFT(E15,4) -> 1002 | I15: =IFERROR(LEFT(E15,FIND(" ",E15)-1),E15) -> 100201 | J15: =LEFT(MID(E15,FIND(" ",E15)+1,LEN(E15)),FIND("-",MID(E15,FIND(" ",E15)+1,LEN(E15))&"-")-1) -> 银行存款 | K15: =IFERROR(MID(MID(E15,FIND(" ",E15)+1,LEN(E15)),FIND("-",MID(E15,FIND(" ",E15)+1,LEN(E15)))+1,IFERROR(FIND("-",MID(E15,FIND(" ",E15)+1,LEN(E15)),FIND("-",MID(E15,FIND(" ",E15)+1,LEN(E15)))+1),LEN(MID(E15,FIND(" ",E15)+1,LEN(E15)))+1)-FIND("-",MID(E15,FIND(" ",E15)+1,LEN(E15)))-1),"") -> 工商银行3066 | L15: =IFERROR(MID(MID(E15,FIND(" ",E15)+1,LEN(E15)),FIND("-",MID(E15,FIND(" ",E15)+1,LEN(E15)),FIND("-",MID(E15,FIND(" ",E15)+1,LEN(E15)))+1)+1,LEN(E15)),"") | M15: =IFERROR(IF(H15="1002",1002,VLOOKUP(I15,亿企科目!A:H,6,0)),VLOOKUP(H15,亿企科目!A:G,6,0)) -> 1002 | N15: =IFERROR(IF(H15="1002","银行账户",IF(H15="1123","供应商",VLOOKUP(I15,亿企科目!A:H,8,0))),"") -> 银行账户 | O15: =IF(N15=0,IF(M15="1002",K15,""),_xlfn.TEXTAFTER(E15,"-",-1)) -> 工商银行3066 | P15: =VLOOKUP(A15,账簿!B:C,2,0) -> 002022 | Q15: =VLOOKUP(P15,账簿!A:B,2,0) -> 昌邑泓澄水业有限公司 | W15: =X15&AB15&AD15 -> 0020222026-04-307 | X15: =P15 -> 002022 | Y15: =X15 -> 002022 | Z15: =Q15 -> 昌邑泓澄水业有限公司 | AA15: =LEFT(B15,7) -> 2026-04 | AB15: =B15 -> 2026-04-30 | AC15: 记 | AD15: =VALUE(_xlfn.TEXTAFTER(C15,"-")) -> 7 | AE15: =D15 -> 往来款,昌邑市城投股权投资管理有限公司 | AF15: 谭雅心 | AG15: 谭雅心 | AN15: =M15 -> 1002 | AP15: =D15 -> 往来款,昌邑市城投股权投资管理有限公司 | AQ15: CNY | AR15: =F15 | AS15: =G15 -> 26000000 | AT15: 01 | AU15: * | AV15: 1 | AW15: =AR15 | AX15: =AS15 -> 26000000 | BQ15: =IF(N15="项目",VLOOKUP(O15,项目!B:C,2,0),IF(K15="空项目",VLOOKUP(K15,项目!B:C,2,0),"")) | BR15: =IFERROR(VLOOKUP(BQ15,项目!A:B,2,0),"") | BU15: =IF(N15="供应商",VLOOKUP(O15,供应商!B:C,2,0),"") | BV15: =IFERROR(VLOOKUP(BU15,供应商!A:B,2,0),"") | BW15: =IF(N15="客户",VLOOKUP(O15,客户!B:C,2,0),"") | BX15: =IFERROR(VLOOKUP(BW15,客户!A:B,2,0),"") | CU15: =IF(N15="费用项目",VLOOKUP(O15,费用项目!B:C,2,0),"") | CV15: =IFERROR(VLOOKUP(CU15,费用项目!A:B,2,0),"") | CW15: =IF(N15="银行账户",VLOOKUP(O15,银行变二级!B:C,2,0),"") -> 工商银行3066 | CX15: =IFERROR(VLOOKUP(O15,银行变二级!A:B,2,0),"") -> 工商银行3066
A16: 昌邑泓澄水业有限公司 | B16: 2026-04-30 | C16: 记-008 | D16: 结转本月损益 | E16: 4103 本年利润 | F16: 370814.29 | H16: =LEFT(E16,4) -> 4103 | I16: =IFERROR(LEFT(E16,FIND(" ",E16)-1),E16) -> 4103 | J16: =LEFT(MID(E16,FIND(" ",E16)+1,LEN(E16)),FIND("-",MID(E16,FIND(" ",E16)+1,LEN(E16))&"-")-1) -> 本年利润 | K16: =IFERROR(MID(MID(E16,FIND(" ",E16)+1,LEN(E16)),FIND("-",MID(E16,FIND(" ",E16)+1,LEN(E16)))+1,IFERROR(FIND("-",MID(E16,FIND(" ",E16)+1,LEN(E16)),FIND("-",MID(E16,FIND(" ",E16)+1,LEN(E16)))+1),LEN(MID(E16,FIND(" ",E16)+1,LEN(E16)))+1)-FIND("-",MID(E16,FIND(" ",E16)+1,LEN(E16)))-1),"") | L16: =IFERROR(MID(MID(E16,FIND(" ",E16)+1,LEN(E16)),FIND("-",MID(E16,FIND(" ",E16)+1,LEN(E16)),FIND("-",MID(E16,FIND(" ",E16)+1,LEN(E16)))+1)+1,LEN(E16)),"") | M16: =IFERROR(IF(H16="1002",1002,VLOOKUP(I16,亿企科目!A:H,6,0)),VLOOKUP(H16,亿企科目!A:G,6,0)) -> 4103 | N16: =IFERROR(IF(H16="1002","银行账户",IF(H16="1123","供应商",VLOOKUP(I16,亿企科目!A:H,8,0))),"") -> 0 | O16: =IF(N16=0,IF(M16="1002",K16,""),_xlfn.TEXTAFTER(E16,"-",-1)) | P16: =VLOOKUP(A16,账簿!B:C,2,0) -> 002022 | Q16: =VLOOKUP(P16,账簿!A:B,2,0) -> 昌邑泓澄水业有限公司 | W16: =X16&AB16&AD16 -> 0020222026-04-308 | X16: =P16 -> 002022 | Y16: =X16 -> 002022 | Z16: =Q16 -> 昌邑泓澄水业有限公司 | AA16: =LEFT(B16,7) -> 2026-04 | AB16: =B16 -> 2026-04-30 | AC16: 记 | AD16: =VALUE(_xlfn.TEXTAFTER(C16,"-")) -> 8 | AE16: =D16 -> 结转本月损益 | AF16: 谭雅心 | AG16: 谭雅心 | AN16: =M16 -> 4103 | AP16: =D16 -> 结转本月损益 | AQ16: CNY | AR16: =F16 -> 370814.29 | AS16: =G16 | AT16: 01 | AU16: * | AV16: 1 | AW16: =AR16 -> 370814.29 | AX16: =AS16 | BQ16: =IF(N16="项目",VLOOKUP(O16,项目!B:C,2,0),IF(K16="空项目",VLOOKUP(K16,项目!B:C,2,0),"")) | BR16: =IFERROR(VLOOKUP(BQ16,项目!A:B,2,0),"") | BU16: =IF(N16="供应商",VLOOKUP(O16,供应商!B:C,2,0),"") | BV16: =IFERROR(VLOOKUP(BU16,供应商!A:B,2,0),"") | BW16: =IF(N16="客户",VLOOKUP(O16,客户!B:C,2,0),"") | BX16: =IFERROR(VLOOKUP(BW16,客户!A:B,2,0),"") | CU16: =IF(N16="费用项目",VLOOKUP(O16,费用项目!B:C,2,0),"") | CV16: =IFERROR(VLOOKUP(CU16,费用项目!A:B,2,0),"") | CW16: =IF(N16="银行账户",VLOOKUP(O16,银行变二级!B:C,2,0),"") | CX16: =IFERROR(VLOOKUP(O16,银行变二级!A:B,2,0),"")
A17: 昌邑泓澄水业有限公司 | B17: 2026-04-30 | C17: 记-008 | D17: 结转本月损益 | E17: 6603 财务费用-利息支出 | G17: 370500.01 | H17: =LEFT(E17,4) -> 6603 | I17: =IFERROR(LEFT(E17,FIND(" ",E17)-1),E17) -> 6603 | J17: =LEFT(MID(E17,FIND(" ",E17)+1,LEN(E17)),FIND("-",MID(E17,FIND(" ",E17)+1,LEN(E17))&"-")-1) -> 财务费用 | K17: =IFERROR(MID(MID(E17,FIND(" ",E17)+1,LEN(E17)),FIND("-",MID(E17,FIND(" ",E17)+1,LEN(E17)))+1,IFERROR(FIND("-",MID(E17,FIND(" ",E17)+1,LEN(E17)),FIND("-",MID(E17,FIND(" ",E17)+1,LEN(E17)))+1),LEN(MID(E17,FIND(" ",E17)+1,LEN(E17)))+1)-FIND("-",MID(E17,FIND(" ",E17)+1,LEN(E17)))-1),"") -> 利息支出 | L17: =IFERROR(MID(MID(E17,FIND(" ",E17)+1,LEN(E17)),FIND("-",MID(E17,FIND(" ",E17)+1,LEN(E17)),FIND("-",MID(E17,FIND(" ",E17)+1,LEN(E17)))+1)+1,LEN(E17)),"") | M17: =IFERROR(IF(H17="1002",1002,VLOOKUP(I17,亿企科目!A:H,6,0)),VLOOKUP(H17,亿企科目!A:G,6,0)) -> 6603 | N17: =IFERROR(IF(H17="1002","银行账户",IF(H17="1123","供应商",VLOOKUP(I17,亿企科目!A:H,8,0))),"") -> 费用项目 | O17: =IF(N17=0,IF(M17="1002",K17,""),_xlfn.TEXTAFTER(E17,"-",-1)) -> 利息支出 | P17: =VLOOKUP(A17,账簿!B:C,2,0) -> 002022 | Q17: =VLOOKUP(P17,账簿!A:B,2,0) -> 昌邑泓澄水业有限公司 | W17: =X17&AB17&AD17 -> 0020222026-04-308 | X17: =P17 -> 002022 | Y17: =X17 -> 002022 | Z17: =Q17 -> 昌邑泓澄水业有限公司 | AA17: =LEFT(B17,7) -> 2026-04 | AB17: =B17 -> 2026-04-30 | AC17: 记 | AD17: =VALUE(_xlfn.TEXTAFTER(C17,"-")) -> 8 | AE17: =D17 -> 结转本月损益 | AF17: 谭雅心 | AG17: 谭雅心 | AN17: =M17 -> 6603 | AP17: =D17 -> 结转本月损益 | AQ17: CNY | AR17: =F17 | AS17: =G17 -> 370500.01 | AT17: 01 | AU17: * | AV17: 1 | AW17: =AR17 | AX17: =AS17 -> 370500.01 | BQ17: =IF(N17="项目",VLOOKUP(O17,项目!B:C,2,0),IF(K17="空项目",VLOOKUP(K17,项目!B:C,2,0),"")) | BR17: =IFERROR(VLOOKUP(BQ17,项目!A:B,2,0),"") | BU17: =IF(N17="供应商",VLOOKUP(O17,供应商!B:C,2,0),"") | BV17: =IFERROR(VLOOKUP(BU17,供应商!A:B,2,0),"") | BW17: =IF(N17="客户",VLOOKUP(O17,客户!B:C,2,0),"") | BX17: =IFERROR(VLOOKUP(BW17,客户!A:B,2,0),"") | CU17: =IF(N17="费用项目",VLOOKUP(O17,费用项目!B:C,2,0),"") -> 660302 | CV17: =IFERROR(VLOOKUP(CU17,费用项目!A:B,2,0),"") -> 利息支出 | CW17: =IF(N17="银行账户",VLOOKUP(O17,银行变二级!B:C,2,0),"") | CX17: =IFERROR(VLOOKUP(O17,银行变二级!A:B,2,0),"")
A18: 昌邑泓澄水业有限公司 | B18: 2026-04-30 | C18: 记-008 | D18: 结转本月损益 | E18: 6603 财务费用-手续费 | G18: 314.28 | H18: =LEFT(E18,4) -> 6603 | I18: =IFERROR(LEFT(E18,FIND(" ",E18)-1),E18) -> 6603 | J18: =LEFT(MID(E18,FIND(" ",E18)+1,LEN(E18)),FIND("-",MID(E18,FIND(" ",E18)+1,LEN(E18))&"-")-1) -> 财务费用 | K18: =IFERROR(MID(MID(E18,FIND(" ",E18)+1,LEN(E18)),FIND("-",MID(E18,FIND(" ",E18)+1,LEN(E18)))+1,IFERROR(FIND("-",MID(E18,FIND(" ",E18)+1,LEN(E18)),FIND("-",MID(E18,FIND(" ",E18)+1,LEN(E18)))+1),LEN(MID(E18,FIND(" ",E18)+1,LEN(E18)))+1)-FIND("-",MID(E18,FIND(" ",E18)+1,LEN(E18)))-1),"") -> 手续费 | L18: =IFERROR(MID(MID(E18,FIND(" ",E18)+1,LEN(E18)),FIND("-",MID(E18,FIND(" ",E18)+1,LEN(E18)),FIND("-",MID(E18,FIND(" ",E18)+1,LEN(E18)))+1)+1,LEN(E18)),"") | M18: =IFERROR(IF(H18="1002",1002,VLOOKUP(I18,亿企科目!A:H,6,0)),VLOOKUP(H18,亿企科目!A:G,6,0)) -> 6603 | N18: =IFERROR(IF(H18="1002","银行账户",IF(H18="1123","供应商",VLOOKUP(I18,亿企科目!A:H,8,0))),"") -> 费用项目 | O18: =IF(N18=0,IF(M18="1002",K18,""),_xlfn.TEXTAFTER(E18,"-",-1)) -> 手续费 | P18: =VLOOKUP(A18,账簿!B:C,2,0) -> 002022 | Q18: =VLOOKUP(P18,账簿!A:B,2,0) -> 昌邑泓澄水业有限公司 | W18: =X18&AB18&AD18 -> 0020222026-04-308 | X18: =P18 -> 002022 | Y18: =X18 -> 002022 | Z18: =Q18 -> 昌邑泓澄水业有限公司 | AA18: =LEFT(B18,7) -> 2026-04 | AB18: =B18 -> 2026-04-30 | AC18: 记 | AD18: =VALUE(_xlfn.TEXTAFTER(C18,"-")) -> 8 | AE18: =D18 -> 结转本月损益 | AF18: 谭雅心 | AG18: 谭雅心 | AN18: =M18 -> 6603 | AP18: =D18 -> 结转本月损益 | AQ18: CNY | AR18: =F18 | AS18: =G18 -> 314.28 | AT18: 01 | AU18: * | AV18: 1 | AW18: =AR18 | AX18: =AS18 -> 314.28 | BQ18: =IF(N18="项目",VLOOKUP(O18,项目!B:C,2,0),IF(K18="空项目",VLOOKUP(K18,项目!B:C,2,0),"")) | BR18: =IFERROR(VLOOKUP(BQ18,项目!A:B,2,0),"") | BU18: =IF(N18="供应商",VLOOKUP(O18,供应商!B:C,2,0),"") | BV18: =IFERROR(VLOOKUP(BU18,供应商!A:B,2,0),"") | BW18: =IF(N18="客户",VLOOKUP(O18,客户!B:C,2,0),"") | BX18: =IFERROR(VLOOKUP(BW18,客户!A:B,2,0),"") | CU18: =IF(N18="费用项目",VLOOKUP(O18,费用项目!B:C,2,0),"") -> 660304 | CV18: =IFERROR(VLOOKUP(CU18,费用项目!A:B,2,0),"") -> 手续费 | CW18: =IF(N18="银行账户",VLOOKUP(O18,银行变二级!B:C,2,0),"") | CX18: =IFERROR(VLOOKUP(O18,银行变二级!A:B,2,0),"")
A19: 昌邑市昌荣城乡建设有限公司 | B19: 2026-04-21 | C19: 记-001 | D19: 2026-04-21,昌邑市昌荣城乡建设有限公司,贷款还款 | E19: 6603 财务费用-利息支出 | F19: 13431.07 | H19: =LEFT(E19,4) -> 6603 | I19: =IFERROR(LEFT(E19,FIND(" ",E19)-1),E19) -> 6603 | J19: =LEFT(MID(E19,FIND(" ",E19)+1,LEN(E19)),FIND("-",MID(E19,FIND(" ",E19)+1,LEN(E19))&"-")-1) -> 财务费用 | K19: =IFERROR(MID(MID(E19,FIND(" ",E19)+1,LEN(E19)),FIND("-",MID(E19,FIND(" ",E19)+1,LEN(E19)))+1,IFERROR(FIND("-",MID(E19,FIND(" ",E19)+1,LEN(E19)),FIND("-",MID(E19,FIND(" ",E19)+1,LEN(E19)))+1),LEN(MID(E19,FIND(" ",E19)+1,LEN(E19)))+1)-FIND("-",MID(E19,FIND(" ",E19)+1,LEN(E19)))-1),"") -> 利息支出 | L19: =IFERROR(MID(MID(E19,FIND(" ",E19)+1,LEN(E19)),FIND("-",MID(E19,FIND(" ",E19)+1,LEN(E19)),FIND("-",MID(E19,FIND(" ",E19)+1,LEN(E19)))+1)+1,LEN(E19)),"") | M19: =IFERROR(IF(H19="1002",1002,VLOOKUP(I19,亿企科目!A:H,6,0)),VLOOKUP(H19,亿企科目!A:G,6,0)) -> 6603 | N19: =IFERROR(IF(H19="1002","银行账户",IF(H19="1123","供应商",VLOOKUP(I19,亿企科目!A:H,8,0))),"") -> 费用项目 | O19: =IF(N19=0,IF(M19="1002",K19,""),_xlfn.TEXTAFTER(E19,"-",-1)) -> 利息支出 | P19: =VLOOKUP(A19,账簿!B:C,2,0) -> 003012 | Q19: =VLOOKUP(P19,账簿!A:B,2,0) -> 昌邑市昌荣城乡建设有限公司 | W19: =X19&AB19&AD19 -> 0030122026-04-211 | X19: =P19 -> 003012 | Y19: =X19 -> 003012 | Z19: =Q19 -> 昌邑市昌荣城乡建设有限公司 | AA19: =LEFT(B19,7) -> 2026-04 | AB19: =B19 -> 2026-04-21 | AC19: 记 | AD19: =VALUE(_xlfn.TEXTAFTER(C19,"-")) -> 1 | AE19: =D19 -> 2026-04-21,昌邑市昌荣城乡建设有限公司,贷款还款 | AF19: 谭雅心 | AG19: 谭雅心 | AN19: =M19 -> 6603 | AP19: =D19 -> 2026-04-21,昌邑市昌荣城乡建设有限公司,贷款还款 | AQ19: CNY | AR19: =F19 -> 13431.07 | AS19: =G19 | AT19: 01 | AU19: * | AV19: 1 | AW19: =AR19 -> 13431.07 | AX19: =AS19 | BQ19: =IF(N19="项目",VLOOKUP(O19,项目!B:C,2,0),IF(K19="空项目",VLOOKUP(K19,项目!B:C,2,0),"")) | BR19: =IFERROR(VLOOKUP(BQ19,项目!A:B,2,0),"") | BU19: =IF(N19="供应商",VLOOKUP(O19,供应商!B:C,2,0),"") | BV19: =IFERROR(VLOOKUP(BU19,供应商!A:B,2,0),"") | BW19: =IF(N19="客户",VLOOKUP(O19,客户!B:C,2,0),"") | BX19: =IFERROR(VLOOKUP(BW19,客户!A:B,2,0),"") | CU19: =IF(N19="费用项目",VLOOKUP(O19,费用项目!B:C,2,0),"") -> 660302 | CV19: =IFERROR(VLOOKUP(CU19,费用项目!A:B,2,0),"") -> 利息支出 | CW19: =IF(N19="银行账户",VLOOKUP(O19,银行变二级!B:C,2,0),"") | CX19: =IFERROR(VLOOKUP(O19,银行变二级!A:B,2,0),"")
A20: 昌邑市昌荣城乡建设有限公司 | B20: 2026-04-21 | C20: 记-001 | D20: 2026-04-21,昌邑市昌荣城乡建设有限公司,贷款还款 | E20: 100203 银行存款-潍坊银行5103 | G20: 13431.07 | H20: =LEFT(E20,4) -> 1002 | I20: =IFERROR(LEFT(E20,FIND(" ",E20)-1),E20) -> 100203 | J20: =LEFT(MID(E20,FIND(" ",E20)+1,LEN(E20)),FIND("-",MID(E20,FIND(" ",E20)+1,LEN(E20))&"-")-1) -> 银行存款 | K20: =IFERROR(MID(MID(E20,FIND(" ",E20)+1,LEN(E20)),FIND("-",MID(E20,FIND(" ",E20)+1,LEN(E20)))+1,IFERROR(FIND("-",MID(E20,FIND(" ",E20)+1,LEN(E20)),FIND("-",MID(E20,FIND(" ",E20)+1,LEN(E20)))+1),LEN(MID(E20,FIND(" ",E20)+1,LEN(E20)))+1)-FIND("-",MID(E20,FIND(" ",E20)+1,LEN(E20)))-1),"") -> 潍坊银行5103 | L20: =IFERROR(MID(MID(E20,FIND(" ",E20)+1,LEN(E20)),FIND("-",MID(E20,FIND(" ",E20)+1,LEN(E20)),FIND("-",MID(E20,FIND(" ",E20)+1,LEN(E20)))+1)+1,LEN(E20)),"") | M20: =IFERROR(IF(H20="1002",1002,VLOOKUP(I20,亿企科目!A:H,6,0)),VLOOKUP(H20,亿企科目!A:G,6,0)) -> 1002 | N20: =IFERROR(IF(H20="1002","银行账户",IF(H20="1123","供应商",VLOOKUP(I20,亿企科目!A:H,8,0))),"") -> 银行账户 | O20: =IF(N20=0,IF(M20="1002",K20,""),_xlfn.TEXTAFTER(E20,"-",-1)) -> 潍坊银行5103 | P20: =VLOOKUP(A20,账簿!B:C,2,0) -> 003012 | Q20: =VLOOKUP(P20,账簿!A:B,2,0) -> 昌邑市昌荣城乡建设有限公司 | W20: =X20&AB20&AD20 -> 0030122026-04-211 | X20: =P20 -> 003012 | Y20: =X20 -> 003012 | Z20: =Q20 -> 昌邑市昌荣城乡建设有限公司 | AA20: =LEFT(B20,7) -> 2026-04 | AB20: =B20 -> 2026-04-21 | AC20: 记 | AD20: =VALUE(_xlfn.TEXTAFTER(C20,"-")) -> 1 | AE20: =D20 -> 2026-04-21,昌邑市昌荣城乡建设有限公司,贷款还款 | AF20: 谭雅心 | AG20: 谭雅心 | AN20: =M20 -> 1002 | AP20: =D20 -> 2026-04-21,昌邑市昌荣城乡建设有限公司,贷款还款 | AQ20: CNY | AR20: =F20 | AS20: =G20 -> 13431.07 | AT20: 01 | AU20: * | AV20: 1 | AW20: =AR20 | AX20: =AS20 -> 13431.07 | BQ20: =IF(N20="项目",VLOOKUP(O20,项目!B:C,2,0),IF(K20="空项目",VLOOKUP(K20,项目!B:C,2,0),"")) | BR20: =IFERROR(VLOOKUP(BQ20,项目!A:B,2,0),"") | BU20: =IF(N20="供应商",VLOOKUP(O20,供应商!B:C,2,0),"") | BV20: =IFERROR(VLOOKUP(BU20,供应商!A:B,2,0),"") | BW20: =IF(N20="客户",VLOOKUP(O20,客户!B:C,2,0),"") | BX20: =IFERROR(VLOOKUP(BW20,客户!A:B,2,0),"") | CU20: =IF(N20="费用项目",VLOOKUP(O20,费用项目!B:C,2,0),"") | CV20: =IFERROR(VLOOKUP(CU20,费用项目!A:B,2,0),"") | CW20: =IF(N20="银行账户",VLOOKUP(O20,银行变二级!B:C,2,0),"") -> 潍坊银行5103 | CX20: =IFERROR(VLOOKUP(O20,银行变二级!A:B,2,0),"") -> 潍坊银行5103
A21: 昌邑市昌荣城乡建设有限公司 | B21: 2026-04-21 | C21: 记-002 | D21: 2026-04-21,昌邑市国有资产经营投资有限公司,往来款 | E21: 100203 银行存款-潍坊银行5103 | F21: 180000 | H21: =LEFT(E21,4) -> 1002 | I21: =IFERROR(LEFT(E21,FIND(" ",E21)-1),E21) -> 100203 | J21: =LEFT(MID(E21,FIND(" ",E21)+1,LEN(E21)),FIND("-",MID(E21,FIND(" ",E21)+1,LEN(E21))&"-")-1) -> 银行存款 | K21: =IFERROR(MID(MID(E21,FIND(" ",E21)+1,LEN(E21)),FIND("-",MID(E21,FIND(" ",E21)+1,LEN(E21)))+1,IFERROR(FIND("-",MID(E21,FIND(" ",E21)+1,LEN(E21)),FIND("-",MID(E21,FIND(" ",E21)+1,LEN(E21)))+1),LEN(MID(E21,FIND(" ",E21)+1,LEN(E21)))+1)-FIND("-",MID(E21,FIND(" ",E21)+1,LEN(E21)))-1),"") -> 潍坊银行5103 | L21: =IFERROR(MID(MID(E21,FIND(" ",E21)+1,LEN(E21)),FIND("-",MID(E21,FIND(" ",E21)+1,LEN(E21)),FIND("-",MID(E21,FIND(" ",E21)+1,LEN(E21)))+1)+1,LEN(E21)),"") | M21: =IFERROR(IF(H21="1002",1002,VLOOKUP(I21,亿企科目!A:H,6,0)),VLOOKUP(H21,亿企科目!A:G,6,0)) -> 1002 | N21: =IFERROR(IF(H21="1002","银行账户",IF(H21="1123","供应商",VLOOKUP(I21,亿企科目!A:H,8,0))),"") -> 银行账户 | O21: =IF(N21=0,IF(M21="1002",K21,""),_xlfn.TEXTAFTER(E21,"-",-1)) -> 潍坊银行5103 | P21: =VLOOKUP(A21,账簿!B:C,2,0) -> 003012 | Q21: =VLOOKUP(P21,账簿!A:B,2,0) -> 昌邑市昌荣城乡建设有限公司 | W21: =X21&AB21&AD21 -> 0030122026-04-212 | X21: =P21 -> 003012 | Y21: =X21 -> 003012 | Z21: =Q21 -> 昌邑市昌荣城乡建设有限公司 | AA21: =LEFT(B21,7) -> 2026-04 | AB21: =B21 -> 2026-04-21 | AC21: 记 | AD21: =VALUE(_xlfn.TEXTAFTER(C21,"-")) -> 2 | AE21: =D21 -> 2026-04-21,昌邑市国有资产经营投资有限公司,往来款 | AF21: 谭雅心 | AG21: 谭雅心 | AN21: =M21 -> 1002 | AP21: =D21 -> 2026-04-21,昌邑市国有资产经营投资有限公司,往来款 | AQ21: CNY | AR21: =F21 -> 180000 | AS21: =G21 | AT21: 01 | AU21: * | AV21: 1 | AW21: =AR21 -> 180000 | AX21: =AS21 | BQ21: =IF(N21="项目",VLOOKUP(O21,项目!B:C,2,0),IF(K21="空项目",VLOOKUP(K21,项目!B:C,2,0),"")) | BR21: =IFERROR(VLOOKUP(BQ21,项目!A:B,2,0),"") | BU21: =IF(N21="供应商",VLOOKUP(O21,供应商!B:C,2,0),"") | BV21: =IFERROR(VLOOKUP(BU21,供应商!A:B,2,0),"") | BW21: =IF(N21="客户",VLOOKUP(O21,客户!B:C,2,0),"") | BX21: =IFERROR(VLOOKUP(BW21,客户!A:B,2,0),"") | CU21: =IF(N21="费用项目",VLOOKUP(O21,费用项目!B:C,2,0),"") | CV21: =IFERROR(VLOOKUP(CU21,费用项目!A:B,2,0),"") | CW21: =IF(N21="银行账户",VLOOKUP(O21,银行变二级!B:C,2,0),"") -> 潍坊银行5103 | CX21: =IFERROR(VLOOKUP(O21,银行变二级!A:B,2,0),"") -> 潍坊银行5103
A22: 昌邑市昌荣城乡建设有限公司 | B22: 2026-04-21 | C22: 记-002 | D22: 2026-04-21,昌邑市国有资产经营投资有限公司,往来款 | E22: 122108 其他应收款-单位-昌邑市国有资产经营投资有限公司 | G22: 180000 | H22: =LEFT(E22,4) -> 1221 | I22: =IFERROR(LEFT(E22,FIND(" ",E22)-1),E22) -> 122108 | J22: =LEFT(MID(E22,FIND(" ",E22)+1,LEN(E22)),FIND("-",MID(E22,FIND(" ",E22)+1,LEN(E22))&"-")-1) -> 其他应收款 | K22: =IFERROR(MID(MID(E22,FIND(" ",E22)+1,LEN(E22)),FIND("-",MID(E22,FIND(" ",E22)+1,LEN(E22)))+1,IFERROR(FIND("-",MID(E22,FIND(" ",E22)+1,LEN(E22)),FIND("-",MID(E22,FIND(" ",E22)+1,LEN(E22)))+1),LEN(MID(E22,FIND(" ",E22)+1,LEN(E22)))+1)-FIND("-",MID(E22,FIND(" ",E22)+1,LEN(E22)))-1),"") -> 单位 | L22: =IFERROR(MID(MID(E22,FIND(" ",E22)+1,LEN(E22)),FIND("-",MID(E22,FIND(" ",E22)+1,LEN(E22)),FIND("-",MID(E22,FIND(" ",E22)+1,LEN(E22)))+1)+1,LEN(E22)),"") -> 昌邑市国有资产经营投资有限公司 | M22: =IFERROR(IF(H22="1002",1002,VLOOKUP(I22,亿企科目!A:H,6,0)),VLOOKUP(H22,亿企科目!A:G,6,0)) -> 122102 | N22: =IFERROR(IF(H22="1002","银行账户",IF(H22="1123","供应商",VLOOKUP(I22,亿企科目!A:H,8,0))),"") -> 客户 | O22: =IF(N22=0,IF(M22="1002",K22,""),_xlfn.TEXTAFTER(E22,"-",-1)) -> 昌邑市国有资产经营投资有限公司 | P22: =VLOOKUP(A22,账簿!B:C,2,0) -> 003012 | Q22: =VLOOKUP(P22,账簿!A:B,2,0) -> 昌邑市昌荣城乡建设有限公司 | W22: =X22&AB22&AD22 -> 0030122026-04-212 | X22: =P22 -> 003012 | Y22: =X22 -> 003012 | Z22: =Q22 -> 昌邑市昌荣城乡建设有限公司 | AA22: =LEFT(B22,7) -> 2026-04 | AB22: =B22 -> 2026-04-21 | AC22: 记 | AD22: =VALUE(_xlfn.TEXTAFTER(C22,"-")) -> 2 | AE22: =D22 -> 2026-04-21,昌邑市国有资产经营投资有限公司,往来款 | AF22: 谭雅心 | AG22: 谭雅心 | AN22: =M22 -> 122102 | AP22: =D22 -> 2026-04-21,昌邑市国有资产经营投资有限公司,往来款 | AQ22: CNY | AR22: =F22 | AS22: =G22 -> 180000 | AT22: 01 | AU22: * | AV22: 1 | AW22: =AR22 | AX22: =AS22 -> 180000 | BQ22: =IF(N22="项目",VLOOKUP(O22,项目!B:C,2,0),IF(K22="空项目",VLOOKUP(K22,项目!B:C,2,0),"")) | BR22: =IFERROR(VLOOKUP(BQ22,项目!A:B,2,0),"") | BU22: =IF(N22="供应商",VLOOKUP(O22,供应商!B:C,2,0),"") | BV22: =IFERROR(VLOOKUP(BU22,供应商!A:B,2,0),"") | BW22: =IF(N22="客户",VLOOKUP(O22,客户!B:C,2,0),"") -> 003 | BX22: =IFERROR(VLOOKUP(BW22,客户!A:B,2,0),"") -> 昌邑市国有资产经营投资有限公司 | CU22: =IF(N22="费用项目",VLOOKUP(O22,费用项目!B:C,2,0),"") | CV22: =IFERROR(VLOOKUP(CU22,费用项目!A:B,2,0),"") | CW22: =IF(N22="银行账户",VLOOKUP(O22,银行变二级!B:C,2,0),"") | CX22: =IFERROR(VLOOKUP(O22,银行变二级!A:B,2,0),"")
A23: 昌邑市昌荣城乡建设有限公司 | B23: 2026-04-21 | C23: 记-003 | D23: 2026-04-21,昌邑市昌荣城乡建设有限公司,贷款还款 | E23: 6603 财务费用-利息支出 | F23: 133818.93 | H23: =LEFT(E23,4) -> 6603 | I23: =IFERROR(LEFT(E23,FIND(" ",E23)-1),E23) -> 6603 | J23: =LEFT(MID(E23,FIND(" ",E23)+1,LEN(E23)),FIND("-",MID(E23,FIND(" ",E23)+1,LEN(E23))&"-")-1) -> 财务费用 | K23: =IFERROR(MID(MID(E23,FIND(" ",E23)+1,LEN(E23)),FIND("-",MID(E23,FIND(" ",E23)+1,LEN(E23)))+1,IFERROR(FIND("-",MID(E23,FIND(" ",E23)+1,LEN(E23)),FIND("-",MID(E23,FIND(" ",E23)+1,LEN(E23)))+1),LEN(MID(E23,FIND(" ",E23)+1,LEN(E23)))+1)-FIND("-",MID(E23,FIND(" ",E23)+1,LEN(E23)))-1),"") -> 利息支出 | L23: =IFERROR(MID(MID(E23,FIND(" ",E23)+1,LEN(E23)),FIND("-",MID(E23,FIND(" ",E23)+1,LEN(E23)),FIND("-",MID(E23,FIND(" ",E23)+1,LEN(E23)))+1)+1,LEN(E23)),"") | M23: =IFERROR(IF(H23="1002",1002,VLOOKUP(I23,亿企科目!A:H,6,0)),VLOOKUP(H23,亿企科目!A:G,6,0)) -> 6603 | N23: =IFERROR(IF(H23="1002","银行账户",IF(H23="1123","供应商",VLOOKUP(I23,亿企科目!A:H,8,0))),"") -> 费用项目 | O23: =IF(N23=0,IF(M23="1002",K23,""),_xlfn.TEXTAFTER(E23,"-",-1)) -> 利息支出 | P23: =VLOOKUP(A23,账簿!B:C,2,0) -> 003012 | Q23: =VLOOKUP(P23,账簿!A:B,2,0) -> 昌邑市昌荣城乡建设有限公司 | W23: =X23&AB23&AD23 -> 0030122026-04-213 | X23: =P23 -> 003012 | Y23: =X23 -> 003012 | Z23: =Q23 -> 昌邑市昌荣城乡建设有限公司 | AA23: =LEFT(B23,7) -> 2026-04 | AB23: =B23 -> 2026-04-21 | AC23: 记 | AD23: =VALUE(_xlfn.TEXTAFTER(C23,"-")) -> 3 | AE23: =D23 -> 2026-04-21,昌邑市昌荣城乡建设有限公司,贷款还款 | AF23: 谭雅心 | AG23: 谭雅心 | AN23: =M23 -> 6603 | AP23: =D23 -> 2026-04-21,昌邑市昌荣城乡建设有限公司,贷款还款 | AQ23: CNY | AR23: =F23 -> 133818.93 | AS23: =G23 | AT23: 01 | AU23: * | AV23: 1 | AW23: =AR23 -> 133818.93 | AX23: =AS23 | BQ23: =IF(N23="项目",VLOOKUP(O23,项目!B:C,2,0),IF(K23="空项目",VLOOKUP(K23,项目!B:C,2,0),"")) | BR23: =IFERROR(VLOOKUP(BQ23,项目!A:B,2,0),"") | BU23: =IF(N23="供应商",VLOOKUP(O23,供应商!B:C,2,0),"") | BV23: =IFERROR(VLOOKUP(BU23,供应商!A:B,2,0),"") | BW23: =IF(N23="客户",VLOOKUP(O23,客户!B:C,2,0),"") | BX23: =IFERROR(VLOOKUP(BW23,客户!A:B,2,0),"") | CU23: =IF(N23="费用项目",VLOOKUP(O23,费用项目!B:C,2,0),"") -> 660302 | CV23: =IFERROR(VLOOKUP(CU23,费用项目!A:B,2,0),"") -> 利息支出 | CW23: =IF(N23="银行账户",VLOOKUP(O23,银行变二级!B:C,2,0),"") | CX23: =IFERROR(VLOOKUP(O23,银行变二级!A:B,2,0),"")
A24: 昌邑市昌荣城乡建设有限公司 | B24: 2026-04-21 | C24: 记-003 | D24: 2026-04-21,昌邑市昌荣城乡建设有限公司,贷款还款 | E24: 100203 银行存款-潍坊银行5103 | G24: 133818.93 | H24: =LEFT(E24,4) -> 1002 | I24: =IFERROR(LEFT(E24,FIND(" ",E24)-1),E24) -> 100203 | J24: =LEFT(MID(E24,FIND(" ",E24)+1,LEN(E24)),FIND("-",MID(E24,FIND(" ",E24)+1,LEN(E24))&"-")-1) -> 银行存款 | K24: =IFERROR(MID(MID(E24,FIND(" ",E24)+1,LEN(E24)),FIND("-",MID(E24,FIND(" ",E24)+1,LEN(E24)))+1,IFERROR(FIND("-",MID(E24,FIND(" ",E24)+1,LEN(E24)),FIND("-",MID(E24,FIND(" ",E24)+1,LEN(E24)))+1),LEN(MID(E24,FIND(" ",E24)+1,LEN(E24)))+1)-FIND("-",MID(E24,FIND(" ",E24)+1,LEN(E24)))-1),"") -> 潍坊银行5103 | L24: =IFERROR(MID(MID(E24,FIND(" ",E24)+1,LEN(E24)),FIND("-",MID(E24,FIND(" ",E24)+1,LEN(E24)),FIND("-",MID(E24,FIND(" ",E24)+1,LEN(E24)))+1)+1,LEN(E24)),"") | M24: =IFERROR(IF(H24="1002",1002,VLOOKUP(I24,亿企科目!A:H,6,0)),VLOOKUP(H24,亿企科目!A:G,6,0)) -> 1002 | N24: =IFERROR(IF(H24="1002","银行账户",IF(H24="1123","供应商",VLOOKUP(I24,亿企科目!A:H,8,0))),"") -> 银行账户 | O24: =IF(N24=0,IF(M24="1002",K24,""),_xlfn.TEXTAFTER(E24,"-",-1)) -> 潍坊银行5103 | P24: =VLOOKUP(A24,账簿!B:C,2,0) -> 003012 | Q24: =VLOOKUP(P24,账簿!A:B,2,0) -> 昌邑市昌荣城乡建设有限公司 | W24: =X24&AB24&AD24 -> 0030122026-04-213 | X24: =P24 -> 003012 | Y24: =X24 -> 003012 | Z24: =Q24 -> 昌邑市昌荣城乡建设有限公司 | AA24: =LEFT(B24,7) -> 2026-04 | AB24: =B24 -> 2026-04-21 | AC24: 记 | AD24: =VALUE(_xlfn.TEXTAFTER(C24,"-")) -> 3 | AE24: =D24 -> 2026-04-21,昌邑市昌荣城乡建设有限公司,贷款还款 | AF24: 谭雅心 | AG24: 谭雅心 | AN24: =M24 -> 1002 | AP24: =D24 -> 2026-04-21,昌邑市昌荣城乡建设有限公司,贷款还款 | AQ24: CNY | AR24: =F24 | AS24: =G24 -> 133818.93 | AT24: 01 | AU24: * | AV24: 1 | AW24: =AR24 | AX24: =AS24 -> 133818.93 | BQ24: =IF(N24="项目",VLOOKUP(O24,项目!B:C,2,0),IF(K24="空项目",VLOOKUP(K24,项目!B:C,2,0),"")) | BR24: =IFERROR(VLOOKUP(BQ24,项目!A:B,2,0),"") | BU24: =IF(N24="供应商",VLOOKUP(O24,供应商!B:C,2,0),"") | BV24: =IFERROR(VLOOKUP(BU24,供应商!A:B,2,0),"") | BW24: =IF(N24="客户",VLOOKUP(O24,客户!B:C,2,0),"") | BX24: =IFERROR(VLOOKUP(BW24,客户!A:B,2,0),"") | CU24: =IF(N24="费用项目",VLOOKUP(O24,费用项目!B:C,2,0),"") | CV24: =IFERROR(VLOOKUP(CU24,费用项目!A:B,2,0),"") | CW24: =IF(N24="银行账户",VLOOKUP(O24,银行变二级!B:C,2,0),"") -> 潍坊银行5103 | CX24: =IFERROR(VLOOKUP(O24,银行变二级!A:B,2,0),"") -> 潍坊银行5103
A25: 昌邑市昌荣城乡建设有限公司 | B25: 2026-04-21 | C25: 记-004 | D25: 2026-04-21,昌邑市昌荣城乡建设有限公司,贷款还款 | E25: 220202 应付账款-明细应付款-山东博林供应链管理服务有限公司 | F25: 29708.33 | H25: =LEFT(E25,4) -> 2202 | I25: =IFERROR(LEFT(E25,FIND(" ",E25)-1),E25) -> 220202 | J25: =LEFT(MID(E25,FIND(" ",E25)+1,LEN(E25)),FIND("-",MID(E25,FIND(" ",E25)+1,LEN(E25))&"-")-1) -> 应付账款 | K25: =IFERROR(MID(MID(E25,FIND(" ",E25)+1,LEN(E25)),FIND("-",MID(E25,FIND(" ",E25)+1,LEN(E25)))+1,IFERROR(FIND("-",MID(E25,FIND(" ",E25)+1,LEN(E25)),FIND("-",MID(E25,FIND(" ",E25)+1,LEN(E25)))+1),LEN(MID(E25,FIND(" ",E25)+1,LEN(E25)))+1)-FIND("-",MID(E25,FIND(" ",E25)+1,LEN(E25)))-1),"") -> 明细应付款 | L25: =IFERROR(MID(MID(E25,FIND(" ",E25)+1,LEN(E25)),FIND("-",MID(E25,FIND(" ",E25)+1,LEN(E25)),FIND("-",MID(E25,FIND(" ",E25)+1,LEN(E25)))+1)+1,LEN(E25)),"") -> 山东博林供应链管理服务有限公司 | M25: =IFERROR(IF(H25="1002",1002,VLOOKUP(I25,亿企科目!A:H,6,0)),VLOOKUP(H25,亿企科目!A:G,6,0)) -> 220202 | N25: =IFERROR(IF(H25="1002","银行账户",IF(H25="1123","供应商",VLOOKUP(I25,亿企科目!A:H,8,0))),"") -> 供应商 | O25: =IF(N25=0,IF(M25="1002",K25,""),_xlfn.TEXTAFTER(E25,"-",-1)) -> 山东博林供应链管理服务有限公司 | P25: =VLOOKUP(A25,账簿!B:C,2,0) -> 003012 | Q25: =VLOOKUP(P25,账簿!A:B,2,0) -> 昌邑市昌荣城乡建设有限公司 | W25: =X25&AB25&AD25 -> 0030122026-04-214 | X25: =P25 -> 003012 | Y25: =X25 -> 003012 | Z25: =Q25 -> 昌邑市昌荣城乡建设有限公司 | AA25: =LEFT(B25,7) -> 2026-04 | AB25: =B25 -> 2026-04-21 | AC25: 记 | AD25: =VALUE(_xlfn.TEXTAFTER(C25,"-")) -> 4 | AE25: =D25 -> 2026-04-21,昌邑市昌荣城乡建设有限公司,贷款还款 | AF25: 谭雅心 | AG25: 谭雅心 | AN25: =M25 -> 220202 | AP25: =D25 -> 2026-04-21,昌邑市昌荣城乡建设有限公司,贷款还款 | AQ25: CNY | AR25: =F25 -> 29708.33 | AS25: =G25 | AT25: 01 | AU25: * | AV25: 1 | AW25: =AR25 -> 29708.33 | AX25: =AS25 | BQ25: =IF(N25="项目",VLOOKUP(O25,项目!B:C,2,0),IF(K25="空项目",VLOOKUP(K25,项目!B:C,2,0),"")) | BR25: =IFERROR(VLOOKUP(BQ25,项目!A:B,2,0),"") | BU25: =IF(N25="供应商",VLOOKUP(O25,供应商!B:C,2,0),"") -> 0011769 | BV25: =IFERROR(VLOOKUP(BU25,供应商!A:B,2,0),"") -> 山东博林供应链管理服务有限公司 | BW25: =IF(N25="客户",VLOOKUP(O25,客户!B:C,2,0),"") | BX25: =IFERROR(VLOOKUP(BW25,客户!A:B,2,0),"") | CU25: =IF(N25="费用项目",VLOOKUP(O25,费用项目!B:C,2,0),"") | CV25: =IFERROR(VLOOKUP(CU25,费用项目!A:B,2,0),"") | CW25: =IF(N25="银行账户",VLOOKUP(O25,银行变二级!B:C,2,0),"") | CX25: =IFERROR(VLOOKUP(O25,银行变二级!A:B,2,0),"")
A26: 昌邑市昌荣城乡建设有限公司 | B26: 2026-04-21 | C26: 记-004 | D26: 2026-04-21,昌邑市昌荣城乡建设有限公司,贷款还款 | E26: 100203 银行存款-潍坊银行5103 | G26: 29708.33 | H26: =LEFT(E26,4) -> 1002 | I26: =IFERROR(LEFT(E26,FIND(" ",E26)-1),E26) -> 100203 | J26: =LEFT(MID(E26,FIND(" ",E26)+1,LEN(E26)),FIND("-",MID(E26,FIND(" ",E26)+1,LEN(E26))&"-")-1) -> 银行存款 | K26: =IFERROR(MID(MID(E26,FIND(" ",E26)+1,LEN(E26)),FIND("-",MID(E26,FIND(" ",E26)+1,LEN(E26)))+1,IFERROR(FIND("-",MID(E26,FIND(" ",E26)+1,LEN(E26)),FIND("-",MID(E26,FIND(" ",E26)+1,LEN(E26)))+1),LEN(MID(E26,FIND(" ",E26)+1,LEN(E26)))+1)-FIND("-",MID(E26,FIND(" ",E26)+1,LEN(E26)))-1),"") -> 潍坊银行5103 | L26: =IFERROR(MID(MID(E26,FIND(" ",E26)+1,LEN(E26)),FIND("-",MID(E26,FIND(" ",E26)+1,LEN(E26)),FIND("-",MID(E26,FIND(" ",E26)+1,LEN(E26)))+1)+1,LEN(E26)),"") | M26: =IFERROR(IF(H26="1002",1002,VLOOKUP(I26,亿企科目!A:H,6,0)),VLOOKUP(H26,亿企科目!A:G,6,0)) -> 1002 | N26: =IFERROR(IF(H26="1002","银行账户",IF(H26="1123","供应商",VLOOKUP(I26,亿企科目!A:H,8,0))),"") -> 银行账户 | O26: =IF(N26=0,IF(M26="1002",K26,""),_xlfn.TEXTAFTER(E26,"-",-1)) -> 潍坊银行5103 | P26: =VLOOKUP(A26,账簿!B:C,2,0) -> 003012 | Q26: =VLOOKUP(P26,账簿!A:B,2,0) -> 昌邑市昌荣城乡建设有限公司 | W26: =X26&AB26&AD26 -> 0030122026-04-214 | X26: =P26 -> 003012 | Y26: =X26 -> 003012 | Z26: =Q26 -> 昌邑市昌荣城乡建设有限公司 | AA26: =LEFT(B26,7) -> 2026-04 | AB26: =B26 -> 2026-04-21 | AC26: 记 | AD26: =VALUE(_xlfn.TEXTAFTER(C26,"-")) -> 4 | AE26: =D26 -> 2026-04-21,昌邑市昌荣城乡建设有限公司,贷款还款 | AF26: 谭雅心 | AG26: 谭雅心 | AN26: =M26 -> 1002 | AP26: =D26 -> 2026-04-21,昌邑市昌荣城乡建设有限公司,贷款还款 | AQ26: CNY | AR26: =F26 | AS26: =G26 -> 29708.33 | AT26: 01 | AU26: * | AV26: 1 | AW26: =AR26 | AX26: =AS26 -> 29708.33 | BQ26: =IF(N26="项目",VLOOKUP(O26,项目!B:C,2,0),IF(K26="空项目",VLOOKUP(K26,项目!B:C,2,0),"")) | BR26: =IFERROR(VLOOKUP(BQ26,项目!A:B,2,0),"") | BU26: =IF(N26="供应商",VLOOKUP(O26,供应商!B:C,2,0),"") | BV26: =IFERROR(VLOOKUP(BU26,供应商!A:B,2,0),"") | BW26: =IF(N26="客户",VLOOKUP(O26,客户!B:C,2,0),"") | BX26: =IFERROR(VLOOKUP(BW26,客户!A:B,2,0),"") | CU26: =IF(N26="费用项目",VLOOKUP(O26,费用项目!B:C,2,0),"") | CV26: =IFERROR(VLOOKUP(CU26,费用项目!A:B,2,0),"") | CW26: =IF(N26="银行账户",VLOOKUP(O26,银行变二级!B:C,2,0),"") -> 潍坊银行5103 | CX26: =IFERROR(VLOOKUP(O26,银行变二级!A:B,2,0),"") -> 潍坊银行5103
A27: 昌邑市昌荣城乡建设有限公司 | B27: 2026-04-30 | C27: 记-005 | D27: 支付金融利息支出,2026-03-24,26372000001300613776,利息收入,山东博林供应链管理服务有限公司;支付金融利息支出,2026-02-28,26372000000872431306,利息收入,山东博林供应链管理服务有限公司;支付金融利息支出,2026-01-28,26372000000431276296,利息收入,山东博林供应链管理服务有限公司 | E27: 6603 财务费用-利息支出 | F27: 86249.99 | H27: =LEFT(E27,4) -> 6603 | I27: =IFERROR(LEFT(E27,FIND(" ",E27)-1),E27) -> 6603 | J27: =LEFT(MID(E27,FIND(" ",E27)+1,LEN(E27)),FIND("-",MID(E27,FIND(" ",E27)+1,LEN(E27))&"-")-1) -> 财务费用 | K27: =IFERROR(MID(MID(E27,FIND(" ",E27)+1,LEN(E27)),FIND("-",MID(E27,FIND(" ",E27)+1,LEN(E27)))+1,IFERROR(FIND("-",MID(E27,FIND(" ",E27)+1,LEN(E27)),FIND("-",MID(E27,FIND(" ",E27)+1,LEN(E27)))+1),LEN(MID(E27,FIND(" ",E27)+1,LEN(E27)))+1)-FIND("-",MID(E27,FIND(" ",E27)+1,LEN(E27)))-1),"") -> 利息支出 | L27: =IFERROR(MID(MID(E27,FIND(" ",E27)+1,LEN(E27)),FIND("-",MID(E27,FIND(" ",E27)+1,LEN(E27)),FIND("-",MID(E27,FIND(" ",E27)+1,LEN(E27)))+1)+1,LEN(E27)),"") | M27: =IFERROR(IF(H27="1002",1002,VLOOKUP(I27,亿企科目!A:H,6,0)),VLOOKUP(H27,亿企科目!A:G,6,0)) -> 6603 | N27: =IFERROR(IF(H27="1002","银行账户",IF(H27="1123","供应商",VLOOKUP(I27,亿企科目!A:H,8,0))),"") -> 费用项目 | O27: =IF(N27=0,IF(M27="1002",K27,""),_xlfn.TEXTAFTER(E27,"-",-1)) -> 利息支出 | P27: =VLOOKUP(A27,账簿!B:C,2,0) -> 003012 | Q27: =VLOOKUP(P27,账簿!A:B,2,0) -> 昌邑市昌荣城乡建设有限公司 | W27: =X27&AB27&AD27 -> 0030122026-04-305 | X27: =P27 -> 003012 | Y27: =X27 -> 003012 | Z27: =Q27 -> 昌邑市昌荣城乡建设有限公司 | AA27: =LEFT(B27,7) -> 2026-04 | AB27: =B27 -> 2026-04-30 | AC27: 记 | AD27: =VALUE(_xlfn.TEXTAFTER(C27,"-")) -> 5 | AE27: =D27 -> 支付金融利息支出,2026-03-24,26372000001300613776,利息收入,山东博林供应链管理服务有限公司;支付金融利息支出,2026-02-28,26372000000872431306,利息收入,山东博林供应链管理服务有限公司;支付金融利息支出,2026-01-28,26372000000431276296,利息收入,山东博林供应链管理服务有限公司 | AF27: 谭雅心 | AG27: 谭雅心 | AN27: =M27 -> 6603 | AP27: =D27 -> 支付金融利息支出,2026-03-24,26372000001300613776,利息收入,山东博林供应链管理服务有限公司;支付金融利息支出,2026-02-28,26372000000872431306,利息收入,山东博林供应链管理服务有限公司;支付金融利息支出,2026-01-28,26372000000431276296,利息收入,山东博林供应链管理服务有限公司 | AQ27: CNY | AR27: =F27 -> 86249.99 | AS27: =G27 | AT27: 01 | AU27: * | AV27: 1 | AW27: =AR27 -> 86249.99 | AX27: =AS27 | BQ27: =IF(N27="项目",VLOOKUP(O27,项目!B:C,2,0),IF(K27="空项目",VLOOKUP(K27,项目!B:C,2,0),"")) | BR27: =IFERROR(VLOOKUP(BQ27,项目!A:B,2,0),"") | BU27: =IF(N27="供应商",VLOOKUP(O27,供应商!B:C,2,0),"") | BV27: =IFERROR(VLOOKUP(BU27,供应商!A:B,2,0),"") | BW27: =IF(N27="客户",VLOOKUP(O27,客户!B:C,2,0),"") | BX27: =IFERROR(VLOOKUP(BW27,客户!A:B,2,0),"") | CU27: =IF(N27="费用项目",VLOOKUP(O27,费用项目!B:C,2,0),"") -> 660302 | CV27: =IFERROR(VLOOKUP(CU27,费用项目!A:B,2,0),"") -> 利息支出 | CW27: =IF(N27="银行账户",VLOOKUP(O27,银行变二级!B:C,2,0),"") | CX27: =IFERROR(VLOOKUP(O27,银行变二级!A:B,2,0),"")
A28: 昌邑市昌荣城乡建设有限公司 | B28: 2026-04-30 | C28: 记-005 | D28: 支付金融利息支出,2026-03-24,26372000001300613776,利息收入,山东博林供应链管理服务有限公司;支付金融利息支出,2026-02-28,26372000000872431306,利息收入,山东博林供应链管理服务有限公司;支付金融利息支出,2026-01-28,26372000000431276296,利息收入,山东博林供应链管理服务有限公司 | E28: 220202 应付账款-明细应付款-山东博林供应链管理服务有限公司 | G28: 29708.33 | H28: =LEFT(E28,4) -> 2202 | I28: =IFERROR(LEFT(E28,FIND(" ",E28)-1),E28) -> 220202 | J28: =LEFT(MID(E28,FIND(" ",E28)+1,LEN(E28)),FIND("-",MID(E28,FIND(" ",E28)+1,LEN(E28))&"-")-1) -> 应付账款 | K28: =IFERROR(MID(MID(E28,FIND(" ",E28)+1,LEN(E28)),FIND("-",MID(E28,FIND(" ",E28)+1,LEN(E28)))+1,IFERROR(FIND("-",MID(E28,FIND(" ",E28)+1,LEN(E28)),FIND("-",MID(E28,FIND(" ",E28)+1,LEN(E28)))+1),LEN(MID(E28,FIND(" ",E28)+1,LEN(E28)))+1)-FIND("-",MID(E28,FIND(" ",E28)+1,LEN(E28)))-1),"") -> 明细应付款 | L28: =IFERROR(MID(MID(E28,FIND(" ",E28)+1,LEN(E28)),FIND("-",MID(E28,FIND(" ",E28)+1,LEN(E28)),FIND("-",MID(E28,FIND(" ",E28)+1,LEN(E28)))+1)+1,LEN(E28)),"") -> 山东博林供应链管理服务有限公司 | M28: =IFERROR(IF(H28="1002",1002,VLOOKUP(I28,亿企科目!A:H,6,0)),VLOOKUP(H28,亿企科目!A:G,6,0)) -> 220202 | N28: =IFERROR(IF(H28="1002","银行账户",IF(H28="1123","供应商",VLOOKUP(I28,亿企科目!A:H,8,0))),"") -> 供应商 | O28: =IF(N28=0,IF(M28="1002",K28,""),_xlfn.TEXTAFTER(E28,"-",-1)) -> 山东博林供应链管理服务有限公司 | P28: =VLOOKUP(A28,账簿!B:C,2,0) -> 003012 | Q28: =VLOOKUP(P28,账簿!A:B,2,0) -> 昌邑市昌荣城乡建设有限公司 | W28: =X28&AB28&AD28 -> 0030122026-04-305 | X28: =P28 -> 003012 | Y28: =X28 -> 003012 | Z28: =Q28 -> 昌邑市昌荣城乡建设有限公司 | AA28: =LEFT(B28,7) -> 2026-04 | AB28: =B28 -> 2026-04-30 | AC28: 记 | AD28: =VALUE(_xlfn.TEXTAFTER(C28,"-")) -> 5 | AE28: =D28 -> 支付金融利息支出,2026-03-24,26372000001300613776,利息收入,山东博林供应链管理服务有限公司;支付金融利息支出,2026-02-28,26372000000872431306,利息收入,山东博林供应链管理服务有限公司;支付金融利息支出,2026-01-28,26372000000431276296,利息收入,山东博林供应链管理服务有限公司 | AF28: 谭雅心 | AG28: 谭雅心 | AN28: =M28 -> 220202 | AP28: =D28 -> 支付金融利息支出,2026-03-24,26372000001300613776,利息收入,山东博林供应链管理服务有限公司;支付金融利息支出,2026-02-28,26372000000872431306,利息收入,山东博林供应链管理服务有限公司;支付金融利息支出,2026-01-28,26372000000431276296,利息收入,山东博林供应链管理服务有限公司 | AQ28: CNY | AR28: =F28 | AS28: =G28 -> 29708.33 | AT28: 01 | AU28: * | AV28: 1 | AW28: =AR28 | AX28: =AS28 -> 29708.33 | BQ28: =IF(N28="项目",VLOOKUP(O28,项目!B:C,2,0),IF(K28="空项目",VLOOKUP(K28,项目!B:C,2,0),"")) | BR28: =IFERROR(VLOOKUP(BQ28,项目!A:B,2,0),"") | BU28: =IF(N28="供应商",VLOOKUP(O28,供应商!B:C,2,0),"") -> 0011769 | BV28: =IFERROR(VLOOKUP(BU28,供应商!A:B,2,0),"") -> 山东博林供应链管理服务有限公司 | BW28: =IF(N28="客户",VLOOKUP(O28,客户!B:C,2,0),"") | BX28: =IFERROR(VLOOKUP(BW28,客户!A:B,2,0),"") | CU28: =IF(N28="费用项目",VLOOKUP(O28,费用项目!B:C,2,0),"") | CV28: =IFERROR(VLOOKUP(CU28,费用项目!A:B,2,0),"") | CW28: =IF(N28="银行账户",VLOOKUP(O28,银行变二级!B:C,2,0),"") | CX28: =IFERROR(VLOOKUP(O28,银行变二级!A:B,2,0),"")
A29: 昌邑市昌荣城乡建设有限公司 | B29: 2026-04-30 | C29: 记-005 | D29: 支付金融利息支出,2026-02-28,26372000000872431306,利息收入,山东博林供应链管理服务有限公司 | E29: 220202 应付账款-明细应付款-山东博林供应链管理服务有限公司 | G29: 29708.33 | H29: =LEFT(E29,4) -> 2202 | I29: =IFERROR(LEFT(E29,FIND(" ",E29)-1),E29) -> 220202 | J29: =LEFT(MID(E29,FIND(" ",E29)+1,LEN(E29)),FIND("-",MID(E29,FIND(" ",E29)+1,LEN(E29))&"-")-1) -> 应付账款 | K29: =IFERROR(MID(MID(E29,FIND(" ",E29)+1,LEN(E29)),FIND("-",MID(E29,FIND(" ",E29)+1,LEN(E29)))+1,IFERROR(FIND("-",MID(E29,FIND(" ",E29)+1,LEN(E29)),FIND("-",MID(E29,FIND(" ",E29)+1,LEN(E29)))+1),LEN(MID(E29,FIND(" ",E29)+1,LEN(E29)))+1)-FIND("-",MID(E29,FIND(" ",E29)+1,LEN(E29)))-1),"") -> 明细应付款 | L29: =IFERROR(MID(MID(E29,FIND(" ",E29)+1,LEN(E29)),FIND("-",MID(E29,FIND(" ",E29)+1,LEN(E29)),FIND("-",MID(E29,FIND(" ",E29)+1,LEN(E29)))+1)+1,LEN(E29)),"") -> 山东博林供应链管理服务有限公司 | M29: =IFERROR(IF(H29="1002",1002,VLOOKUP(I29,亿企科目!A:H,6,0)),VLOOKUP(H29,亿企科目!A:G,6,0)) -> 220202 | N29: =IFERROR(IF(H29="1002","银行账户",IF(H29="1123","供应商",VLOOKUP(I29,亿企科目!A:H,8,0))),"") -> 供应商 | O29: =IF(N29=0,IF(M29="1002",K29,""),_xlfn.TEXTAFTER(E29,"-",-1)) -> 山东博林供应链管理服务有限公司 | P29: =VLOOKUP(A29,账簿!B:C,2,0) -> 003012 | Q29: =VLOOKUP(P29,账簿!A:B,2,0) -> 昌邑市昌荣城乡建设有限公司 | W29: =X29&AB29&AD29 -> 0030122026-04-305 | X29: =P29 -> 003012 | Y29: =X29 -> 003012 | Z29: =Q29 -> 昌邑市昌荣城乡建设有限公司 | AA29: =LEFT(B29,7) -> 2026-04 | AB29: =B29 -> 2026-04-30 | AC29: 记 | AD29: =VALUE(_xlfn.TEXTAFTER(C29,"-")) -> 5 | AE29: =D29 -> 支付金融利息支出,2026-02-28,26372000000872431306,利息收入,山东博林供应链管理服务有限公司 | AF29: 谭雅心 | AG29: 谭雅心 | AN29: =M29 -> 220202 | AP29: =D29 -> 支付金融利息支出,2026-02-28,26372000000872431306,利息收入,山东博林供应链管理服务有限公司 | AQ29: CNY | AR29: =F29 | AS29: =G29 -> 29708.33 | AT29: 01 | AU29: * | AV29: 1 | AW29: =AR29 | AX29: =AS29 -> 29708.33 | BQ29: =IF(N29="项目",VLOOKUP(O29,项目!B:C,2,0),IF(K29="空项目",VLOOKUP(K29,项目!B:C,2,0),"")) | BR29: =IFERROR(VLOOKUP(BQ29,项目!A:B,2,0),"") | BU29: =IF(N29="供应商",VLOOKUP(O29,供应商!B:C,2,0),"") -> 0011769 | BV29: =IFERROR(VLOOKUP(BU29,供应商!A:B,2,0),"") -> 山东博林供应链管理服务有限公司 | BW29: =IF(N29="客户",VLOOKUP(O29,客户!B:C,2,0),"") | BX29: =IFERROR(VLOOKUP(BW29,客户!A:B,2,0),"") | CU29: =IF(N29="费用项目",VLOOKUP(O29,费用项目!B:C,2,0),"") | CV29: =IFERROR(VLOOKUP(CU29,费用项目!A:B,2,0),"") | CW29: =IF(N29="银行账户",VLOOKUP(O29,银行变二级!B:C,2,0),"") | CX29: =IFERROR(VLOOKUP(O29,银行变二级!A:B,2,0),"")
A30: 昌邑市昌荣城乡建设有限公司 | B30: 2026-04-30 | C30: 记-005 | D30: 支付金融利息支出,2026-03-24,26372000001300613776,利息收入,山东博林供应链管理服务有限公司 | E30: 220202 应付账款-明细应付款-山东博林供应链管理服务有限公司 | G30: 26833.33 | H30: =LEFT(E30,4) -> 2202 | I30: =IFERROR(LEFT(E30,FIND(" ",E30)-1),E30) -> 220202 | J30: =LEFT(MID(E30,FIND(" ",E30)+1,LEN(E30)),FIND("-",MID(E30,FIND(" ",E30)+1,LEN(E30))&"-")-1) -> 应付账款 | K30: =IFERROR(MID(MID(E30,FIND(" ",E30)+1,LEN(E30)),FIND("-",MID(E30,FIND(" ",E30)+1,LEN(E30)))+1,IFERROR(FIND("-",MID(E30,FIND(" ",E30)+1,LEN(E30)),FIND("-",MID(E30,FIND(" ",E30)+1,LEN(E30)))+1),LEN(MID(E30,FIND(" ",E30)+1,LEN(E30)))+1)-FIND("-",MID(E30,FIND(" ",E30)+1,LEN(E30)))-1),"") -> 明细应付款 | L30: =IFERROR(MID(MID(E30,FIND(" ",E30)+1,LEN(E30)),FIND("-",MID(E30,FIND(" ",E30)+1,LEN(E30)),FIND("-",MID(E30,FIND(" ",E30)+1,LEN(E30)))+1)+1,LEN(E30)),"") -> 山东博林供应链管理服务有限公司 | M30: =IFERROR(IF(H30="1002",1002,VLOOKUP(I30,亿企科目!A:H,6,0)),VLOOKUP(H30,亿企科目!A:G,6,0)) -> 220202 | N30: =IFERROR(IF(H30="1002","银行账户",IF(H30="1123","供应商",VLOOKUP(I30,亿企科目!A:H,8,0))),"") -> 供应商 | O30: =IF(N30=0,IF(M30="1002",K30,""),_xlfn.TEXTAFTER(E30,"-",-1)) -> 山东博林供应链管理服务有限公司 | P30: =VLOOKUP(A30,账簿!B:C,2,0) -> 003012 | Q30: =VLOOKUP(P30,账簿!A:B,2,0) -> 昌邑市昌荣城乡建设有限公司 | W30: =X30&AB30&AD30 -> 0030122026-04-305 | X30: =P30 -> 003012 | Y30: =X30 -> 003012 | Z30: =Q30 -> 昌邑市昌荣城乡建设有限公司 | AA30: =LEFT(B30,7) -> 2026-04 | AB30: =B30 -> 2026-04-30 | AC30: 记 | AD30: =VALUE(_xlfn.TEXTAFTER(C30,"-")) -> 5 | AE30: =D30 -> 支付金融利息支出,2026-03-24,26372000001300613776,利息收入,山东博林供应链管理服务有限公司 | AF30: 谭雅心 | AG30: 谭雅心 | AN30: =M30 -> 220202 | AP30: =D30 -> 支付金融利息支出,2026-03-24,26372000001300613776,利息收入,山东博林供应链管理服务有限公司 | AQ30: CNY | AR30: =F30 | AS30: =G30 -> 26833.33 | AT30: 01 | AU30: * | AV30: 1 | AW30: =AR30 | AX30: =AS30 -> 26833.33 | BQ30: =IF(N30="项目",VLOOKUP(O30,项目!B:C,2,0),IF(K30="空项目",VLOOKUP(K30,项目!B:C,2,0),"")) | BR30: =IFERROR(VLOOKUP(BQ30,项目!A:B,2,0),"") | BU30: =IF(N30="供应商",VLOOKUP(O30,供应商!B:C,2,0),"") -> 0011769 | BV30: =IFERROR(VLOOKUP(BU30,供应商!A:B,2,0),"") -> 山东博林供应链管理服务有限公司 | BW30: =IF(N30="客户",VLOOKUP(O30,客户!B:C,2,0),"") | BX30: =IFERROR(VLOOKUP(BW30,客户!A:B,2,0),"") | CU30: =IF(N30="费用项目",VLOOKUP(O30,费用项目!B:C,2,0),"") | CV30: =IFERROR(VLOOKUP(CU30,费用项目!A:B,2,0),"") | CW30: =IF(N30="银行账户",VLOOKUP(O30,银行变二级!B:C,2,0),"") | CX30: =IFERROR(VLOOKUP(O30,银行变二级!A:B,2,0),"")
A31: 昌邑市昌荣城乡建设有限公司 | B31: 2026-04-30 | C31: 记-005 | D31: 支付金融利息支出,2026-03-24,26372000001300613776,利息收入,山东博林供应链管理服务有限公司 | E31: 6603 财务费用-利息支出 | F31: -86249.99 | H31: =LEFT(E31,4) -> 6603 | I31: =IFERROR(LEFT(E31,FIND(" ",E31)-1),E31) -> 6603 | J31: =LEFT(MID(E31,FIND(" ",E31)+1,LEN(E31)),FIND("-",MID(E31,FIND(" ",E31)+1,LEN(E31))&"-")-1) -> 财务费用 | K31: =IFERROR(MID(MID(E31,FIND(" ",E31)+1,LEN(E31)),FIND("-",MID(E31,FIND(" ",E31)+1,LEN(E31)))+1,IFERROR(FIND("-",MID(E31,FIND(" ",E31)+1,LEN(E31)),FIND("-",MID(E31,FIND(" ",E31)+1,LEN(E31)))+1),LEN(MID(E31,FIND(" ",E31)+1,LEN(E31)))+1)-FIND("-",MID(E31,FIND(" ",E31)+1,LEN(E31)))-1),"") -> 利息支出 | L31: =IFERROR(MID(MID(E31,FIND(" ",E31)+1,LEN(E31)),FIND("-",MID(E31,FIND(" ",E31)+1,LEN(E31)),FIND("-",MID(E31,FIND(" ",E31)+1,LEN(E31)))+1)+1,LEN(E31)),"") | M31: =IFERROR(IF(H31="1002",1002,VLOOKUP(I31,亿企科目!A:H,6,0)),VLOOKUP(H31,亿企科目!A:G,6,0)) -> 6603 | N31: =IFERROR(IF(H31="1002","银行账户",IF(H31="1123","供应商",VLOOKUP(I31,亿企科目!A:H,8,0))),"") -> 费用项目 | O31: =IF(N31=0,IF(M31="1002",K31,""),_xlfn.TEXTAFTER(E31,"-",-1)) -> 利息支出 | P31: =VLOOKUP(A31,账簿!B:C,2,0) -> 003012 | Q31: =VLOOKUP(P31,账簿!A:B,2,0) -> 昌邑市昌荣城乡建设有限公司 | W31: =X31&AB31&AD31 -> 0030122026-04-305 | X31: =P31 -> 003012 | Y31: =X31 -> 003012 | Z31: =Q31 -> 昌邑市昌荣城乡建设有限公司 | AA31: =LEFT(B31,7) -> 2026-04 | AB31: =B31 -> 2026-04-30 | AC31: 记 | AD31: =VALUE(_xlfn.TEXTAFTER(C31,"-")) -> 5 | AE31: =D31 -> 支付金融利息支出,2026-03-24,26372000001300613776,利息收入,山东博林供应链管理服务有限公司 | AF31: 谭雅心 | AG31: 谭雅心 | AN31: =M31 -> 6603 | AP31: =D31 -> 支付金融利息支出,2026-03-24,26372000001300613776,利息收入,山东博林供应链管理服务有限公司 | AQ31: CNY | AR31: =F31 -> -86249.99 | AS31: =G31 | AT31: 01 | AU31: * | AV31: 1 | AW31: =AR31 -> -86249.99 | AX31: =AS31 | BQ31: =IF(N31="项目",VLOOKUP(O31,项目!B:C,2,0),IF(K31="空项目",VLOOKUP(K31,项目!B:C,2,0),"")) | BR31: =IFERROR(VLOOKUP(BQ31,项目!A:B,2,0),"") | BU31: =IF(N31="供应商",VLOOKUP(O31,供应商!B:C,2,0),"") | BV31: =IFERROR(VLOOKUP(BU31,供应商!A:B,2,0),"") | BW31: =IF(N31="客户",VLOOKUP(O31,客户!B:C,2,0),"") | BX31: =IFERROR(VLOOKUP(BW31,客户!A:B,2,0),"") | CU31: =IF(N31="费用项目",VLOOKUP(O31,费用项目!B:C,2,0),"") -> 660302 | CV31: =IFERROR(VLOOKUP(CU31,费用项目!A:B,2,0),"") -> 利息支出 | CW31: =IF(N31="银行账户",VLOOKUP(O31,银行变二级!B:C,2,0),"") | CX31: =IFERROR(VLOOKUP(O31,银行变二级!A:B,2,0),"")
A32: 昌邑市昌荣城乡建设有限公司 | B32: 2026-04-30 | C32: 记-005 | D32: 支付金融利息支出,2026-03-24,26372000001300613776,利息收入,山东博林供应链管理服务有限公司 | E32: 220202 应付账款-明细应付款-山东博林供应链管理服务有限公司 | G32: -86249.99 | H32: =LEFT(E32,4) -> 2202 | I32: =IFERROR(LEFT(E32,FIND(" ",E32)-1),E32) -> 220202 | J32: =LEFT(MID(E32,FIND(" ",E32)+1,LEN(E32)),FIND("-",MID(E32,FIND(" ",E32)+1,LEN(E32))&"-")-1) -> 应付账款 | K32: =IFERROR(MID(MID(E32,FIND(" ",E32)+1,LEN(E32)),FIND("-",MID(E32,FIND(" ",E32)+1,LEN(E32)))+1,IFERROR(FIND("-",MID(E32,FIND(" ",E32)+1,LEN(E32)),FIND("-",MID(E32,FIND(" ",E32)+1,LEN(E32)))+1),LEN(MID(E32,FIND(" ",E32)+1,LEN(E32)))+1)-FIND("-",MID(E32,FIND(" ",E32)+1,LEN(E32)))-1),"") -> 明细应付款 | L32: =IFERROR(MID(MID(E32,FIND(" ",E32)+1,LEN(E32)),FIND("-",MID(E32,FIND(" ",E32)+1,LEN(E32)),FIND("-",MID(E32,FIND(" ",E32)+1,LEN(E32)))+1)+1,LEN(E32)),"") -> 山东博林供应链管理服务有限公司 | M32: =IFERROR(IF(H32="1002",1002,VLOOKUP(I32,亿企科目!A:H,6,0)),VLOOKUP(H32,亿企科目!A:G,6,0)) -> 220202 | N32: =IFERROR(IF(H32="1002","银行账户",IF(H32="1123","供应商",VLOOKUP(I32,亿企科目!A:H,8,0))),"") -> 供应商 | O32: =IF(N32=0,IF(M32="1002",K32,""),_xlfn.TEXTAFTER(E32,"-",-1)) -> 山东博林供应链管理服务有限公司 | P32: =VLOOKUP(A32,账簿!B:C,2,0) -> 003012 | Q32: =VLOOKUP(P32,账簿!A:B,2,0) -> 昌邑市昌荣城乡建设有限公司 | W32: =X32&AB32&AD32 -> 0030122026-04-305 | X32: =P32 -> 003012 | Y32: =X32 -> 003012 | Z32: =Q32 -> 昌邑市昌荣城乡建设有限公司 | AA32: =LEFT(B32,7) -> 2026-04 | AB32: =B32 -> 2026-04-30 | AC32: 记 | AD32: =VALUE(_xlfn.TEXTAFTER(C32,"-")) -> 5 | AE32: =D32 -> 支付金融利息支出,2026-03-24,26372000001300613776,利息收入,山东博林供应链管理服务有限公司 | AF32: 谭雅心 | AG32: 谭雅心 | AN32: =M32 -> 220202 | AP32: =D32 -> 支付金融利息支出,2026-03-24,26372000001300613776,利息收入,山东博林供应链管理服务有限公司 | AQ32: CNY | AR32: =F32 | AS32: =G32 -> -86249.99 | AT32: 01 | AU32: * | AV32: 1 | AW32: =AR32 | AX32: =AS32 -> -86249.99 | BQ32: =IF(N32="项目",VLOOKUP(O32,项目!B:C,2,0),IF(K32="空项目",VLOOKUP(K32,项目!B:C,2,0),"")) | BR32: =IFERROR(VLOOKUP(BQ32,项目!A:B,2,0),"") | BU32: =IF(N32="供应商",VLOOKUP(O32,供应商!B:C,2,0),"") -> 0011769 | BV32: =IFERROR(VLOOKUP(BU32,供应商!A:B,2,0),"") -> 山东博林供应链管理服务有限公司 | BW32: =IF(N32="客户",VLOOKUP(O32,客户!B:C,2,0),"") | BX32: =IFERROR(VLOOKUP(BW32,客户!A:B,2,0),"") | CU32: =IF(N32="费用项目",VLOOKUP(O32,费用项目!B:C,2,0),"") | CV32: =IFERROR(VLOOKUP(CU32,费用项目!A:B,2,0),"") | CW32: =IF(N32="银行账户",VLOOKUP(O32,银行变二级!B:C,2,0),"") | CX32: =IFERROR(VLOOKUP(O32,银行变二级!A:B,2,0),"")
A33: 昌邑市昌荣城乡建设有限公司 | B33: 2026-04-30 | C33: 记-006 | D33: 支付金融利息支出,2026-04-28,26372000001964444461,利息收入,山东博林供应链管理服务有限公司 | E33: 6603 财务费用-利息支出 | F33: 29708.33 | H33: =LEFT(E33,4) -> 6603 | I33: =IFERROR(LEFT(E33,FIND(" ",E33)-1),E33) -> 6603 | J33: =LEFT(MID(E33,FIND(" ",E33)+1,LEN(E33)),FIND("-",MID(E33,FIND(" ",E33)+1,LEN(E33))&"-")-1) -> 财务费用 | K33: =IFERROR(MID(MID(E33,FIND(" ",E33)+1,LEN(E33)),FIND("-",MID(E33,FIND(" ",E33)+1,LEN(E33)))+1,IFERROR(FIND("-",MID(E33,FIND(" ",E33)+1,LEN(E33)),FIND("-",MID(E33,FIND(" ",E33)+1,LEN(E33)))+1),LEN(MID(E33,FIND(" ",E33)+1,LEN(E33)))+1)-FIND("-",MID(E33,FIND(" ",E33)+1,LEN(E33)))-1),"") -> 利息支出 | L33: =IFERROR(MID(MID(E33,FIND(" ",E33)+1,LEN(E33)),FIND("-",MID(E33,FIND(" ",E33)+1,LEN(E33)),FIND("-",MID(E33,FIND(" ",E33)+1,LEN(E33)))+1)+1,LEN(E33)),"") | M33: =IFERROR(IF(H33="1002",1002,VLOOKUP(I33,亿企科目!A:H,6,0)),VLOOKUP(H33,亿企科目!A:G,6,0)) -> 6603 | N33: =IFERROR(IF(H33="1002","银行账户",IF(H33="1123","供应商",VLOOKUP(I33,亿企科目!A:H,8,0))),"") -> 费用项目 | O33: =IF(N33=0,IF(M33="1002",K33,""),_xlfn.TEXTAFTER(E33,"-",-1)) -> 利息支出 | P33: =VLOOKUP(A33,账簿!B:C,2,0) -> 003012 | Q33: =VLOOKUP(P33,账簿!A:B,2,0) -> 昌邑市昌荣城乡建设有限公司 | W33: =X33&AB33&AD33 -> 0030122026-04-306 | X33: =P33 -> 003012 | Y33: =X33 -> 003012 | Z33: =Q33 -> 昌邑市昌荣城乡建设有限公司 | AA33: =LEFT(B33,7) -> 2026-04 | AB33: =B33 -> 2026-04-30 | AC33: 记 | AD33: =VALUE(_xlfn.TEXTAFTER(C33,"-")) -> 6 | AE33: =D33 -> 支付金融利息支出,2026-04-28,26372000001964444461,利息收入,山东博林供应链管理服务有限公司 | AF33: 谭雅心 | AG33: 谭雅心 | AN33: =M33 -> 6603 | AP33: =D33 -> 支付金融利息支出,2026-04-28,26372000001964444461,利息收入,山东博林供应链管理服务有限公司 | AQ33: CNY | AR33: =F33 -> 29708.33 | AS33: =G33 | AT33: 01 | AU33: * | AV33: 1 | AW33: =AR33 -> 29708.33 | AX33: =AS33 | BQ33: =IF(N33="项目",VLOOKUP(O33,项目!B:C,2,0),IF(K33="空项目",VLOOKUP(K33,项目!B:C,2,0),"")) | BR33: =IFERROR(VLOOKUP(BQ33,项目!A:B,2,0),"") | BU33: =IF(N33="供应商",VLOOKUP(O33,供应商!B:C,2,0),"") | BV33: =IFERROR(VLOOKUP(BU33,供应商!A:B,2,0),"") | BW33: =IF(N33="客户",VLOOKUP(O33,客户!B:C,2,0),"") | BX33: =IFERROR(VLOOKUP(BW33,客户!A:B,2,0),"") | CU33: =IF(N33="费用项目",VLOOKUP(O33,费用项目!B:C,2,0),"") -> 660302 | CV33: =IFERROR(VLOOKUP(CU33,费用项目!A:B,2,0),"") -> 利息支出 | CW33: =IF(N33="银行账户",VLOOKUP(O33,银行变二级!B:C,2,0),"") | CX33: =IFERROR(VLOOKUP(O33,银行变二级!A:B,2,0),"")
A34: 昌邑市昌荣城乡建设有限公司 | B34: 2026-04-30 | C34: 记-006 | D34: 支付金融利息支出,2026-04-28,26372000001964444461,利息收入,山东博林供应链管理服务有限公司 | E34: 220202 应付账款-明细应付款-山东博林供应链管理服务有限公司 | G34: 29708.33 | H34: =LEFT(E34,4) -> 2202 | I34: =IFERROR(LEFT(E34,FIND(" ",E34)-1),E34) -> 220202 | J34: =LEFT(MID(E34,FIND(" ",E34)+1,LEN(E34)),FIND("-",MID(E34,FIND(" ",E34)+1,LEN(E34))&"-")-1) -> 应付账款 | K34: =IFERROR(MID(MID(E34,FIND(" ",E34)+1,LEN(E34)),FIND("-",MID(E34,FIND(" ",E34)+1,LEN(E34)))+1,IFERROR(FIND("-",MID(E34,FIND(" ",E34)+1,LEN(E34)),FIND("-",MID(E34,FIND(" ",E34)+1,LEN(E34)))+1),LEN(MID(E34,FIND(" ",E34)+1,LEN(E34)))+1)-FIND("-",MID(E34,FIND(" ",E34)+1,LEN(E34)))-1),"") -> 明细应付款 | L34: =IFERROR(MID(MID(E34,FIND(" ",E34)+1,LEN(E34)),FIND("-",MID(E34,FIND(" ",E34)+1,LEN(E34)),FIND("-",MID(E34,FIND(" ",E34)+1,LEN(E34)))+1)+1,LEN(E34)),"") -> 山东博林供应链管理服务有限公司 | M34: =IFERROR(IF(H34="1002",1002,VLOOKUP(I34,亿企科目!A:H,6,0)),VLOOKUP(H34,亿企科目!A:G,6,0)) -> 220202 | N34: =IFERROR(IF(H34="1002","银行账户",IF(H34="1123","供应商",VLOOKUP(I34,亿企科目!A:H,8,0))),"") -> 供应商 | O34: =IF(N34=0,IF(M34="1002",K34,""),_xlfn.TEXTAFTER(E34,"-",-1)) -> 山东博林供应链管理服务有限公司 | P34: =VLOOKUP(A34,账簿!B:C,2,0) -> 003012 | Q34: =VLOOKUP(P34,账簿!A:B,2,0) -> 昌邑市昌荣城乡建设有限公司 | W34: =X34&AB34&AD34 -> 0030122026-04-306 | X34: =P34 -> 003012 | Y34: =X34 -> 003012 | Z34: =Q34 -> 昌邑市昌荣城乡建设有限公司 | AA34: =LEFT(B34,7) -> 2026-04 | AB34: =B34 -> 2026-04-30 | AC34: 记 | AD34: =VALUE(_xlfn.TEXTAFTER(C34,"-")) -> 6 | AE34: =D34 -> 支付金融利息支出,2026-04-28,26372000001964444461,利息收入,山东博林供应链管理服务有限公司 | AF34: 谭雅心 | AG34: 谭雅心 | AN34: =M34 -> 220202 | AP34: =D34 -> 支付金融利息支出,2026-04-28,26372000001964444461,利息收入,山东博林供应链管理服务有限公司 | AQ34: CNY | AR34: =F34 | AS34: =G34 -> 29708.33 | AT34: 01 | AU34: * | AV34: 1 | AW34: =AR34 | AX34: =AS34 -> 29708.33 | BQ34: =IF(N34="项目",VLOOKUP(O34,项目!B:C,2,0),IF(K34="空项目",VLOOKUP(K34,项目!B:C,2,0),"")) | BR34: =IFERROR(VLOOKUP(BQ34,项目!A:B,2,0),"") | BU34: =IF(N34="供应商",VLOOKUP(O34,供应商!B:C,2,0),"") -> 0011769 | BV34: =IFERROR(VLOOKUP(BU34,供应商!A:B,2,0),"") -> 山东博林供应链管理服务有限公司 | BW34: =IF(N34="客户",VLOOKUP(O34,客户!B:C,2,0),"") | BX34: =IFERROR(VLOOKUP(BW34,客户!A:B,2,0),"") | CU34: =IF(N34="费用项目",VLOOKUP(O34,费用项目!B:C,2,0),"") | CV34: =IFERROR(VLOOKUP(CU34,费用项目!A:B,2,0),"") | CW34: =IF(N34="银行账户",VLOOKUP(O34,银行变二级!B:C,2,0),"") | CX34: =IFERROR(VLOOKUP(O34,银行变二级!A:B,2,0),"")
A35: 昌邑市昌荣城乡建设有限公司 | B35: 2026-04-30 | C35: 记-007 | D35: 调整四方协议 | E35: 224102 其他应付款-单位-昌邑市昌宜投资有限公司 | F35: 19000000 | H35: =LEFT(E35,4) -> 2241 | I35: =IFERROR(LEFT(E35,FIND(" ",E35)-1),E35) -> 224102 | J35: =LEFT(MID(E35,FIND(" ",E35)+1,LEN(E35)),FIND("-",MID(E35,FIND(" ",E35)+1,LEN(E35))&"-")-1) -> 其他应付款 | K35: =IFERROR(MID(MID(E35,FIND(" ",E35)+1,LEN(E35)),FIND("-",MID(E35,FIND(" ",E35)+1,LEN(E35)))+1,IFERROR(FIND("-",MID(E35,FIND(" ",E35)+1,LEN(E35)),FIND("-",MID(E35,FIND(" ",E35)+1,LEN(E35)))+1),LEN(MID(E35,FIND(" ",E35)+1,LEN(E35)))+1)-FIND("-",MID(E35,FIND(" ",E35)+1,LEN(E35)))-1),"") -> 单位 | L35: =IFERROR(MID(MID(E35,FIND(" ",E35)+1,LEN(E35)),FIND("-",MID(E35,FIND(" ",E35)+1,LEN(E35)),FIND("-",MID(E35,FIND(" ",E35)+1,LEN(E35)))+1)+1,LEN(E35)),"") -> 昌邑市昌宜投资有限公司 | M35: =IFERROR(IF(H35="1002",1002,VLOOKUP(I35,亿企科目!A:H,6,0)),VLOOKUP(H35,亿企科目!A:G,6,0)) -> 224102 | N35: =IFERROR(IF(H35="1002","银行账户",IF(H35="1123","供应商",VLOOKUP(I35,亿企科目!A:H,8,0))),"") -> 供应商 | O35: =IF(N35=0,IF(M35="1002",K35,""),_xlfn.TEXTAFTER(E35,"-",-1)) -> 昌邑市昌宜投资有限公司 | P35: =VLOOKUP(A35,账簿!B:C,2,0) -> 003012 | Q35: =VLOOKUP(P35,账簿!A:B,2,0) -> 昌邑市昌荣城乡建设有限公司 | W35: =X35&AB35&AD35 -> 0030122026-04-307 | X35: =P35 -> 003012 | Y35: =X35 -> 003012 | Z35: =Q35 -> 昌邑市昌荣城乡建设有限公司 | AA35: =LEFT(B35,7) -> 2026-04 | AB35: =B35 -> 2026-04-30 | AC35: 记 | AD35: =VALUE(_xlfn.TEXTAFTER(C35,"-")) -> 7 | AE35: =D35 -> 调整四方协议 | AF35: 谭雅心 | AG35: 谭雅心 | AN35: =M35 -> 224102 | AP35: =D35 -> 调整四方协议 | AQ35: CNY | AR35: =F35 -> 19000000 | AS35: =G35 | AT35: 01 | AU35: * | AV35: 1 | AW35: =AR35 -> 19000000 | AX35: =AS35 | BQ35: =IF(N35="项目",VLOOKUP(O35,项目!B:C,2,0),IF(K35="空项目",VLOOKUP(K35,项目!B:C,2,0),"")) | BR35: =IFERROR(VLOOKUP(BQ35,项目!A:B,2,0),"") | BU35: =IF(N35="供应商",VLOOKUP(O35,供应商!B:C,2,0),"") -> 003019 | BV35: =IFERROR(VLOOKUP(BU35,供应商!A:B,2,0),"") -> 昌邑市昌宜投资有限公司 | BW35: =IF(N35="客户",VLOOKUP(O35,客户!B:C,2,0),"") | BX35: =IFERROR(VLOOKUP(BW35,客户!A:B,2,0),"") | CU35: =IF(N35="费用项目",VLOOKUP(O35,费用项目!B:C,2,0),"") | CV35: =IFERROR(VLOOKUP(CU35,费用项目!A:B,2,0),"") | CW35: =IF(N35="银行账户",VLOOKUP(O35,银行变二级!B:C,2,0),"") | CX35: =IFERROR(VLOOKUP(O35,银行变二级!A:B,2,0),"")
A36: 昌邑市昌荣城乡建设有限公司 | B36: 2026-04-30 | C36: 记-007 | D36: 调整四方协议 | E36: 224102 其他应付款-单位-昌邑市惠合智能产业园投资有限公司 | G36: 19000000 | H36: =LEFT(E36,4) -> 2241 | I36: =IFERROR(LEFT(E36,FIND(" ",E36)-1),E36) -> 224102 | J36: =LEFT(MID(E36,FIND(" ",E36)+1,LEN(E36)),FIND("-",MID(E36,FIND(" ",E36)+1,LEN(E36))&"-")-1) -> 其他应付款 | K36: =IFERROR(MID(MID(E36,FIND(" ",E36)+1,LEN(E36)),FIND("-",MID(E36,FIND(" ",E36)+1,LEN(E36)))+1,IFERROR(FIND("-",MID(E36,FIND(" ",E36)+1,LEN(E36)),FIND("-",MID(E36,FIND(" ",E36)+1,LEN(E36)))+1),LEN(MID(E36,FIND(" ",E36)+1,LEN(E36)))+1)-FIND("-",MID(E36,FIND(" ",E36)+1,LEN(E36)))-1),"") -> 单位 | L36: =IFERROR(MID(MID(E36,FIND(" ",E36)+1,LEN(E36)),FIND("-",MID(E36,FIND(" ",E36)+1,LEN(E36)),FIND("-",MID(E36,FIND(" ",E36)+1,LEN(E36)))+1)+1,LEN(E36)),"") -> 昌邑市惠合智能产业园投资有限公司 | M36: =IFERROR(IF(H36="1002",1002,VLOOKUP(I36,亿企科目!A:H,6,0)),VLOOKUP(H36,亿企科目!A:G,6,0)) -> 224102 | N36: =IFERROR(IF(H36="1002","银行账户",IF(H36="1123","供应商",VLOOKUP(I36,亿企科目!A:H,8,0))),"") -> 供应商 | O36: =IF(N36=0,IF(M36="1002",K36,""),_xlfn.TEXTAFTER(E36,"-",-1)) -> 昌邑市惠合智能产业园投资有限公司 | P36: =VLOOKUP(A36,账簿!B:C,2,0) -> 003012 | Q36: =VLOOKUP(P36,账簿!A:B,2,0) -> 昌邑市昌荣城乡建设有限公司 | W36: =X36&AB36&AD36 -> 0030122026-04-307 | X36: =P36 -> 003012 | Y36: =X36 -> 003012 | Z36: =Q36 -> 昌邑市昌荣城乡建设有限公司 | AA36: =LEFT(B36,7) -> 2026-04 | AB36: =B36 -> 2026-04-30 | AC36: 记 | AD36: =VALUE(_xlfn.TEXTAFTER(C36,"-")) -> 7 | AE36: =D36 -> 调整四方协议 | AF36: 谭雅心 | AG36: 谭雅心 | AN36: =M36 -> 224102 | AP36: =D36 -> 调整四方协议 | AQ36: CNY | AR36: =F36 | AS36: =G36 -> 19000000 | AT36: 01 | AU36: * | AV36: 1 | AW36: =AR36 | AX36: =AS36 -> 19000000 | BQ36: =IF(N36="项目",VLOOKUP(O36,项目!B:C,2,0),IF(K36="空项目",VLOOKUP(K36,项目!B:C,2,0),"")) | BR36: =IFERROR(VLOOKUP(BQ36,项目!A:B,2,0),"") | BU36: =IF(N36="供应商",VLOOKUP(O36,供应商!B:C,2,0),"") -> 001001004 | BV36: =IFERROR(VLOOKUP(BU36,供应商!A:B,2,0),"") -> 昌邑市惠合智能产业园投资有限公司 | BW36: =IF(N36="客户",VLOOKUP(O36,客户!B:C,2,0),"") | BX36: =IFERROR(VLOOKUP(BW36,客户!A:B,2,0),"") | CU36: =IF(N36="费用项目",VLOOKUP(O36,费用项目!B:C,2,0),"") | CV36: =IFERROR(VLOOKUP(CU36,费用项目!A:B,2,0),"") | CW36: =IF(N36="银行账户",VLOOKUP(O36,银行变二级!B:C,2,0),"") | CX36: =IFERROR(VLOOKUP(O36,银行变二级!A:B,2,0),"")
A37: 昌邑市昌荣城乡建设有限公司 | B37: 2026-04-30 | C37: 记-008 | D37: 调整四方协议 | E37: 122108 其他应收款-单位-昌邑市昌盛管网建设投资有限公司 | F37: 9500000 | H37: =LEFT(E37,4) -> 1221 | I37: =IFERROR(LEFT(E37,FIND(" ",E37)-1),E37) -> 122108 | J37: =LEFT(MID(E37,FIND(" ",E37)+1,LEN(E37)),FIND("-",MID(E37,FIND(" ",E37)+1,LEN(E37))&"-")-1) -> 其他应收款 | K37: =IFERROR(MID(MID(E37,FIND(" ",E37)+1,LEN(E37)),FIND("-",MID(E37,FIND(" ",E37)+1,LEN(E37)))+1,IFERROR(FIND("-",MID(E37,FIND(" ",E37)+1,LEN(E37)),FIND("-",MID(E37,FIND(" ",E37)+1,LEN(E37)))+1),LEN(MID(E37,FIND(" ",E37)+1,LEN(E37)))+1)-FIND("-",MID(E37,FIND(" ",E37)+1,LEN(E37)))-1),"") -> 单位 | L37: =IFERROR(MID(MID(E37,FIND(" ",E37)+1,LEN(E37)),FIND("-",MID(E37,FIND(" ",E37)+1,LEN(E37)),FIND("-",MID(E37,FIND(" ",E37)+1,LEN(E37)))+1)+1,LEN(E37)),"") -> 昌邑市昌盛管网建设投资有限公司 | M37: =IFERROR(IF(H37="1002",1002,VLOOKUP(I37,亿企科目!A:H,6,0)),VLOOKUP(H37,亿企科目!A:G,6,0)) -> 122102 | N37: =IFERROR(IF(H37="1002","银行账户",IF(H37="1123","供应商",VLOOKUP(I37,亿企科目!A:H,8,0))),"") -> 客户 | O37: =IF(N37=0,IF(M37="1002",K37,""),_xlfn.TEXTAFTER(E37,"-",-1)) -> 昌邑市昌盛管网建设投资有限公司 | P37: =VLOOKUP(A37,账簿!B:C,2,0) -> 003012 | Q37: =VLOOKUP(P37,账簿!A:B,2,0) -> 昌邑市昌荣城乡建设有限公司 | W37: =X37&AB37&AD37 -> 0030122026-04-308 | X37: =P37 -> 003012 | Y37: =X37 -> 003012 | Z37: =Q37 -> 昌邑市昌荣城乡建设有限公司 | AA37: =LEFT(B37,7) -> 2026-04 | AB37: =B37 -> 2026-04-30 | AC37: 记 | AD37: =VALUE(_xlfn.TEXTAFTER(C37,"-")) -> 8 | AE37: =D37 -> 调整四方协议 | AF37: 谭雅心 | AG37: 谭雅心 | AN37: =M37 -> 122102 | AP37: =D37 -> 调整四方协议 | AQ37: CNY | AR37: =F37 -> 9500000 | AS37: =G37 | AT37: 01 | AU37: * | AV37: 1 | AW37: =AR37 -> 9500000 | AX37: =AS37 | BQ37: =IF(N37="项目",VLOOKUP(O37,项目!B:C,2,0),IF(K37="空项目",VLOOKUP(K37,项目!B:C,2,0),"")) | BR37: =IFERROR(VLOOKUP(BQ37,项目!A:B,2,0),"") | BU37: =IF(N37="供应商",VLOOKUP(O37,供应商!B:C,2,0),"") | BV37: =IFERROR(VLOOKUP(BU37,供应商!A:B,2,0),"") | BW37: =IF(N37="客户",VLOOKUP(O37,客户!B:C,2,0),"") -> 001001001 | BX37: =IFERROR(VLOOKUP(BW37,客户!A:B,2,0),"") -> 昌邑市昌盛管网建设投资有限公司 | CU37: =IF(N37="费用项目",VLOOKUP(O37,费用项目!B:C,2,0),"") | CV37: =IFERROR(VLOOKUP(CU37,费用项目!A:B,2,0),"") | CW37: =IF(N37="银行账户",VLOOKUP(O37,银行变二级!B:C,2,0),"") | CX37: =IFERROR(VLOOKUP(O37,银行变二级!A:B,2,0),"")
A38: 昌邑市昌荣城乡建设有限公司 | B38: 2026-04-30 | C38: 记-008 | D38: 调整四方协议 | E38: 122108 其他应收款-单位-山东盛汇经贸有限公司 | G38: 9500000 | H38: =LEFT(E38,4) -> 1221 | I38: =IFERROR(LEFT(E38,FIND(" ",E38)-1),E38) -> 122108 | J38: =LEFT(MID(E38,FIND(" ",E38)+1,LEN(E38)),FIND("-",MID(E38,FIND(" ",E38)+1,LEN(E38))&"-")-1) -> 其他应收款 | K38: =IFERROR(MID(MID(E38,FIND(" ",E38)+1,LEN(E38)),FIND("-",MID(E38,FIND(" ",E38)+1,LEN(E38)))+1,IFERROR(FIND("-",MID(E38,FIND(" ",E38)+1,LEN(E38)),FIND("-",MID(E38,FIND(" ",E38)+1,LEN(E38)))+1),LEN(MID(E38,FIND(" ",E38)+1,LEN(E38)))+1)-FIND("-",MID(E38,FIND(" ",E38)+1,LEN(E38)))-1),"") -> 单位 | L38: =IFERROR(MID(MID(E38,FIND(" ",E38)+1,LEN(E38)),FIND("-",MID(E38,FIND(" ",E38)+1,LEN(E38)),FIND("-",MID(E38,FIND(" ",E38)+1,LEN(E38)))+1)+1,LEN(E38)),"") -> 山东盛汇经贸有限公司 | M38: =IFERROR(IF(H38="1002",1002,VLOOKUP(I38,亿企科目!A:H,6,0)),VLOOKUP(H38,亿企科目!A:G,6,0)) -> 122102 | N38: =IFERROR(IF(H38="1002","银行账户",IF(H38="1123","供应商",VLOOKUP(I38,亿企科目!A:H,8,0))),"") -> 客户 | O38: =IF(N38=0,IF(M38="1002",K38,""),_xlfn.TEXTAFTER(E38,"-",-1)) -> 山东盛汇经贸有限公司 | P38: =VLOOKUP(A38,账簿!B:C,2,0) -> 003012 | Q38: =VLOOKUP(P38,账簿!A:B,2,0) -> 昌邑市昌荣城乡建设有限公司 | W38: =X38&AB38&AD38 -> 0030122026-04-308 | X38: =P38 -> 003012 | Y38: =X38 -> 003012 | Z38: =Q38 -> 昌邑市昌荣城乡建设有限公司 | AA38: =LEFT(B38,7) -> 2026-04 | AB38: =B38 -> 2026-04-30 | AC38: 记 | AD38: =VALUE(_xlfn.TEXTAFTER(C38,"-")) -> 8 | AE38: =D38 -> 调整四方协议 | AF38: 谭雅心 | AG38: 谭雅心 | AN38: =M38 -> 122102 | AP38: =D38 -> 调整四方协议 | AQ38: CNY | AR38: =F38 | AS38: =G38 -> 9500000 | AT38: 01 | AU38: * | AV38: 1 | AW38: =AR38 | AX38: =AS38 -> 9500000 | BQ38: =IF(N38="项目",VLOOKUP(O38,项目!B:C,2,0),IF(K38="空项目",VLOOKUP(K38,项目!B:C,2,0),"")) | BR38: =IFERROR(VLOOKUP(BQ38,项目!A:B,2,0),"") | BU38: =IF(N38="供应商",VLOOKUP(O38,供应商!B:C,2,0),"") | BV38: =IFERROR(VLOOKUP(BU38,供应商!A:B,2,0),"") | BW38: =IF(N38="客户",VLOOKUP(O38,客户!B:C,2,0),"") -> 001001007 | BX38: =IFERROR(VLOOKUP(BW38,客户!A:B,2,0),"") -> 山东盛汇经贸有限公司 | CU38: =IF(N38="费用项目",VLOOKUP(O38,费用项目!B:C,2,0),"") | CV38: =IFERROR(VLOOKUP(CU38,费用项目!A:B,2,0),"") | CW38: =IF(N38="银行账户",VLOOKUP(O38,银行变二级!B:C,2,0),"") | CX38: =IFERROR(VLOOKUP(O38,银行变二级!A:B,2,0),"")
A39: 昌邑市昌荣城乡建设有限公司 | B39: 2026-04-30 | C39: 记-009 | D39: 调整四方协议 | E39: 224102 其他应付款-单位-山东昌盛供应链有限公司 | F39: 50000000 | H39: =LEFT(E39,4) -> 2241 | I39: =IFERROR(LEFT(E39,FIND(" ",E39)-1),E39) -> 224102 | J39: =LEFT(MID(E39,FIND(" ",E39)+1,LEN(E39)),FIND("-",MID(E39,FIND(" ",E39)+1,LEN(E39))&"-")-1) -> 其他应付款 | K39: =IFERROR(MID(MID(E39,FIND(" ",E39)+1,LEN(E39)),FIND("-",MID(E39,FIND(" ",E39)+1,LEN(E39)))+1,IFERROR(FIND("-",MID(E39,FIND(" ",E39)+1,LEN(E39)),FIND("-",MID(E39,FIND(" ",E39)+1,LEN(E39)))+1),LEN(MID(E39,FIND(" ",E39)+1,LEN(E39)))+1)-FIND("-",MID(E39,FIND(" ",E39)+1,LEN(E39)))-1),"") -> 单位 | L39: =IFERROR(MID(MID(E39,FIND(" ",E39)+1,LEN(E39)),FIND("-",MID(E39,FIND(" ",E39)+1,LEN(E39)),FIND("-",MID(E39,FIND(" ",E39)+1,LEN(E39)))+1)+1,LEN(E39)),"") -> 山东昌盛供应链有限公司 | M39: =IFERROR(IF(H39="1002",1002,VLOOKUP(I39,亿企科目!A:H,6,0)),VLOOKUP(H39,亿企科目!A:G,6,0)) -> 224102 | N39: =IFERROR(IF(H39="1002","银行账户",IF(H39="1123","供应商",VLOOKUP(I39,亿企科目!A:H,8,0))),"") -> 供应商 | O39: =IF(N39=0,IF(M39="1002",K39,""),_xlfn.TEXTAFTER(E39,"-",-1)) -> 山东昌盛供应链有限公司 | P39: =VLOOKUP(A39,账簿!B:C,2,0) -> 003012 | Q39: =VLOOKUP(P39,账簿!A:B,2,0) -> 昌邑市昌荣城乡建设有限公司 | W39: =X39&AB39&AD39 -> 0030122026-04-309 | X39: =P39 -> 003012 | Y39: =X39 -> 003012 | Z39: =Q39 -> 昌邑市昌荣城乡建设有限公司 | AA39: =LEFT(B39,7) -> 2026-04 | AB39: =B39 -> 2026-04-30 | AC39: 记 | AD39: =VALUE(_xlfn.TEXTAFTER(C39,"-")) -> 9 | AE39: =D39 -> 调整四方协议 | AF39: 谭雅心 | AG39: 谭雅心 | AN39: =M39 -> 224102 | AP39: =D39 -> 调整四方协议 | AQ39: CNY | AR39: =F39 -> 50000000 | AS39: =G39 | AT39: 01 | AU39: * | AV39: 1 | AW39: =AR39 -> 50000000 | AX39: =AS39 | BQ39: =IF(N39="项目",VLOOKUP(O39,项目!B:C,2,0),IF(K39="空项目",VLOOKUP(K39,项目!B:C,2,0),"")) | BR39: =IFERROR(VLOOKUP(BQ39,项目!A:B,2,0),"") | BU39: =IF(N39="供应商",VLOOKUP(O39,供应商!B:C,2,0),"") -> 002015 | BV39: =IFERROR(VLOOKUP(BU39,供应商!A:B,2,0),"") -> 山东昌盛供应链有限公司 | BW39: =IF(N39="客户",VLOOKUP(O39,客户!B:C,2,0),"") | BX39: =IFERROR(VLOOKUP(BW39,客户!A:B,2,0),"") | CU39: =IF(N39="费用项目",VLOOKUP(O39,费用项目!B:C,2,0),"") | CV39: =IFERROR(VLOOKUP(CU39,费用项目!A:B,2,0),"") | CW39: =IF(N39="银行账户",VLOOKUP(O39,银行变二级!B:C,2,0),"") | CX39: =IFERROR(VLOOKUP(O39,银行变二级!A:B,2,0),"")
A40: 昌邑市昌荣城乡建设有限公司 | B40: 2026-04-30 | C40: 记-009 | D40: 调整四方协议，应该是其他应收款，3月10#科目选成了其他应付 | E40: 224102 其他应付款-单位-昌邑市城投股权投资管理有限公司 | G40: 50000000 | H40: =LEFT(E40,4) -> 2241 | I40: =IFERROR(LEFT(E40,FIND(" ",E40)-1),E40) -> 224102 | J40: =LEFT(MID(E40,FIND(" ",E40)+1,LEN(E40)),FIND("-",MID(E40,FIND(" ",E40)+1,LEN(E40))&"-")-1) -> 其他应付款 | K40: =IFERROR(MID(MID(E40,FIND(" ",E40)+1,LEN(E40)),FIND("-",MID(E40,FIND(" ",E40)+1,LEN(E40)))+1,IFERROR(FIND("-",MID(E40,FIND(" ",E40)+1,LEN(E40)),FIND("-",MID(E40,FIND(" ",E40)+1,LEN(E40)))+1),LEN(MID(E40,FIND(" ",E40)+1,LEN(E40)))+1)-FIND("-",MID(E40,FIND(" ",E40)+1,LEN(E40)))-1),"") -> 单位 | L40: =IFERROR(MID(MID(E40,FIND(" ",E40)+1,LEN(E40)),FIND("-",MID(E40,FIND(" ",E40)+1,LEN(E40)),FIND("-",MID(E40,FIND(" ",E40)+1,LEN(E40)))+1)+1,LEN(E40)),"") -> 昌邑市城投股权投资管理有限公司 | M40: =IFERROR(IF(H40="1002",1002,VLOOKUP(I40,亿企科目!A:H,6,0)),VLOOKUP(H40,亿企科目!A:G,6,0)) -> 224102 | N40: =IFERROR(IF(H40="1002","银行账户",IF(H40="1123","供应商",VLOOKUP(I40,亿企科目!A:H,8,0))),"") -> 供应商 | O40: =IF(N40=0,IF(M40="1002",K40,""),_xlfn.TEXTAFTER(E40,"-",-1)) -> 昌邑市城投股权投资管理有限公司 | P40: =VLOOKUP(A40,账簿!B:C,2,0) -> 003012 | Q40: =VLOOKUP(P40,账簿!A:B,2,0) -> 昌邑市昌荣城乡建设有限公司 | W40: =X40&AB40&AD40 -> 0030122026-04-309 | X40: =P40 -> 003012 | Y40: =X40 -> 003012 | Z40: =Q40 -> 昌邑市昌荣城乡建设有限公司 | AA40: =LEFT(B40,7) -> 2026-04 | AB40: =B40 -> 2026-04-30 | AC40: 记 | AD40: =VALUE(_xlfn.TEXTAFTER(C40,"-")) -> 9 | AE40: =D40 -> 调整四方协议，应该是其他应收款，3月10#科目选成了其他应付 | AF40: 谭雅心 | AG40: 谭雅心 | AN40: =M40 -> 224102 | AP40: =D40 -> 调整四方协议，应该是其他应收款，3月10#科目选成了其他应付 | AQ40: CNY | AR40: =F40 | AS40: =G40 -> 50000000 | AT40: 01 | AU40: * | AV40: 1 | AW40: =AR40 | AX40: =AS40 -> 50000000 | BQ40: =IF(N40="项目",VLOOKUP(O40,项目!B:C,2,0),IF(K40="空项目",VLOOKUP(K40,项目!B:C,2,0),"")) | BR40: =IFERROR(VLOOKUP(BQ40,项目!A:B,2,0),"") | BU40: =IF(N40="供应商",VLOOKUP(O40,供应商!B:C,2,0),"") -> 002008 | BV40: =IFERROR(VLOOKUP(BU40,供应商!A:B,2,0),"") -> 昌邑市城投股权投资管理有限公司 | BW40: =IF(N40="客户",VLOOKUP(O40,客户!B:C,2,0),"") | BX40: =IFERROR(VLOOKUP(BW40,客户!A:B,2,0),"") | CU40: =IF(N40="费用项目",VLOOKUP(O40,费用项目!B:C,2,0),"") | CV40: =IFERROR(VLOOKUP(CU40,费用项目!A:B,2,0),"") | CW40: =IF(N40="银行账户",VLOOKUP(O40,银行变二级!B:C,2,0),"") | CX40: =IFERROR(VLOOKUP(O40,银行变二级!A:B,2,0),"")
A41: 昌邑市昌荣城乡建设有限公司 | B41: 2026-04-30 | C41: 记-010 | D41: 补提2025年第四季度土地使用税 | E41: 410401 利润分配-未分配利润 | F41: 175290.4 | H41: =LEFT(E41,4) -> 4104 | I41: =IFERROR(LEFT(E41,FIND(" ",E41)-1),E41) -> 410401 | J41: =LEFT(MID(E41,FIND(" ",E41)+1,LEN(E41)),FIND("-",MID(E41,FIND(" ",E41)+1,LEN(E41))&"-")-1) -> 利润分配 | K41: =IFERROR(MID(MID(E41,FIND(" ",E41)+1,LEN(E41)),FIND("-",MID(E41,FIND(" ",E41)+1,LEN(E41)))+1,IFERROR(FIND("-",MID(E41,FIND(" ",E41)+1,LEN(E41)),FIND("-",MID(E41,FIND(" ",E41)+1,LEN(E41)))+1),LEN(MID(E41,FIND(" ",E41)+1,LEN(E41)))+1)-FIND("-",MID(E41,FIND(" ",E41)+1,LEN(E41)))-1),"") -> 未分配利润 | L41: =IFERROR(MID(MID(E41,FIND(" ",E41)+1,LEN(E41)),FIND("-",MID(E41,FIND(" ",E41)+1,LEN(E41)),FIND("-",MID(E41,FIND(" ",E41)+1,LEN(E41)))+1)+1,LEN(E41)),"") | M41: =IFERROR(IF(H41="1002",1002,VLOOKUP(I41,亿企科目!A:H,6,0)),VLOOKUP(H41,亿企科目!A:G,6,0)) -> 410405 | N41: =IFERROR(IF(H41="1002","银行账户",IF(H41="1123","供应商",VLOOKUP(I41,亿企科目!A:H,8,0))),"") -> 0 | O41: =IF(N41=0,IF(M41="1002",K41,""),_xlfn.TEXTAFTER(E41,"-",-1)) | P41: =VLOOKUP(A41,账簿!B:C,2,0) -> 003012 | Q41: =VLOOKUP(P41,账簿!A:B,2,0) -> 昌邑市昌荣城乡建设有限公司 | W41: =X41&AB41&AD41 -> 0030122026-04-3010 | X41: =P41 -> 003012 | Y41: =X41 -> 003012 | Z41: =Q41 -> 昌邑市昌荣城乡建设有限公司 | AA41: =LEFT(B41,7) -> 2026-04 | AB41: =B41 -> 2026-04-30 | AC41: 记 | AD41: =VALUE(_xlfn.TEXTAFTER(C41,"-")) -> 10 | AE41: =D41 -> 补提2025年第四季度土地使用税 | AF41: 谭雅心 | AG41: 谭雅心 | AN41: =M41 -> 410405 | AP41: =D41 -> 补提2025年第四季度土地使用税 | AQ41: CNY | AR41: =F41 -> 175290.4 | AS41: =G41 | AT41: 01 | AU41: * | AV41: 1 | AW41: =AR41 -> 175290.4 | AX41: =AS41 | BQ41: =IF(N41="项目",VLOOKUP(O41,项目!B:C,2,0),IF(K41="空项目",VLOOKUP(K41,项目!B:C,2,0),"")) | BR41: =IFERROR(VLOOKUP(BQ41,项目!A:B,2,0),"") | BU41: =IF(N41="供应商",VLOOKUP(O41,供应商!B:C,2,0),"") | BV41: =IFERROR(VLOOKUP(BU41,供应商!A:B,2,0),"") | BW41: =IF(N41="客户",VLOOKUP(O41,客户!B:C,2,0),"") | BX41: =IFERROR(VLOOKUP(BW41,客户!A:B,2,0),"") | CU41: =IF(N41="费用项目",VLOOKUP(O41,费用项目!B:C,2,0),"") | CV41: =IFERROR(VLOOKUP(CU41,费用项目!A:B,2,0),"") | CW41: =IF(N41="银行账户",VLOOKUP(O41,银行变二级!B:C,2,0),"") | CX41: =IFERROR(VLOOKUP(O41,银行变二级!A:B,2,0),"")
A42: 昌邑市昌荣城乡建设有限公司 | B42: 2026-04-30 | C42: 记-010 | D42: 补提2025年第四季度土地使用税 | E42: 222119 应交税费-应交土地使用税 | G42: 175290.4 | H42: =LEFT(E42,4) -> 2221 | I42: =IFERROR(LEFT(E42,FIND(" ",E42)-1),E42) -> 222119 | J42: =LEFT(MID(E42,FIND(" ",E42)+1,LEN(E42)),FIND("-",MID(E42,FIND(" ",E42)+1,LEN(E42))&"-")-1) -> 应交税费 | K42: =IFERROR(MID(MID(E42,FIND(" ",E42)+1,LEN(E42)),FIND("-",MID(E42,FIND(" ",E42)+1,LEN(E42)))+1,IFERROR(FIND("-",MID(E42,FIND(" ",E42)+1,LEN(E42)),FIND("-",MID(E42,FIND(" ",E42)+1,LEN(E42)))+1),LEN(MID(E42,FIND(" ",E42)+1,LEN(E42)))+1)-FIND("-",MID(E42,FIND(" ",E42)+1,LEN(E42)))-1),"") -> 应交土地使用税 | L42: =IFERROR(MID(MID(E42,FIND(" ",E42)+1,LEN(E42)),FIND("-",MID(E42,FIND(" ",E42)+1,LEN(E42)),FIND("-",MID(E42,FIND(" ",E42)+1,LEN(E42)))+1)+1,LEN(E42)),"") | M42: =IFERROR(IF(H42="1002",1002,VLOOKUP(I42,亿企科目!A:H,6,0)),VLOOKUP(H42,亿企科目!A:G,6,0)) -> 222116 | N42: =IFERROR(IF(H42="1002","银行账户",IF(H42="1123","供应商",VLOOKUP(I42,亿企科目!A:H,8,0))),"") -> 0 | O42: =IF(N42=0,IF(M42="1002",K42,""),_xlfn.TEXTAFTER(E42,"-",-1)) | P42: =VLOOKUP(A42,账簿!B:C,2,0) -> 003012 | Q42: =VLOOKUP(P42,账簿!A:B,2,0) -> 昌邑市昌荣城乡建设有限公司 | W42: =X42&AB42&AD42 -> 0030122026-04-3010 | X42: =P42 -> 003012 | Y42: =X42 -> 003012 | Z42: =Q42 -> 昌邑市昌荣城乡建设有限公司 | AA42: =LEFT(B42,7) -> 2026-04 | AB42: =B42 -> 2026-04-30 | AC42: 记 | AD42: =VALUE(_xlfn.TEXTAFTER(C42,"-")) -> 10 | AE42: =D42 -> 补提2025年第四季度土地使用税 | AF42: 谭雅心 | AG42: 谭雅心 | AN42: =M42 -> 222116 | AP42: =D42 -> 补提2025年第四季度土地使用税 | AQ42: CNY | AR42: =F42 | AS42: =G42 -> 175290.4 | AT42: 01 | AU42: * | AV42: 1 | AW42: =AR42 | AX42: =AS42 -> 175290.4 | BQ42: =IF(N42="项目",VLOOKUP(O42,项目!B:C,2,0),IF(K42="空项目",VLOOKUP(K42,项目!B:C,2,0),"")) | BR42: =IFERROR(VLOOKUP(BQ42,项目!A:B,2,0),"") | BU42: =IF(N42="供应商",VLOOKUP(O42,供应商!B:C,2,0),"") | BV42: =IFERROR(VLOOKUP(BU42,供应商!A:B,2,0),"") | BW42: =IF(N42="客户",VLOOKUP(O42,客户!B:C,2,0),"") | BX42: =IFERROR(VLOOKUP(BW42,客户!A:B,2,0),"") | CU42: =IF(N42="费用项目",VLOOKUP(O42,费用项目!B:C,2,0),"") | CV42: =IFERROR(VLOOKUP(CU42,费用项目!A:B,2,0),"") | CW42: =IF(N42="银行账户",VLOOKUP(O42,银行变二级!B:C,2,0),"") | CX42: =IFERROR(VLOOKUP(O42,银行变二级!A:B,2,0),"")
A43: 昌邑市昌荣城乡建设有限公司 | B43: 2026-04-30 | C43: 记-011 | D43: 结转本月损益 | E43: 4103 本年利润 | F43: 176958.33 | H43: =LEFT(E43,4) -> 4103 | I43: =IFERROR(LEFT(E43,FIND(" ",E43)-1),E43) -> 4103 | J43: =LEFT(MID(E43,FIND(" ",E43)+1,LEN(E43)),FIND("-",MID(E43,FIND(" ",E43)+1,LEN(E43))&"-")-1) -> 本年利润 | K43: =IFERROR(MID(MID(E43,FIND(" ",E43)+1,LEN(E43)),FIND("-",MID(E43,FIND(" ",E43)+1,LEN(E43)))+1,IFERROR(FIND("-",MID(E43,FIND(" ",E43)+1,LEN(E43)),FIND("-",MID(E43,FIND(" ",E43)+1,LEN(E43)))+1),LEN(MID(E43,FIND(" ",E43)+1,LEN(E43)))+1)-FIND("-",MID(E43,FIND(" ",E43)+1,LEN(E43)))-1),"") | L43: =IFERROR(MID(MID(E43,FIND(" ",E43)+1,LEN(E43)),FIND("-",MID(E43,FIND(" ",E43)+1,LEN(E43)),FIND("-",MID(E43,FIND(" ",E43)+1,LEN(E43)))+1)+1,LEN(E43)),"") | M43: =IFERROR(IF(H43="1002",1002,VLOOKUP(I43,亿企科目!A:H,6,0)),VLOOKUP(H43,亿企科目!A:G,6,0)) -> 4103 | N43: =IFERROR(IF(H43="1002","银行账户",IF(H43="1123","供应商",VLOOKUP(I43,亿企科目!A:H,8,0))),"") -> 0 | O43: =IF(N43=0,IF(M43="1002",K43,""),_xlfn.TEXTAFTER(E43,"-",-1)) | P43: =VLOOKUP(A43,账簿!B:C,2,0) -> 003012 | Q43: =VLOOKUP(P43,账簿!A:B,2,0) -> 昌邑市昌荣城乡建设有限公司 | W43: =X43&AB43&AD43 -> 0030122026-04-3011 | X43: =P43 -> 003012 | Y43: =X43 -> 003012 | Z43: =Q43 -> 昌邑市昌荣城乡建设有限公司 | AA43: =LEFT(B43,7) -> 2026-04 | AB43: =B43 -> 2026-04-30 | AC43: 记 | AD43: =VALUE(_xlfn.TEXTAFTER(C43,"-")) -> 11 | AE43: =D43 -> 结转本月损益 | AF43: 谭雅心 | AG43: 谭雅心 | AN43: =M43 -> 4103 | AP43: =D43 -> 结转本月损益 | AQ43: CNY | AR43: =F43 -> 176958.33 | AS43: =G43 | AT43: 01 | AU43: * | AV43: 1 | AW43: =AR43 -> 176958.33 | AX43: =AS43 | BQ43: =IF(N43="项目",VLOOKUP(O43,项目!B:C,2,0),IF(K43="空项目",VLOOKUP(K43,项目!B:C,2,0),"")) | BR43: =IFERROR(VLOOKUP(BQ43,项目!A:B,2,0),"") | BU43: =IF(N43="供应商",VLOOKUP(O43,供应商!B:C,2,0),"") | BV43: =IFERROR(VLOOKUP(BU43,供应商!A:B,2,0),"") | BW43: =IF(N43="客户",VLOOKUP(O43,客户!B:C,2,0),"") | BX43: =IFERROR(VLOOKUP(BW43,客户!A:B,2,0),"") | CU43: =IF(N43="费用项目",VLOOKUP(O43,费用项目!B:C,2,0),"") | CV43: =IFERROR(VLOOKUP(CU43,费用项目!A:B,2,0),"") | CW43: =IF(N43="银行账户",VLOOKUP(O43,银行变二级!B:C,2,0),"") | CX43: =IFERROR(VLOOKUP(O43,银行变二级!A:B,2,0),"")
A44: 昌邑市昌荣城乡建设有限公司 | B44: 2026-04-30 | C44: 记-011 | D44: 结转本月损益 | E44: 6603 财务费用-利息支出 | G44: 176958.33 | H44: =LEFT(E44,4) -> 6603 | I44: =IFERROR(LEFT(E44,FIND(" ",E44)-1),E44) -> 6603 | J44: =LEFT(MID(E44,FIND(" ",E44)+1,LEN(E44)),FIND("-",MID(E44,FIND(" ",E44)+1,LEN(E44))&"-")-1) -> 财务费用 | K44: =IFERROR(MID(MID(E44,FIND(" ",E44)+1,LEN(E44)),FIND("-",MID(E44,FIND(" ",E44)+1,LEN(E44)))+1,IFERROR(FIND("-",MID(E44,FIND(" ",E44)+1,LEN(E44)),FIND("-",MID(E44,FIND(" ",E44)+1,LEN(E44)))+1),LEN(MID(E44,FIND(" ",E44)+1,LEN(E44)))+1)-FIND("-",MID(E44,FIND(" ",E44)+1,LEN(E44)))-1),"") -> 利息支出 | L44: =IFERROR(MID(MID(E44,FIND(" ",E44)+1,LEN(E44)),FIND("-",MID(E44,FIND(" ",E44)+1,LEN(E44)),FIND("-",MID(E44,FIND(" ",E44)+1,LEN(E44)))+1)+1,LEN(E44)),"") | M44: =IFERROR(IF(H44="1002",1002,VLOOKUP(I44,亿企科目!A:H,6,0)),VLOOKUP(H44,亿企科目!A:G,6,0)) -> 6603 | N44: =IFERROR(IF(H44="1002","银行账户",IF(H44="1123","供应商",VLOOKUP(I44,亿企科目!A:H,8,0))),"") -> 费用项目 | O44: =IF(N44=0,IF(M44="1002",K44,""),_xlfn.TEXTAFTER(E44,"-",-1)) -> 利息支出 | P44: =VLOOKUP(A44,账簿!B:C,2,0) -> 003012 | Q44: =VLOOKUP(P44,账簿!A:B,2,0) -> 昌邑市昌荣城乡建设有限公司 | W44: =X44&AB44&AD44 -> 0030122026-04-3011 | X44: =P44 -> 003012 | Y44: =X44 -> 003012 | Z44: =Q44 -> 昌邑市昌荣城乡建设有限公司 | AA44: =LEFT(B44,7) -> 2026-04 | AB44: =B44 -> 2026-04-30 | AC44: 记 | AD44: =VALUE(_xlfn.TEXTAFTER(C44,"-")) -> 11 | AE44: =D44 -> 结转本月损益 | AF44: 谭雅心 | AG44: 谭雅心 | AN44: =M44 -> 6603 | AP44: =D44 -> 结转本月损益 | AQ44: CNY | AR44: =F44 | AS44: =G44 -> 176958.33 | AT44: 01 | AU44: * | AV44: 1 | AW44: =AR44 | AX44: =AS44 -> 176958.33 | BQ44: =IF(N44="项目",VLOOKUP(O44,项目!B:C,2,0),IF(K44="空项目",VLOOKUP(K44,项目!B:C,2,0),"")) | BR44: =IFERROR(VLOOKUP(BQ44,项目!A:B,2,0),"") | BU44: =IF(N44="供应商",VLOOKUP(O44,供应商!B:C,2,0),"") | BV44: =IFERROR(VLOOKUP(BU44,供应商!A:B,2,0),"") | BW44: =IF(N44="客户",VLOOKUP(O44,客户!B:C,2,0),"") | BX44: =IFERROR(VLOOKUP(BW44,客户!A:B,2,0),"") | CU44: =IF(N44="费用项目",VLOOKUP(O44,费用项目!B:C,2,0),"") -> 660302 | CV44: =IFERROR(VLOOKUP(CU44,费用项目!A:B,2,0),"") -> 利息支出 | CW44: =IF(N44="银行账户",VLOOKUP(O44,银行变二级!B:C,2,0),"") | CX44: =IFERROR(VLOOKUP(O44,银行变二级!A:B,2,0),"")
A45: 昌邑市昌荣环保科技有限公司 | B45: 2026-04-29 | C45: 记-001 | D45: 2026-04-29,网银转账,任伟新 | E45: 122111 其他应收款-内部往来-任伟新 | F45: 200 | H45: =LEFT(E45,4) -> 1221 | I45: =IFERROR(LEFT(E45,FIND(" ",E45)-1),E45) -> 122111 | J45: =LEFT(MID(E45,FIND(" ",E45)+1,LEN(E45)),FIND("-",MID(E45,FIND(" ",E45)+1,LEN(E45))&"-")-1) -> 其他应收款 | K45: =IFERROR(MID(MID(E45,FIND(" ",E45)+1,LEN(E45)),FIND("-",MID(E45,FIND(" ",E45)+1,LEN(E45)))+1,IFERROR(FIND("-",MID(E45,FIND(" ",E45)+1,LEN(E45)),FIND("-",MID(E45,FIND(" ",E45)+1,LEN(E45)))+1),LEN(MID(E45,FIND(" ",E45)+1,LEN(E45)))+1)-FIND("-",MID(E45,FIND(" ",E45)+1,LEN(E45)))-1),"") -> 内部往来 | L45: =IFERROR(MID(MID(E45,FIND(" ",E45)+1,LEN(E45)),FIND("-",MID(E45,FIND(" ",E45)+1,LEN(E45)),FIND("-",MID(E45,FIND(" ",E45)+1,LEN(E45)))+1)+1,LEN(E45)),"") -> 任伟新 | M45: =IFERROR(IF(H45="1002",1002,VLOOKUP(I45,亿企科目!A:H,6,0)),VLOOKUP(H45,亿企科目!A:G,6,0)) -> 122105 | N45: =IFERROR(IF(H45="1002","银行账户",IF(H45="1123","供应商",VLOOKUP(I45,亿企科目!A:H,8,0))),"") -> 供应商 | O45: =IF(N45=0,IF(M45="1002",K45,""),_xlfn.TEXTAFTER(E45,"-",-1)) -> 任伟新 | P45: =VLOOKUP(A45,账簿!B:C,2,0) -> 003010 | Q45: =VLOOKUP(P45,账簿!A:B,2,0) -> 昌邑市昌荣环保科技有限公司 | W45: =X45&AB45&AD45 -> 0030102026-04-291 | X45: =P45 -> 003010 | Y45: =X45 -> 003010 | Z45: =Q45 -> 昌邑市昌荣环保科技有限公司 | AA45: =LEFT(B45,7) -> 2026-04 | AB45: =B45 -> 2026-04-29 | AC45: 记 | AD45: =VALUE(_xlfn.TEXTAFTER(C45,"-")) -> 1 | AE45: =D45 -> 2026-04-29,网银转账,任伟新 | AF45: 谭雅心 | AG45: 谭雅心 | AN45: =M45 -> 122105 | AP45: =D45 -> 2026-04-29,网银转账,任伟新 | AQ45: CNY | AR45: =F45 -> 200 | AS45: =G45 | AT45: 01 | AU45: * | AV45: 1 | AW45: =AR45 -> 200 | AX45: =AS45 | BQ45: =IF(N45="项目",VLOOKUP(O45,项目!B:C,2,0),IF(K45="空项目",VLOOKUP(K45,项目!B:C,2,0),"")) | BR45: =IFERROR(VLOOKUP(BQ45,项目!A:B,2,0),"") | BU45: =IF(N45="供应商",VLOOKUP(O45,供应商!B:C,2,0),"") -> 0030002 | BV45: =IFERROR(VLOOKUP(BU45,供应商!A:B,2,0),"") -> 任伟新 | BW45: =IF(N45="客户",VLOOKUP(O45,客户!B:C,2,0),"") | BX45: =IFERROR(VLOOKUP(BW45,客户!A:B,2,0),"") | CU45: =IF(N45="费用项目",VLOOKUP(O45,费用项目!B:C,2,0),"") | CV45: =IFERROR(VLOOKUP(CU45,费用项目!A:B,2,0),"") | CW45: =IF(N45="银行账户",VLOOKUP(O45,银行变二级!B:C,2,0),"") | CX45: =IFERROR(VLOOKUP(O45,银行变二级!A:B,2,0),"")
A46: 昌邑市昌荣环保科技有限公司 | B46: 2026-04-29 | C46: 记-001 | D46: 2026-04-29,网银转账,任伟新 | E46: 100203 银行存款-潍坊银行3535 | G46: 200 | H46: =LEFT(E46,4) -> 1002 | I46: =IFERROR(LEFT(E46,FIND(" ",E46)-1),E46) -> 100203 | J46: =LEFT(MID(E46,FIND(" ",E46)+1,LEN(E46)),FIND("-",MID(E46,FIND(" ",E46)+1,LEN(E46))&"-")-1) -> 银行存款 | K46: =IFERROR(MID(MID(E46,FIND(" ",E46)+1,LEN(E46)),FIND("-",MID(E46,FIND(" ",E46)+1,LEN(E46)))+1,IFERROR(FIND("-",MID(E46,FIND(" ",E46)+1,LEN(E46)),FIND("-",MID(E46,FIND(" ",E46)+1,LEN(E46)))+1),LEN(MID(E46,FIND(" ",E46)+1,LEN(E46)))+1)-FIND("-",MID(E46,FIND(" ",E46)+1,LEN(E46)))-1),"") -> 潍坊银行3535 | L46: =IFERROR(MID(MID(E46,FIND(" ",E46)+1,LEN(E46)),FIND("-",MID(E46,FIND(" ",E46)+1,LEN(E46)),FIND("-",MID(E46,FIND(" ",E46)+1,LEN(E46)))+1)+1,LEN(E46)),"") | M46: =IFERROR(IF(H46="1002",1002,VLOOKUP(I46,亿企科目!A:H,6,0)),VLOOKUP(H46,亿企科目!A:G,6,0)) -> 1002 | N46: =IFERROR(IF(H46="1002","银行账户",IF(H46="1123","供应商",VLOOKUP(I46,亿企科目!A:H,8,0))),"") -> 银行账户 | O46: =IF(N46=0,IF(M46="1002",K46,""),_xlfn.TEXTAFTER(E46,"-",-1)) -> 潍坊银行3535 | P46: =VLOOKUP(A46,账簿!B:C,2,0) -> 003010 | Q46: =VLOOKUP(P46,账簿!A:B,2,0) -> 昌邑市昌荣环保科技有限公司 | W46: =X46&AB46&AD46 -> 0030102026-04-291 | X46: =P46 -> 003010 | Y46: =X46 -> 003010 | Z46: =Q46 -> 昌邑市昌荣环保科技有限公司 | AA46: =LEFT(B46,7) -> 2026-04 | AB46: =B46 -> 2026-04-29 | AC46: 记 | AD46: =VALUE(_xlfn.TEXTAFTER(C46,"-")) -> 1 | AE46: =D46 -> 2026-04-29,网银转账,任伟新 | AF46: 谭雅心 | AG46: 谭雅心 | AN46: =M46 -> 1002 | AP46: =D46 -> 2026-04-29,网银转账,任伟新 | AQ46: CNY | AR46: =F46 | AS46: =G46 -> 200 | AT46: 01 | AU46: * | AV46: 1 | AW46: =AR46 | AX46: =AS46 -> 200 | BQ46: =IF(N46="项目",VLOOKUP(O46,项目!B:C,2,0),IF(K46="空项目",VLOOKUP(K46,项目!B:C,2,0),"")) | BR46: =IFERROR(VLOOKUP(BQ46,项目!A:B,2,0),"") | BU46: =IF(N46="供应商",VLOOKUP(O46,供应商!B:C,2,0),"") | BV46: =IFERROR(VLOOKUP(BU46,供应商!A:B,2,0),"") | BW46: =IF(N46="客户",VLOOKUP(O46,客户!B:C,2,0),"") | BX46: =IFERROR(VLOOKUP(BW46,客户!A:B,2,0),"") | CU46: =IF(N46="费用项目",VLOOKUP(O46,费用项目!B:C,2,0),"") | CV46: =IFERROR(VLOOKUP(CU46,费用项目!A:B,2,0),"") | CW46: =IF(N46="银行账户",VLOOKUP(O46,银行变二级!B:C,2,0),"") -> 潍坊银行3535 | CX46: =IFERROR(VLOOKUP(O46,银行变二级!A:B,2,0),"") -> 潍坊银行3535
A47: 昌邑市昌荣环保科技有限公司 | B47: 2026-04-30 | C47: 记-002 | D47: 税收罚金 | E47: 671101 营业外支出-税收滞纳金、罚金、罚款 | F47: 200 | H47: =LEFT(E47,4) -> 6711 | I47: =IFERROR(LEFT(E47,FIND(" ",E47)-1),E47) -> 671101 | J47: =LEFT(MID(E47,FIND(" ",E47)+1,LEN(E47)),FIND("-",MID(E47,FIND(" ",E47)+1,LEN(E47))&"-")-1) -> 营业外支出 | K47: =IFERROR(MID(MID(E47,FIND(" ",E47)+1,LEN(E47)),FIND("-",MID(E47,FIND(" ",E47)+1,LEN(E47)))+1,IFERROR(FIND("-",MID(E47,FIND(" ",E47)+1,LEN(E47)),FIND("-",MID(E47,FIND(" ",E47)+1,LEN(E47)))+1),LEN(MID(E47,FIND(" ",E47)+1,LEN(E47)))+1)-FIND("-",MID(E47,FIND(" ",E47)+1,LEN(E47)))-1),"") -> 税收滞纳金、罚金、罚款 | L47: =IFERROR(MID(MID(E47,FIND(" ",E47)+1,LEN(E47)),FIND("-",MID(E47,FIND(" ",E47)+1,LEN(E47)),FIND("-",MID(E47,FIND(" ",E47)+1,LEN(E47)))+1)+1,LEN(E47)),"") | M47: =IFERROR(IF(H47="1002",1002,VLOOKUP(I47,亿企科目!A:H,6,0)),VLOOKUP(H47,亿企科目!A:G,6,0)) -> 6711 | N47: =IFERROR(IF(H47="1002","银行账户",IF(H47="1123","供应商",VLOOKUP(I47,亿企科目!A:H,8,0))),"") | O47: =IF(N47=0,IF(M47="1002",K47,""),_xlfn.TEXTAFTER(E47,"-",-1)) -> 税收滞纳金、罚金、罚款 | P47: =VLOOKUP(A47,账簿!B:C,2,0) -> 003010 | Q47: =VLOOKUP(P47,账簿!A:B,2,0) -> 昌邑市昌荣环保科技有限公司 | W47: =X47&AB47&AD47 -> 0030102026-04-302 | X47: =P47 -> 003010 | Y47: =X47 -> 003010 | Z47: =Q47 -> 昌邑市昌荣环保科技有限公司 | AA47: =LEFT(B47,7) -> 2026-04 | AB47: =B47 -> 2026-04-30 | AC47: 记 | AD47: =VALUE(_xlfn.TEXTAFTER(C47,"-")) -> 2 | AE47: =D47 -> 税收罚金 | AF47: 谭雅心 | AG47: 谭雅心 | AN47: =M47 -> 6711 | AP47: =D47 -> 税收罚金 | AQ47: CNY | AR47: =F47 -> 200 | AS47: =G47 | AT47: 01 | AU47: * | AV47: 1 | AW47: =AR47 -> 200 | AX47: =AS47 | BQ47: =IF(N47="项目",VLOOKUP(O47,项目!B:C,2,0),IF(K47="空项目",VLOOKUP(K47,项目!B:C,2,0),"")) | BR47: =IFERROR(VLOOKUP(BQ47,项目!A:B,2,0),"") | BU47: =IF(N47="供应商",VLOOKUP(O47,供应商!B:C,2,0),"") | BV47: =IFERROR(VLOOKUP(BU47,供应商!A:B,2,0),"") | BW47: =IF(N47="客户",VLOOKUP(O47,客户!B:C,2,0),"") | BX47: =IFERROR(VLOOKUP(BW47,客户!A:B,2,0),"") | CU47: =IF(N47="费用项目",VLOOKUP(O47,费用项目!B:C,2,0),"") | CV47: =IFERROR(VLOOKUP(CU47,费用项目!A:B,2,0),"") | CW47: =IF(N47="银行账户",VLOOKUP(O47,银行变二级!B:C,2,0),"") | CX47: =IFERROR(VLOOKUP(O47,银行变二级!A:B,2,0),"")
A48: 昌邑市昌荣环保科技有限公司 | B48: 2026-04-30 | C48: 记-002 | D48: 税收罚金 | E48: 122111 其他应收款-内部往来-任伟新 | G48: 200 | H48: =LEFT(E48,4) -> 1221 | I48: =IFERROR(LEFT(E48,FIND(" ",E48)-1),E48) -> 122111 | J48: =LEFT(MID(E48,FIND(" ",E48)+1,LEN(E48)),FIND("-",MID(E48,FIND(" ",E48)+1,LEN(E48))&"-")-1) -> 其他应收款 | K48: =IFERROR(MID(MID(E48,FIND(" ",E48)+1,LEN(E48)),FIND("-",MID(E48,FIND(" ",E48)+1,LEN(E48)))+1,IFERROR(FIND("-",MID(E48,FIND(" ",E48)+1,LEN(E48)),FIND("-",MID(E48,FIND(" ",E48)+1,LEN(E48)))+1),LEN(MID(E48,FIND(" ",E48)+1,LEN(E48)))+1)-FIND("-",MID(E48,FIND(" ",E48)+1,LEN(E48)))-1),"") -> 内部往来 | L48: =IFERROR(MID(MID(E48,FIND(" ",E48)+1,LEN(E48)),FIND("-",MID(E48,FIND(" ",E48)+1,LEN(E48)),FIND("-",MID(E48,FIND(" ",E48)+1,LEN(E48)))+1)+1,LEN(E48)),"") -> 任伟新 | M48: =IFERROR(IF(H48="1002",1002,VLOOKUP(I48,亿企科目!A:H,6,0)),VLOOKUP(H48,亿企科目!A:G,6,0)) -> 122105 | N48: =IFERROR(IF(H48="1002","银行账户",IF(H48="1123","供应商",VLOOKUP(I48,亿企科目!A:H,8,0))),"") -> 供应商 | O48: =IF(N48=0,IF(M48="1002",K48,""),_xlfn.TEXTAFTER(E48,"-",-1)) -> 任伟新 | P48: =VLOOKUP(A48,账簿!B:C,2,0) -> 003010 | Q48: =VLOOKUP(P48,账簿!A:B,2,0) -> 昌邑市昌荣环保科技有限公司 | W48: =X48&AB48&AD48 -> 0030102026-04-302 | X48: =P48 -> 003010 | Y48: =X48 -> 003010 | Z48: =Q48 -> 昌邑市昌荣环保科技有限公司 | AA48: =LEFT(B48,7) -> 2026-04 | AB48: =B48 -> 2026-04-30 | AC48: 记 | AD48: =VALUE(_xlfn.TEXTAFTER(C48,"-")) -> 2 | AE48: =D48 -> 税收罚金 | AF48: 谭雅心 | AG48: 谭雅心 | AN48: =M48 -> 122105 | AP48: =D48 -> 税收罚金 | AQ48: CNY | AR48: =F48 | AS48: =G48 -> 200 | AT48: 01 | AU48: * | AV48: 1 | AW48: =AR48 | AX48: =AS48 -> 200 | BQ48: =IF(N48="项目",VLOOKUP(O48,项目!B:C,2,0),IF(K48="空项目",VLOOKUP(K48,项目!B:C,2,0),"")) | BR48: =IFERROR(VLOOKUP(BQ48,项目!A:B,2,0),"") | BU48: =IF(N48="供应商",VLOOKUP(O48,供应商!B:C,2,0),"") -> 0030002 | BV48: =IFERROR(VLOOKUP(BU48,供应商!A:B,2,0),"") -> 任伟新 | BW48: =IF(N48="客户",VLOOKUP(O48,客户!B:C,2,0),"") | BX48: =IFERROR(VLOOKUP(BW48,客户!A:B,2,0),"") | CU48: =IF(N48="费用项目",VLOOKUP(O48,费用项目!B:C,2,0),"") | CV48: =IFERROR(VLOOKUP(CU48,费用项目!A:B,2,0),"") | CW48: =IF(N48="银行账户",VLOOKUP(O48,银行变二级!B:C,2,0),"") | CX48: =IFERROR(VLOOKUP(O48,银行变二级!A:B,2,0),"")
A49: 昌邑市昌荣环保科技有限公司 | B49: 2026-04-30 | C49: 记-003 | D49: 工程造价咨询费，山东宜信建设项目管理有限公司 | E49: 6602 管理费用-咨询费 | F49: 40000 | H49: =LEFT(E49,4) -> 6602 | I49: =IFERROR(LEFT(E49,FIND(" ",E49)-1),E49) -> 6602 | J49: =LEFT(MID(E49,FIND(" ",E49)+1,LEN(E49)),FIND("-",MID(E49,FIND(" ",E49)+1,LEN(E49))&"-")-1) -> 管理费用 | K49: =IFERROR(MID(MID(E49,FIND(" ",E49)+1,LEN(E49)),FIND("-",MID(E49,FIND(" ",E49)+1,LEN(E49)))+1,IFERROR(FIND("-",MID(E49,FIND(" ",E49)+1,LEN(E49)),FIND("-",MID(E49,FIND(" ",E49)+1,LEN(E49)))+1),LEN(MID(E49,FIND(" ",E49)+1,LEN(E49)))+1)-FIND("-",MID(E49,FIND(" ",E49)+1,LEN(E49)))-1),"") -> 咨询费 | L49: =IFERROR(MID(MID(E49,FIND(" ",E49)+1,LEN(E49)),FIND("-",MID(E49,FIND(" ",E49)+1,LEN(E49)),FIND("-",MID(E49,FIND(" ",E49)+1,LEN(E49)))+1)+1,LEN(E49)),"") | M49: =IFERROR(IF(H49="1002",1002,VLOOKUP(I49,亿企科目!A:H,6,0)),VLOOKUP(H49,亿企科目!A:G,6,0)) -> 6602 | N49: =IFERROR(IF(H49="1002","银行账户",IF(H49="1123","供应商",VLOOKUP(I49,亿企科目!A:H,8,0))),"") -> 费用项目 | O49: =IF(N49=0,IF(M49="1002",K49,""),_xlfn.TEXTAFTER(E49,"-",-1)) -> 咨询费 | P49: =VLOOKUP(A49,账簿!B:C,2,0) -> 003010 | Q49: =VLOOKUP(P49,账簿!A:B,2,0) -> 昌邑市昌荣环保科技有限公司 | W49: =X49&AB49&AD49 -> 0030102026-04-303 | X49: =P49 -> 003010 | Y49: =X49 -> 003010 | Z49: =Q49 -> 昌邑市昌荣环保科技有限公司 | AA49: =LEFT(B49,7) -> 2026-04 | AB49: =B49 -> 2026-04-30 | AC49: 记 | AD49: =VALUE(_xlfn.TEXTAFTER(C49,"-")) -> 3 | AE49: =D49 -> 工程造价咨询费，山东宜信建设项目管理有限公司 | AF49: 谭雅心 | AG49: 谭雅心 | AN49: =M49 -> 6602 | AP49: =D49 -> 工程造价咨询费，山东宜信建设项目管理有限公司 | AQ49: CNY | AR49: =F49 -> 40000 | AS49: =G49 | AT49: 01 | AU49: * | AV49: 1 | AW49: =AR49 -> 40000 | AX49: =AS49 | BQ49: =IF(N49="项目",VLOOKUP(O49,项目!B:C,2,0),IF(K49="空项目",VLOOKUP(K49,项目!B:C,2,0),"")) | BR49: =IFERROR(VLOOKUP(BQ49,项目!A:B,2,0),"") | BU49: =IF(N49="供应商",VLOOKUP(O49,供应商!B:C,2,0),"") | BV49: =IFERROR(VLOOKUP(BU49,供应商!A:B,2,0),"") | BW49: =IF(N49="客户",VLOOKUP(O49,客户!B:C,2,0),"") | BX49: =IFERROR(VLOOKUP(BW49,客户!A:B,2,0),"") | CU49: =IF(N49="费用项目",VLOOKUP(O49,费用项目!B:C,2,0),"") -> 660210 | CV49: =IFERROR(VLOOKUP(CU49,费用项目!A:B,2,0),"") -> 咨询费 | CW49: =IF(N49="银行账户",VLOOKUP(O49,银行变二级!B:C,2,0),"") | CX49: =IFERROR(VLOOKUP(O49,银行变二级!A:B,2,0),"")
A50: 昌邑市昌荣环保科技有限公司 | B50: 2026-04-30 | C50: 记-003 | D50: 工程造价咨询费，山东宜信建设项目管理有限公司 | E50: 224102 其他应付款-单位-山东宜信建设项目管理有限公司 | G50: 40000 | H50: =LEFT(E50,4) -> 2241 | I50: =IFERROR(LEFT(E50,FIND(" ",E50)-1),E50) -> 224102 | J50: =LEFT(MID(E50,FIND(" ",E50)+1,LEN(E50)),FIND("-",MID(E50,FIND(" ",E50)+1,LEN(E50))&"-")-1) -> 其他应付款 | K50: =IFERROR(MID(MID(E50,FIND(" ",E50)+1,LEN(E50)),FIND("-",MID(E50,FIND(" ",E50)+1,LEN(E50)))+1,IFERROR(FIND("-",MID(E50,FIND(" ",E50)+1,LEN(E50)),FIND("-",MID(E50,FIND(" ",E50)+1,LEN(E50)))+1),LEN(MID(E50,FIND(" ",E50)+1,LEN(E50)))+1)-FIND("-",MID(E50,FIND(" ",E50)+1,LEN(E50)))-1),"") -> 单位 | L50: =IFERROR(MID(MID(E50,FIND(" ",E50)+1,LEN(E50)),FIND("-",MID(E50,FIND(" ",E50)+1,LEN(E50)),FIND("-",MID(E50,FIND(" ",E50)+1,LEN(E50)))+1)+1,LEN(E50)),"") -> 山东宜信建设项目管理有限公司 | M50: =IFERROR(IF(H50="1002",1002,VLOOKUP(I50,亿企科目!A:H,6,0)),VLOOKUP(H50,亿企科目!A:G,6,0)) -> 224102 | N50: =IFERROR(IF(H50="1002","银行账户",IF(H50="1123","供应商",VLOOKUP(I50,亿企科目!A:H,8,0))),"") -> 供应商 | O50: =IF(N50=0,IF(M50="1002",K50,""),_xlfn.TEXTAFTER(E50,"-",-1)) -> 山东宜信建设项目管理有限公司 | P50: =VLOOKUP(A50,账簿!B:C,2,0) -> 003010 | Q50: =VLOOKUP(P50,账簿!A:B,2,0) -> 昌邑市昌荣环保科技有限公司 | W50: =X50&AB50&AD50 -> 0030102026-04-303 | X50: =P50 -> 003010 | Y50: =X50 -> 003010 | Z50: =Q50 -> 昌邑市昌荣环保科技有限公司 | AA50: =LEFT(B50,7) -> 2026-04 | AB50: =B50 -> 2026-04-30 | AC50: 记 | AD50: =VALUE(_xlfn.TEXTAFTER(C50,"-")) -> 3 | AE50: =D50 -> 工程造价咨询费，山东宜信建设项目管理有限公司 | AF50: 谭雅心 | AG50: 谭雅心 | AN50: =M50 -> 224102 | AP50: =D50 -> 工程造价咨询费，山东宜信建设项目管理有限公司 | AQ50: CNY | AR50: =F50 | AS50: =G50 -> 40000 | AT50: 01 | AU50: * | AV50: 1 | AW50: =AR50 | AX50: =AS50 -> 40000 | BQ50: =IF(N50="项目",VLOOKUP(O50,项目!B:C,2,0),IF(K50="空项目",VLOOKUP(K50,项目!B:C,2,0),"")) | BR50: =IFERROR(VLOOKUP(BQ50,项目!A:B,2,0),"") | BU50: =IF(N50="供应商",VLOOKUP(O50,供应商!B:C,2,0),"") -> 0007508 | BV50: =IFERROR(VLOOKUP(BU50,供应商!A:B,2,0),"") -> 山东宜信建设项目管理有限公司 | BW50: =IF(N50="客户",VLOOKUP(O50,客户!B:C,2,0),"") | BX50: =IFERROR(VLOOKUP(BW50,客户!A:B,2,0),"") | CU50: =IF(N50="费用项目",VLOOKUP(O50,费用项目!B:C,2,0),"") | CV50: =IFERROR(VLOOKUP(CU50,费用项目!A:B,2,0),"") | CW50: =IF(N50="银行账户",VLOOKUP(O50,银行变二级!B:C,2,0),"") | CX50: =IFERROR(VLOOKUP(O50,银行变二级!A:B,2,0),"")
A51: 昌邑市昌荣环保科技有限公司 | B51: 2026-04-30 | C51: 记-004 | D51: 结转本月损益 | E51: 4103 本年利润 | F51: 40200 | H51: =LEFT(E51,4) -> 4103 | I51: =IFERROR(LEFT(E51,FIND(" ",E51)-1),E51) -> 4103 | J51: =LEFT(MID(E51,FIND(" ",E51)+1,LEN(E51)),FIND("-",MID(E51,FIND(" ",E51)+1,LEN(E51))&"-")-1) -> 本年利润 | K51: =IFERROR(MID(MID(E51,FIND(" ",E51)+1,LEN(E51)),FIND("-",MID(E51,FIND(" ",E51)+1,LEN(E51)))+1,IFERROR(FIND("-",MID(E51,FIND(" ",E51)+1,LEN(E51)),FIND("-",MID(E51,FIND(" ",E51)+1,LEN(E51)))+1),LEN(MID(E51,FIND(" ",E51)+1,LEN(E51)))+1)-FIND("-",MID(E51,FIND(" ",E51)+1,LEN(E51)))-1),"") | L51: =IFERROR(MID(MID(E51,FIND(" ",E51)+1,LEN(E51)),FIND("-",MID(E51,FIND(" ",E51)+1,LEN(E51)),FIND("-",MID(E51,FIND(" ",E51)+1,LEN(E51)))+1)+1,LEN(E51)),"") | M51: =IFERROR(IF(H51="1002",1002,VLOOKUP(I51,亿企科目!A:H,6,0)),VLOOKUP(H51,亿企科目!A:G,6,0)) -> 4103 | N51: =IFERROR(IF(H51="1002","银行账户",IF(H51="1123","供应商",VLOOKUP(I51,亿企科目!A:H,8,0))),"") -> 0 | O51: =IF(N51=0,IF(M51="1002",K51,""),_xlfn.TEXTAFTER(E51,"-",-1)) | P51: =VLOOKUP(A51,账簿!B:C,2,0) -> 003010 | Q51: =VLOOKUP(P51,账簿!A:B,2,0) -> 昌邑市昌荣环保科技有限公司 | W51: =X51&AB51&AD51 -> 0030102026-04-304 | X51: =P51 -> 003010 | Y51: =X51 -> 003010 | Z51: =Q51 -> 昌邑市昌荣环保科技有限公司 | AA51: =LEFT(B51,7) -> 2026-04 | AB51: =B51 -> 2026-04-30 | AC51: 记 | AD51: =VALUE(_xlfn.TEXTAFTER(C51,"-")) -> 4 | AE51: =D51 -> 结转本月损益 | AF51: 谭雅心 | AG51: 谭雅心 | AN51: =M51 -> 4103 | AP51: =D51 -> 结转本月损益 | AQ51: CNY | AR51: =F51 -> 40200 | AS51: =G51 | AT51: 01 | AU51: * | AV51: 1 | AW51: =AR51 -> 40200 | AX51: =AS51 | BQ51: =IF(N51="项目",VLOOKUP(O51,项目!B:C,2,0),IF(K51="空项目",VLOOKUP(K51,项目!B:C,2,0),"")) | BR51: =IFERROR(VLOOKUP(BQ51,项目!A:B,2,0),"") | BU51: =IF(N51="供应商",VLOOKUP(O51,供应商!B:C,2,0),"") | BV51: =IFERROR(VLOOKUP(BU51,供应商!A:B,2,0),"") | BW51: =IF(N51="客户",VLOOKUP(O51,客户!B:C,2,0),"") | BX51: =IFERROR(VLOOKUP(BW51,客户!A:B,2,0),"") | CU51: =IF(N51="费用项目",VLOOKUP(O51,费用项目!B:C,2,0),"") | CV51: =IFERROR(VLOOKUP(CU51,费用项目!A:B,2,0),"") | CW51: =IF(N51="银行账户",VLOOKUP(O51,银行变二级!B:C,2,0),"") | CX51: =IFERROR(VLOOKUP(O51,银行变二级!A:B,2,0),"")
A52: 昌邑市昌荣环保科技有限公司 | B52: 2026-04-30 | C52: 记-004 | D52: 结转本月损益 | E52: 6602 管理费用-咨询费 | G52: 40000 | H52: =LEFT(E52,4) -> 6602 | I52: =IFERROR(LEFT(E52,FIND(" ",E52)-1),E52) -> 6602 | J52: =LEFT(MID(E52,FIND(" ",E52)+1,LEN(E52)),FIND("-",MID(E52,FIND(" ",E52)+1,LEN(E52))&"-")-1) -> 管理费用 | K52: =IFERROR(MID(MID(E52,FIND(" ",E52)+1,LEN(E52)),FIND("-",MID(E52,FIND(" ",E52)+1,LEN(E52)))+1,IFERROR(FIND("-",MID(E52,FIND(" ",E52)+1,LEN(E52)),FIND("-",MID(E52,FIND(" ",E52)+1,LEN(E52)))+1),LEN(MID(E52,FIND(" ",E52)+1,LEN(E52)))+1)-FIND("-",MID(E52,FIND(" ",E52)+1,LEN(E52)))-1),"") -> 咨询费 | L52: =IFERROR(MID(MID(E52,FIND(" ",E52)+1,LEN(E52)),FIND("-",MID(E52,FIND(" ",E52)+1,LEN(E52)),FIND("-",MID(E52,FIND(" ",E52)+1,LEN(E52)))+1)+1,LEN(E52)),"") | M52: =IFERROR(IF(H52="1002",1002,VLOOKUP(I52,亿企科目!A:H,6,0)),VLOOKUP(H52,亿企科目!A:G,6,0)) -> 6602 | N52: =IFERROR(IF(H52="1002","银行账户",IF(H52="1123","供应商",VLOOKUP(I52,亿企科目!A:H,8,0))),"") -> 费用项目 | O52: =IF(N52=0,IF(M52="1002",K52,""),_xlfn.TEXTAFTER(E52,"-",-1)) -> 咨询费 | P52: =VLOOKUP(A52,账簿!B:C,2,0) -> 003010 | Q52: =VLOOKUP(P52,账簿!A:B,2,0) -> 昌邑市昌荣环保科技有限公司 | W52: =X52&AB52&AD52 -> 0030102026-04-304 | X52: =P52 -> 003010 | Y52: =X52 -> 003010 | Z52: =Q52 -> 昌邑市昌荣环保科技有限公司 | AA52: =LEFT(B52,7) -> 2026-04 | AB52: =B52 -> 2026-04-30 | AC52: 记 | AD52: =VALUE(_xlfn.TEXTAFTER(C52,"-")) -> 4 | AE52: =D52 -> 结转本月损益 | AF52: 谭雅心 | AG52: 谭雅心 | AN52: =M52 -> 6602 | AP52: =D52 -> 结转本月损益 | AQ52: CNY | AR52: =F52 | AS52: =G52 -> 40000 | AT52: 01 | AU52: * | AV52: 1 | AW52: =AR52 | AX52: =AS52 -> 40000 | BQ52: =IF(N52="项目",VLOOKUP(O52,项目!B:C,2,0),IF(K52="空项目",VLOOKUP(K52,项目!B:C,2,0),"")) | BR52: =IFERROR(VLOOKUP(BQ52,项目!A:B,2,0),"") | BU52: =IF(N52="供应商",VLOOKUP(O52,供应商!B:C,2,0),"") | BV52: =IFERROR(VLOOKUP(BU52,供应商!A:B,2,0),"") | BW52: =IF(N52="客户",VLOOKUP(O52,客户!B:C,2,0),"") | BX52: =IFERROR(VLOOKUP(BW52,客户!A:B,2,0),"") | CU52: =IF(N52="费用项目",VLOOKUP(O52,费用项目!B:C,2,0),"") -> 660210 | CV52: =IFERROR(VLOOKUP(CU52,费用项目!A:B,2,0),"") -> 咨询费 | CW52: =IF(N52="银行账户",VLOOKUP(O52,银行变二级!B:C,2,0),"") | CX52: =IFERROR(VLOOKUP(O52,银行变二级!A:B,2,0),"")
A53: 昌邑市昌荣环保科技有限公司 | B53: 2026-04-30 | C53: 记-004 | D53: 结转本月损益 | E53: 671101 营业外支出-税收滞纳金、罚金、罚款 | G53: 200 | H53: =LEFT(E53,4) -> 6711 | I53: =IFERROR(LEFT(E53,FIND(" ",E53)-1),E53) -> 671101 | J53: =LEFT(MID(E53,FIND(" ",E53)+1,LEN(E53)),FIND("-",MID(E53,FIND(" ",E53)+1,LEN(E53))&"-")-1) -> 营业外支出 | K53: =IFERROR(MID(MID(E53,FIND(" ",E53)+1,LEN(E53)),FIND("-",MID(E53,FIND(" ",E53)+1,LEN(E53)))+1,IFERROR(FIND("-",MID(E53,FIND(" ",E53)+1,LEN(E53)),FIND("-",MID(E53,FIND(" ",E53)+1,LEN(E53)))+1),LEN(MID(E53,FIND(" ",E53)+1,LEN(E53)))+1)-FIND("-",MID(E53,FIND(" ",E53)+1,LEN(E53)))-1),"") -> 税收滞纳金、罚金、罚款 | L53: =IFERROR(MID(MID(E53,FIND(" ",E53)+1,LEN(E53)),FIND("-",MID(E53,FIND(" ",E53)+1,LEN(E53)),FIND("-",MID(E53,FIND(" ",E53)+1,LEN(E53)))+1)+1,LEN(E53)),"") | M53: =IFERROR(IF(H53="1002",1002,VLOOKUP(I53,亿企科目!A:H,6,0)),VLOOKUP(H53,亿企科目!A:G,6,0)) -> 6711 | N53: =IFERROR(IF(H53="1002","银行账户",IF(H53="1123","供应商",VLOOKUP(I53,亿企科目!A:H,8,0))),"") | O53: =IF(N53=0,IF(M53="1002",K53,""),_xlfn.TEXTAFTER(E53,"-",-1)) -> 税收滞纳金、罚金、罚款 | P53: =VLOOKUP(A53,账簿!B:C,2,0) -> 003010 | Q53: =VLOOKUP(P53,账簿!A:B,2,0) -> 昌邑市昌荣环保科技有限公司 | W53: =X53&AB53&AD53 -> 0030102026-04-304 | X53: =P53 -> 003010 | Y53: =X53 -> 003010 | Z53: =Q53 -> 昌邑市昌荣环保科技有限公司 | AA53: =LEFT(B53,7) -> 2026-04 | AB53: =B53 -> 2026-04-30 | AC53: 记 | AD53: =VALUE(_xlfn.TEXTAFTER(C53,"-")) -> 4 | AE53: =D53 -> 结转本月损益 | AF53: 谭雅心 | AG53: 谭雅心 | AN53: =M53 -> 6711 | AP53: =D53 -> 结转本月损益 | AQ53: CNY | AR53: =F53 | AS53: =G53 -> 200 | AT53: 01 | AU53: * | AV53: 1 | AW53: =AR53 | AX53: =AS53 -> 200 | BQ53: =IF(N53="项目",VLOOKUP(O53,项目!B:C,2,0),IF(K53="空项目",VLOOKUP(K53,项目!B:C,2,0),"")) | BR53: =IFERROR(VLOOKUP(BQ53,项目!A:B,2,0),"") | BU53: =IF(N53="供应商",VLOOKUP(O53,供应商!B:C,2,0),"") | BV53: =IFERROR(VLOOKUP(BU53,供应商!A:B,2,0),"") | BW53: =IF(N53="客户",VLOOKUP(O53,客户!B:C,2,0),"") | BX53: =IFERROR(VLOOKUP(BW53,客户!A:B,2,0),"") | CU53: =IF(N53="费用项目",VLOOKUP(O53,费用项目!B:C,2,0),"") | CV53: =IFERROR(VLOOKUP(CU53,费用项目!A:B,2,0),"") | CW53: =IF(N53="银行账户",VLOOKUP(O53,银行变二级!B:C,2,0),"") | CX53: =IFERROR(VLOOKUP(O53,银行变二级!A:B,2,0),"")
A54: 昌邑市昌荣农业科技有限责任公司 | B54: 2026-04-02 | C54: 记-001 | D54: 网银转账,山东佳德贸易有限公司 | E54: 100202 银行存款-潍坊银行0950 | F54: 90000000 | H54: =LEFT(E54,4) -> 1002 | I54: =IFERROR(LEFT(E54,FIND(" ",E54)-1),E54) -> 100202 | J54: =LEFT(MID(E54,FIND(" ",E54)+1,LEN(E54)),FIND("-",MID(E54,FIND(" ",E54)+1,LEN(E54))&"-")-1) -> 银行存款 | K54: =IFERROR(MID(MID(E54,FIND(" ",E54)+1,LEN(E54)),FIND("-",MID(E54,FIND(" ",E54)+1,LEN(E54)))+1,IFERROR(FIND("-",MID(E54,FIND(" ",E54)+1,LEN(E54)),FIND("-",MID(E54,FIND(" ",E54)+1,LEN(E54)))+1),LEN(MID(E54,FIND(" ",E54)+1,LEN(E54)))+1)-FIND("-",MID(E54,FIND(" ",E54)+1,LEN(E54)))-1),"") -> 潍坊银行0950 | L54: =IFERROR(MID(MID(E54,FIND(" ",E54)+1,LEN(E54)),FIND("-",MID(E54,FIND(" ",E54)+1,LEN(E54)),FIND("-",MID(E54,FIND(" ",E54)+1,LEN(E54)))+1)+1,LEN(E54)),"") | M54: =IFERROR(IF(H54="1002",1002,VLOOKUP(I54,亿企科目!A:H,6,0)),VLOOKUP(H54,亿企科目!A:G,6,0)) -> 1002 | N54: =IFERROR(IF(H54="1002","银行账户",IF(H54="1123","供应商",VLOOKUP(I54,亿企科目!A:H,8,0))),"") -> 银行账户 | O54: =IF(N54=0,IF(M54="1002",K54,""),_xlfn.TEXTAFTER(E54,"-",-1)) -> 潍坊银行0950 | P54: =VLOOKUP(A54,账簿!B:C,2,0) -> 030006 | Q54: =VLOOKUP(P54,账簿!A:B,2,0) -> 昌邑市昌荣农业科技有限责任公司 | W54: =X54&AB54&AD54 -> 0300062026-04-021 | X54: =P54 -> 030006 | Y54: =X54 -> 030006 | Z54: =Q54 -> 昌邑市昌荣农业科技有限责任公司 | AA54: =LEFT(B54,7) -> 2026-04 | AB54: =B54 -> 2026-04-02 | AC54: 记 | AD54: =VALUE(_xlfn.TEXTAFTER(C54,"-")) -> 1 | AE54: =D54 -> 网银转账,山东佳德贸易有限公司 | AF54: 谭雅心 | AG54: 谭雅心 | AN54: =M54 -> 1002 | AP54: =D54 -> 网银转账,山东佳德贸易有限公司 | AQ54: CNY | AR54: =F54 -> 90000000 | AS54: =G54 | AT54: 01 | AU54: * | AV54: 1 | AW54: =AR54 -> 90000000 | AX54: =AS54 | BQ54: =IF(N54="项目",VLOOKUP(O54,项目!B:C,2,0),IF(K54="空项目",VLOOKUP(K54,项目!B:C,2,0),"")) | BR54: =IFERROR(VLOOKUP(BQ54,项目!A:B,2,0),"") | BU54: =IF(N54="供应商",VLOOKUP(O54,供应商!B:C,2,0),"") | BV54: =IFERROR(VLOOKUP(BU54,供应商!A:B,2,0),"") | BW54: =IF(N54="客户",VLOOKUP(O54,客户!B:C,2,0),"") | BX54: =IFERROR(VLOOKUP(BW54,客户!A:B,2,0),"") | CU54: =IF(N54="费用项目",VLOOKUP(O54,费用项目!B:C,2,0),"") | CV54: =IFERROR(VLOOKUP(CU54,费用项目!A:B,2,0),"") | CW54: =IF(N54="银行账户",VLOOKUP(O54,银行变二级!B:C,2,0),"") -> 潍坊银行0950 | CX54: =IFERROR(VLOOKUP(O54,银行变二级!A:B,2,0),"") -> 潍坊银行0950
A55: 昌邑市昌荣农业科技有限责任公司 | B55: 2026-04-02 | C55: 记-001 | D55: 网银转账,山东佳德贸易有限公司 | E55: 224102 其他应付款-单位-山东佳德贸易有限公司 | G55: 90000000 | H55: =LEFT(E55,4) -> 2241 | I55: =IFERROR(LEFT(E55,FIND(" ",E55)-1),E55) -> 224102 | J55: =LEFT(MID(E55,FIND(" ",E55)+1,LEN(E55)),FIND("-",MID(E55,FIND(" ",E55)+1,LEN(E55))&"-")-1) -> 其他应付款 | K55: =IFERROR(MID(MID(E55,FIND(" ",E55)+1,LEN(E55)),FIND("-",MID(E55,FIND(" ",E55)+1,LEN(E55)))+1,IFERROR(FIND("-",MID(E55,FIND(" ",E55)+1,LEN(E55)),FIND("-",MID(E55,FIND(" ",E55)+1,LEN(E55)))+1),LEN(MID(E55,FIND(" ",E55)+1,LEN(E55)))+1)-FIND("-",MID(E55,FIND(" ",E55)+1,LEN(E55)))-1),"") -> 单位 | L55: =IFERROR(MID(MID(E55,FIND(" ",E55)+1,LEN(E55)),FIND("-",MID(E55,FIND(" ",E55)+1,LEN(E55)),FIND("-",MID(E55,FIND(" ",E55)+1,LEN(E55)))+1)+1,LEN(E55)),"") -> 山东佳德贸易有限公司 | M55: =IFERROR(IF(H55="1002",1002,VLOOKUP(I55,亿企科目!A:H,6,0)),VLOOKUP(H55,亿企科目!A:G,6,0)) -> 224102 | N55: =IFERROR(IF(H55="1002","银行账户",IF(H55="1123","供应商",VLOOKUP(I55,亿企科目!A:H,8,0))),"") -> 供应商 | O55: =IF(N55=0,IF(M55="1002",K55,""),_xlfn.TEXTAFTER(E55,"-",-1)) -> 山东佳德贸易有限公司 | P55: =VLOOKUP(A55,账簿!B:C,2,0) -> 030006 | Q55: =VLOOKUP(P55,账簿!A:B,2,0) -> 昌邑市昌荣农业科技有限责任公司 | W55: =X55&AB55&AD55 -> 0300062026-04-021 | X55: =P55 -> 030006 | Y55: =X55 -> 030006 | Z55: =Q55 -> 昌邑市昌荣农业科技有限责任公司 | AA55: =LEFT(B55,7) -> 2026-04 | AB55: =B55 -> 2026-04-02 | AC55: 记 | AD55: =VALUE(_xlfn.TEXTAFTER(C55,"-")) -> 1 | AE55: =D55 -> 网银转账,山东佳德贸易有限公司 | AF55: 谭雅心 | AG55: 谭雅心 | AN55: =M55 -> 224102 | AP55: =D55 -> 网银转账,山东佳德贸易有限公司 | AQ55: CNY | AR55: =F55 | AS55: =G55 -> 90000000 | AT55: 01 | AU55: * | AV55: 1 | AW55: =AR55 | AX55: =AS55 -> 90000000 | BQ55: =IF(N55="项目",VLOOKUP(O55,项目!B:C,2,0),IF(K55="空项目",VLOOKUP(K55,项目!B:C,2,0),"")) | BR55: =IFERROR(VLOOKUP(BQ55,项目!A:B,2,0),"") | BU55: =IF(N55="供应商",VLOOKUP(O55,供应商!B:C,2,0),"") -> 0015321 | BV55: =IFERROR(VLOOKUP(BU55,供应商!A:B,2,0),"") -> 山东佳德贸易有限公司 | BW55: =IF(N55="客户",VLOOKUP(O55,客户!B:C,2,0),"") | BX55: =IFERROR(VLOOKUP(BW55,客户!A:B,2,0),"") | CU55: =IF(N55="费用项目",VLOOKUP(O55,费用项目!B:C,2,0),"") | CV55: =IFERROR(VLOOKUP(CU55,费用项目!A:B,2,0),"") | CW55: =IF(N55="银行账户",VLOOKUP(O55,银行变二级!B:C,2,0),"") | CX55: =IFERROR(VLOOKUP(O55,银行变二级!A:B,2,0),"")
A56: 昌邑市昌荣农业科技有限责任公司 | B56: 2026-04-02 | C56: 记-002 | D56: 网银转账,昌邑市昌盛管网建设投资有限公司 | E56: 122108 其他应收款-单位-昌邑市昌盛管网建设投资有限公司 | F56: 90000000 | H56: =LEFT(E56,4) -> 1221 | I56: =IFERROR(LEFT(E56,FIND(" ",E56)-1),E56) -> 122108 | J56: =LEFT(MID(E56,FIND(" ",E56)+1,LEN(E56)),FIND("-",MID(E56,FIND(" ",E56)+1,LEN(E56))&"-")-1) -> 其他应收款 | K56: =IFERROR(MID(MID(E56,FIND(" ",E56)+1,LEN(E56)),FIND("-",MID(E56,FIND(" ",E56)+1,LEN(E56)))+1,IFERROR(FIND("-",MID(E56,FIND(" ",E56)+1,LEN(E56)),FIND("-",MID(E56,FIND(" ",E56)+1,LEN(E56)))+1),LEN(MID(E56,FIND(" ",E56)+1,LEN(E56)))+1)-FIND("-",MID(E56,FIND(" ",E56)+1,LEN(E56)))-1),"") -> 单位 | L56: =IFERROR(MID(MID(E56,FIND(" ",E56)+1,LEN(E56)),FIND("-",MID(E56,FIND(" ",E56)+1,LEN(E56)),FIND("-",MID(E56,FIND(" ",E56)+1,LEN(E56)))+1)+1,LEN(E56)),"") -> 昌邑市昌盛管网建设投资有限公司 | M56: =IFERROR(IF(H56="1002",1002,VLOOKUP(I56,亿企科目!A:H,6,0)),VLOOKUP(H56,亿企科目!A:G,6,0)) -> 122102 | N56: =IFERROR(IF(H56="1002","银行账户",IF(H56="1123","供应商",VLOOKUP(I56,亿企科目!A:H,8,0))),"") -> 客户 | O56: =IF(N56=0,IF(M56="1002",K56,""),_xlfn.TEXTAFTER(E56,"-",-1)) -> 昌邑市昌盛管网建设投资有限公司 | P56: =VLOOKUP(A56,账簿!B:C,2,0) -> 030006 | Q56: =VLOOKUP(P56,账簿!A:B,2,0) -> 昌邑市昌荣农业科技有限责任公司 | W56: =X56&AB56&AD56 -> 0300062026-04-022 | X56: =P56 -> 030006 | Y56: =X56 -> 030006 | Z56: =Q56 -> 昌邑市昌荣农业科技有限责任公司 | AA56: =LEFT(B56,7) -> 2026-04 | AB56: =B56 -> 2026-04-02 | AC56: 记 | AD56: =VALUE(_xlfn.TEXTAFTER(C56,"-")) -> 2 | AE56: =D56 -> 网银转账,昌邑市昌盛管网建设投资有限公司 | AF56: 谭雅心 | AG56: 谭雅心 | AN56: =M56 -> 122102 | AP56: =D56 -> 网银转账,昌邑市昌盛管网建设投资有限公司 | AQ56: CNY | AR56: =F56 -> 90000000 | AS56: =G56 | AT56: 01 | AU56: * | AV56: 1 | AW56: =AR56 -> 90000000 | AX56: =AS56 | BQ56: =IF(N56="项目",VLOOKUP(O56,项目!B:C,2,0),IF(K56="空项目",VLOOKUP(K56,项目!B:C,2,0),"")) | BR56: =IFERROR(VLOOKUP(BQ56,项目!A:B,2,0),"") | BU56: =IF(N56="供应商",VLOOKUP(O56,供应商!B:C,2,0),"") | BV56: =IFERROR(VLOOKUP(BU56,供应商!A:B,2,0),"") | BW56: =IF(N56="客户",VLOOKUP(O56,客户!B:C,2,0),"") -> 001001001 | BX56: =IFERROR(VLOOKUP(BW56,客户!A:B,2,0),"") -> 昌邑市昌盛管网建设投资有限公司 | CU56: =IF(N56="费用项目",VLOOKUP(O56,费用项目!B:C,2,0),"") | CV56: =IFERROR(VLOOKUP(CU56,费用项目!A:B,2,0),"") | CW56: =IF(N56="银行账户",VLOOKUP(O56,银行变二级!B:C,2,0),"") | CX56: =IFERROR(VLOOKUP(O56,银行变二级!A:B,2,0),"")
A57: 昌邑市昌荣农业科技有限责任公司 | B57: 2026-04-02 | C57: 记-002 | D57: 网银转账,昌邑市昌盛管网建设投资有限公司 | E57: 100202 银行存款-潍坊银行0950 | G57: 90000000 | H57: =LEFT(E57,4) -> 1002 | I57: =IFERROR(LEFT(E57,FIND(" ",E57)-1),E57) -> 100202 | J57: =LEFT(MID(E57,FIND(" ",E57)+1,LEN(E57)),FIND("-",MID(E57,FIND(" ",E57)+1,LEN(E57))&"-")-1) -> 银行存款 | K57: =IFERROR(MID(MID(E57,FIND(" ",E57)+1,LEN(E57)),FIND("-",MID(E57,FIND(" ",E57)+1,LEN(E57)))+1,IFERROR(FIND("-",MID(E57,FIND(" ",E57)+1,LEN(E57)),FIND("-",MID(E57,FIND(" ",E57)+1,LEN(E57)))+1),LEN(MID(E57,FIND(" ",E57)+1,LEN(E57)))+1)-FIND("-",MID(E57,FIND(" ",E57)+1,LEN(E57)))-1),"") -> 潍坊银行0950 | L57: =IFERROR(MID(MID(E57,FIND(" ",E57)+1,LEN(E57)),FIND("-",MID(E57,FIND(" ",E57)+1,LEN(E57)),FIND("-",MID(E57,FIND(" ",E57)+1,LEN(E57)))+1)+1,LEN(E57)),"") | M57: =IFERROR(IF(H57="1002",1002,VLOOKUP(I57,亿企科目!A:H,6,0)),VLOOKUP(H57,亿企科目!A:G,6,0)) -> 1002 | N57: =IFERROR(IF(H57="1002","银行账户",IF(H57="1123","供应商",VLOOKUP(I57,亿企科目!A:H,8,0))),"") -> 银行账户 | O57: =IF(N57=0,IF(M57="1002",K57,""),_xlfn.TEXTAFTER(E57,"-",-1)) -> 潍坊银行0950 | P57: =VLOOKUP(A57,账簿!B:C,2,0) -> 030006 | Q57: =VLOOKUP(P57,账簿!A:B,2,0) -> 昌邑市昌荣农业科技有限责任公司 | W57: =X57&AB57&AD57 -> 0300062026-04-022 | X57: =P57 -> 030006 | Y57: =X57 -> 030006 | Z57: =Q57 -> 昌邑市昌荣农业科技有限责任公司 | AA57: =LEFT(B57,7) -> 2026-04 | AB57: =B57 -> 2026-04-02 | AC57: 记 | AD57: =VALUE(_xlfn.TEXTAFTER(C57,"-")) -> 2 | AE57: =D57 -> 网银转账,昌邑市昌盛管网建设投资有限公司 | AF57: 谭雅心 | AG57: 谭雅心 | AN57: =M57 -> 1002 | AP57: =D57 -> 网银转账,昌邑市昌盛管网建设投资有限公司 | AQ57: CNY | AR57: =F57 | AS57: =G57 -> 90000000 | AT57: 01 | AU57: * | AV57: 1 | AW57: =AR57 | AX57: =AS57 -> 90000000 | BQ57: =IF(N57="项目",VLOOKUP(O57,项目!B:C,2,0),IF(K57="空项目",VLOOKUP(K57,项目!B:C,2,0),"")) | BR57: =IFERROR(VLOOKUP(BQ57,项目!A:B,2,0),"") | BU57: =IF(N57="供应商",VLOOKUP(O57,供应商!B:C,2,0),"") | BV57: =IFERROR(VLOOKUP(BU57,供应商!A:B,2,0),"") | BW57: =IF(N57="客户",VLOOKUP(O57,客户!B:C,2,0),"") | BX57: =IFERROR(VLOOKUP(BW57,客户!A:B,2,0),"") | CU57: =IF(N57="费用项目",VLOOKUP(O57,费用项目!B:C,2,0),"") | CV57: =IFERROR(VLOOKUP(CU57,费用项目!A:B,2,0),"") | CW57: =IF(N57="银行账户",VLOOKUP(O57,银行变二级!B:C,2,0),"") -> 潍坊银行0950 | CX57: =IFERROR(VLOOKUP(O57,银行变二级!A:B,2,0),"") -> 潍坊银行0950
A58: 昌邑市昌荣农业科技有限责任公司 | B58: 2026-04-02 | C58: 记-003 | D58: 汇款,山东佳德贸易有限公司 | E58: 100202 银行存款-潍坊银行0950 | F58: 6000000 | H58: =LEFT(E58,4) -> 1002 | I58: =IFERROR(LEFT(E58,FIND(" ",E58)-1),E58) -> 100202 | J58: =LEFT(MID(E58,FIND(" ",E58)+1,LEN(E58)),FIND("-",MID(E58,FIND(" ",E58)+1,LEN(E58))&"-")-1) -> 银行存款 | K58: =IFERROR(MID(MID(E58,FIND(" ",E58)+1,LEN(E58)),FIND("-",MID(E58,FIND(" ",E58)+1,LEN(E58)))+1,IFERROR(FIND("-",MID(E58,FIND(" ",E58)+1,LEN(E58)),FIND("-",MID(E58,FIND(" ",E58)+1,LEN(E58)))+1),LEN(MID(E58,FIND(" ",E58)+1,LEN(E58)))+1)-FIND("-",MID(E58,FIND(" ",E58)+1,LEN(E58)))-1),"") -> 潍坊银行0950 | L58: =IFERROR(MID(MID(E58,FIND(" ",E58)+1,LEN(E58)),FIND("-",MID(E58,FIND(" ",E58)+1,LEN(E58)),FIND("-",MID(E58,FIND(" ",E58)+1,LEN(E58)))+1)+1,LEN(E58)),"") | M58: =IFERROR(IF(H58="1002",1002,VLOOKUP(I58,亿企科目!A:H,6,0)),VLOOKUP(H58,亿企科目!A:G,6,0)) -> 1002 | N58: =IFERROR(IF(H58="1002","银行账户",IF(H58="1123","供应商",VLOOKUP(I58,亿企科目!A:H,8,0))),"") -> 银行账户 | O58: =IF(N58=0,IF(M58="1002",K58,""),_xlfn.TEXTAFTER(E58,"-",-1)) -> 潍坊银行0950 | P58: =VLOOKUP(A58,账簿!B:C,2,0) -> 030006 | Q58: =VLOOKUP(P58,账簿!A:B,2,0) -> 昌邑市昌荣农业科技有限责任公司 | W58: =X58&AB58&AD58 -> 0300062026-04-023 | X58: =P58 -> 030006 | Y58: =X58 -> 030006 | Z58: =Q58 -> 昌邑市昌荣农业科技有限责任公司 | AA58: =LEFT(B58,7) -> 2026-04 | AB58: =B58 -> 2026-04-02 | AC58: 记 | AD58: =VALUE(_xlfn.TEXTAFTER(C58,"-")) -> 3 | AE58: =D58 -> 汇款,山东佳德贸易有限公司 | AF58: 谭雅心 | AG58: 谭雅心 | AN58: =M58 -> 1002 | AP58: =D58 -> 汇款,山东佳德贸易有限公司 | AQ58: CNY | AR58: =F58 -> 6000000 | AS58: =G58 | AT58: 01 | AU58: * | AV58: 1 | AW58: =AR58 -> 6000000 | AX58: =AS58 | BQ58: =IF(N58="项目",VLOOKUP(O58,项目!B:C,2,0),IF(K58="空项目",VLOOKUP(K58,项目!B:C,2,0),"")) | BR58: =IFERROR(VLOOKUP(BQ58,项目!A:B,2,0),"") | BU58: =IF(N58="供应商",VLOOKUP(O58,供应商!B:C,2,0),"") | BV58: =IFERROR(VLOOKUP(BU58,供应商!A:B,2,0),"") | BW58: =IF(N58="客户",VLOOKUP(O58,客户!B:C,2,0),"") | BX58: =IFERROR(VLOOKUP(BW58,客户!A:B,2,0),"") | CU58: =IF(N58="费用项目",VLOOKUP(O58,费用项目!B:C,2,0),"") | CV58: =IFERROR(VLOOKUP(CU58,费用项目!A:B,2,0),"") | CW58: =IF(N58="银行账户",VLOOKUP(O58,银行变二级!B:C,2,0),"") -> 潍坊银行0950 | CX58: =IFERROR(VLOOKUP(O58,银行变二级!A:B,2,0),"") -> 潍坊银行0950
A59: 昌邑市昌荣农业科技有限责任公司 | B59: 2026-04-02 | C59: 记-003 | D59: 汇款,山东佳德贸易有限公司 | E59: 224102 其他应付款-单位-山东佳德贸易有限公司 | G59: 6000000 | H59: =LEFT(E59,4) -> 2241 | I59: =IFERROR(LEFT(E59,FIND(" ",E59)-1),E59) -> 224102 | J59: =LEFT(MID(E59,FIND(" ",E59)+1,LEN(E59)),FIND("-",MID(E59,FIND(" ",E59)+1,LEN(E59))&"-")-1) -> 其他应付款 | K59: =IFERROR(MID(MID(E59,FIND(" ",E59)+1,LEN(E59)),FIND("-",MID(E59,FIND(" ",E59)+1,LEN(E59)))+1,IFERROR(FIND("-",MID(E59,FIND(" ",E59)+1,LEN(E59)),FIND("-",MID(E59,FIND(" ",E59)+1,LEN(E59)))+1),LEN(MID(E59,FIND(" ",E59)+1,LEN(E59)))+1)-FIND("-",MID(E59,FIND(" ",E59)+1,LEN(E59)))-1),"") -> 单位 | L59: =IFERROR(MID(MID(E59,FIND(" ",E59)+1,LEN(E59)),FIND("-",MID(E59,FIND(" ",E59)+1,LEN(E59)),FIND("-",MID(E59,FIND(" ",E59)+1,LEN(E59)))+1)+1,LEN(E59)),"") -> 山东佳德贸易有限公司 | M59: =IFERROR(IF(H59="1002",1002,VLOOKUP(I59,亿企科目!A:H,6,0)),VLOOKUP(H59,亿企科目!A:G,6,0)) -> 224102 | N59: =IFERROR(IF(H59="1002","银行账户",IF(H59="1123","供应商",VLOOKUP(I59,亿企科目!A:H,8,0))),"") -> 供应商 | O59: =IF(N59=0,IF(M59="1002",K59,""),_xlfn.TEXTAFTER(E59,"-",-1)) -> 山东佳德贸易有限公司 | P59: =VLOOKUP(A59,账簿!B:C,2,0) -> 030006 | Q59: =VLOOKUP(P59,账簿!A:B,2,0) -> 昌邑市昌荣农业科技有限责任公司 | W59: =X59&AB59&AD59 -> 0300062026-04-023 | X59: =P59 -> 030006 | Y59: =X59 -> 030006 | Z59: =Q59 -> 昌邑市昌荣农业科技有限责任公司 | AA59: =LEFT(B59,7) -> 2026-04 | AB59: =B59 -> 2026-04-02 | AC59: 记 | AD59: =VALUE(_xlfn.TEXTAFTER(C59,"-")) -> 3 | AE59: =D59 -> 汇款,山东佳德贸易有限公司 | AF59: 谭雅心 | AG59: 谭雅心 | AN59: =M59 -> 224102 | AP59: =D59 -> 汇款,山东佳德贸易有限公司 | AQ59: CNY | AR59: =F59 | AS59: =G59 -> 6000000 | AT59: 01 | AU59: * | AV59: 1 | AW59: =AR59 | AX59: =AS59 -> 6000000 | BQ59: =IF(N59="项目",VLOOKUP(O59,项目!B:C,2,0),IF(K59="空项目",VLOOKUP(K59,项目!B:C,2,0),"")) | BR59: =IFERROR(VLOOKUP(BQ59,项目!A:B,2,0),"") | BU59: =IF(N59="供应商",VLOOKUP(O59,供应商!B:C,2,0),"") -> 0015321 | BV59: =IFERROR(VLOOKUP(BU59,供应商!A:B,2,0),"") -> 山东佳德贸易有限公司 | BW59: =IF(N59="客户",VLOOKUP(O59,客户!B:C,2,0),"") | BX59: =IFERROR(VLOOKUP(BW59,客户!A:B,2,0),"") | CU59: =IF(N59="费用项目",VLOOKUP(O59,费用项目!B:C,2,0),"") | CV59: =IFERROR(VLOOKUP(CU59,费用项目!A:B,2,0),"") | CW59: =IF(N59="银行账户",VLOOKUP(O59,银行变二级!B:C,2,0),"") | CX59: =IFERROR(VLOOKUP(O59,银行变二级!A:B,2,0),"")
A60: 昌邑市昌荣农业科技有限责任公司 | B60: 2026-04-03 | C60: 记-004 | D60: 网银转账,昌邑市昌盛管网建设投资有限公司 | E60: 122108 其他应收款-单位-昌邑市昌盛管网建设投资有限公司 | F60: 6000000 | H60: =LEFT(E60,4) -> 1221 | I60: =IFERROR(LEFT(E60,FIND(" ",E60)-1),E60) -> 122108 | J60: =LEFT(MID(E60,FIND(" ",E60)+1,LEN(E60)),FIND("-",MID(E60,FIND(" ",E60)+1,LEN(E60))&"-")-1) -> 其他应收款 | K60: =IFERROR(MID(MID(E60,FIND(" ",E60)+1,LEN(E60)),FIND("-",MID(E60,FIND(" ",E60)+1,LEN(E60)))+1,IFERROR(FIND("-",MID(E60,FIND(" ",E60)+1,LEN(E60)),FIND("-",MID(E60,FIND(" ",E60)+1,LEN(E60)))+1),LEN(MID(E60,FIND(" ",E60)+1,LEN(E60)))+1)-FIND("-",MID(E60,FIND(" ",E60)+1,LEN(E60)))-1),"") -> 单位 | L60: =IFERROR(MID(MID(E60,FIND(" ",E60)+1,LEN(E60)),FIND("-",MID(E60,FIND(" ",E60)+1,LEN(E60)),FIND("-",MID(E60,FIND(" ",E60)+1,LEN(E60)))+1)+1,LEN(E60)),"") -> 昌邑市昌盛管网建设投资有限公司 | M60: =IFERROR(IF(H60="1002",1002,VLOOKUP(I60,亿企科目!A:H,6,0)),VLOOKUP(H60,亿企科目!A:G,6,0)) -> 122102 | N60: =IFERROR(IF(H60="1002","银行账户",IF(H60="1123","供应商",VLOOKUP(I60,亿企科目!A:H,8,0))),"") -> 客户 | O60: =IF(N60=0,IF(M60="1002",K60,""),_xlfn.TEXTAFTER(E60,"-",-1)) -> 昌邑市昌盛管网建设投资有限公司 | P60: =VLOOKUP(A60,账簿!B:C,2,0) -> 030006 | Q60: =VLOOKUP(P60,账簿!A:B,2,0) -> 昌邑市昌荣农业科技有限责任公司 | W60: =X60&AB60&AD60 -> 0300062026-04-034 | X60: =P60 -> 030006 | Y60: =X60 -> 030006 | Z60: =Q60 -> 昌邑市昌荣农业科技有限责任公司 | AA60: =LEFT(B60,7) -> 2026-04 | AB60: =B60 -> 2026-04-03 | AC60: 记 | AD60: =VALUE(_xlfn.TEXTAFTER(C60,"-")) -> 4 | AE60: =D60 -> 网银转账,昌邑市昌盛管网建设投资有限公司 | AF60: 谭雅心 | AG60: 谭雅心 | AN60: =M60 -> 122102 | AP60: =D60 -> 网银转账,昌邑市昌盛管网建设投资有限公司 | AQ60: CNY | AR60: =F60 -> 6000000 | AS60: =G60 | AT60: 01 | AU60: * | AV60: 1 | AW60: =AR60 -> 6000000 | AX60: =AS60 | BQ60: =IF(N60="项目",VLOOKUP(O60,项目!B:C,2,0),IF(K60="空项目",VLOOKUP(K60,项目!B:C,2,0),"")) | BR60: =IFERROR(VLOOKUP(BQ60,项目!A:B,2,0),"") | BU60: =IF(N60="供应商",VLOOKUP(O60,供应商!B:C,2,0),"") | BV60: =IFERROR(VLOOKUP(BU60,供应商!A:B,2,0),"") | BW60: =IF(N60="客户",VLOOKUP(O60,客户!B:C,2,0),"") -> 001001001 | BX60: =IFERROR(VLOOKUP(BW60,客户!A:B,2,0),"") -> 昌邑市昌盛管网建设投资有限公司 | CU60: =IF(N60="费用项目",VLOOKUP(O60,费用项目!B:C,2,0),"") | CV60: =IFERROR(VLOOKUP(CU60,费用项目!A:B,2,0),"") | CW60: =IF(N60="银行账户",VLOOKUP(O60,银行变二级!B:C,2,0),"") | CX60: =IFERROR(VLOOKUP(O60,银行变二级!A:B,2,0),"")
A61: 昌邑市昌荣农业科技有限责任公司 | B61: 2026-04-03 | C61: 记-004 | D61: 网银转账,昌邑市昌盛管网建设投资有限公司 | E61: 100202 银行存款-潍坊银行0950 | G61: 6000000 | H61: =LEFT(E61,4) -> 1002 | I61: =IFERROR(LEFT(E61,FIND(" ",E61)-1),E61) -> 100202 | J61: =LEFT(MID(E61,FIND(" ",E61)+1,LEN(E61)),FIND("-",MID(E61,FIND(" ",E61)+1,LEN(E61))&"-")-1) -> 银行存款 | K61: =IFERROR(MID(MID(E61,FIND(" ",E61)+1,LEN(E61)),FIND("-",MID(E61,FIND(" ",E61)+1,LEN(E61)))+1,IFERROR(FIND("-",MID(E61,FIND(" ",E61)+1,LEN(E61)),FIND("-",MID(E61,FIND(" ",E61)+1,LEN(E61)))+1),LEN(MID(E61,FIND(" ",E61)+1,LEN(E61)))+1)-FIND("-",MID(E61,FIND(" ",E61)+1,LEN(E61)))-1),"") -> 潍坊银行0950 | L61: =IFERROR(MID(MID(E61,FIND(" ",E61)+1,LEN(E61)),FIND("-",MID(E61,FIND(" ",E61)+1,LEN(E61)),FIND("-",MID(E61,FIND(" ",E61)+1,LEN(E61)))+1)+1,LEN(E61)),"") | M61: =IFERROR(IF(H61="1002",1002,VLOOKUP(I61,亿企科目!A:H,6,0)),VLOOKUP(H61,亿企科目!A:G,6,0)) -> 1002 | N61: =IFERROR(IF(H61="1002","银行账户",IF(H61="1123","供应商",VLOOKUP(I61,亿企科目!A:H,8,0))),"") -> 银行账户 | O61: =IF(N61=0,IF(M61="1002",K61,""),_xlfn.TEXTAFTER(E61,"-",-1)) -> 潍坊银行0950 | P61: =VLOOKUP(A61,账簿!B:C,2,0) -> 030006 | Q61: =VLOOKUP(P61,账簿!A:B,2,0) -> 昌邑市昌荣农业科技有限责任公司 | W61: =X61&AB61&AD61 -> 0300062026-04-034 | X61: =P61 -> 030006 | Y61: =X61 -> 030006 | Z61: =Q61 -> 昌邑市昌荣农业科技有限责任公司 | AA61: =LEFT(B61,7) -> 2026-04 | AB61: =B61 -> 2026-04-03 | AC61: 记 | AD61: =VALUE(_xlfn.TEXTAFTER(C61,"-")) -> 4 | AE61: =D61 -> 网银转账,昌邑市昌盛管网建设投资有限公司 | AF61: 谭雅心 | AG61: 谭雅心 | AN61: =M61 -> 1002 | AP61: =D61 -> 网银转账,昌邑市昌盛管网建设投资有限公司 | AQ61: CNY | AR61: =F61 | AS61: =G61 -> 6000000 | AT61: 01 | AU61: * | AV61: 1 | AW61: =AR61 | AX61: =AS61 -> 6000000 | BQ61: =IF(N61="项目",VLOOKUP(O61,项目!B:C,2,0),IF(K61="空项目",VLOOKUP(K61,项目!B:C,2,0),"")) | BR61: =IFERROR(VLOOKUP(BQ61,项目!A:B,2,0),"") | BU61: =IF(N61="供应商",VLOOKUP(O61,供应商!B:C,2,0),"") | BV61: =IFERROR(VLOOKUP(BU61,供应商!A:B,2,0),"") | BW61: =IF(N61="客户",VLOOKUP(O61,客户!B:C,2,0),"") | BX61: =IFERROR(VLOOKUP(BW61,客户!A:B,2,0),"") | CU61: =IF(N61="费用项目",VLOOKUP(O61,费用项目!B:C,2,0),"") | CV61: =IFERROR(VLOOKUP(CU61,费用项目!A:B,2,0),"") | CW61: =IF(N61="银行账户",VLOOKUP(O61,银行变二级!B:C,2,0),"") -> 潍坊银行0950 | CX61: =IFERROR(VLOOKUP(O61,银行变二级!A:B,2,0),"") -> 潍坊银行0950
A62: 昌邑市昌荣农业科技有限责任公司 | B62: 2026-04-14 | C62: 记-005 | D62: 税收罚金 | E62: 671101 营业外支出-税收滞纳金、罚金、罚款 | F62: 69.5 | H62: =LEFT(E62,4) -> 6711 | I62: =IFERROR(LEFT(E62,FIND(" ",E62)-1),E62) -> 671101 | J62: =LEFT(MID(E62,FIND(" ",E62)+1,LEN(E62)),FIND("-",MID(E62,FIND(" ",E62)+1,LEN(E62))&"-")-1) -> 营业外支出 | K62: =IFERROR(MID(MID(E62,FIND(" ",E62)+1,LEN(E62)),FIND("-",MID(E62,FIND(" ",E62)+1,LEN(E62)))+1,IFERROR(FIND("-",MID(E62,FIND(" ",E62)+1,LEN(E62)),FIND("-",MID(E62,FIND(" ",E62)+1,LEN(E62)))+1),LEN(MID(E62,FIND(" ",E62)+1,LEN(E62)))+1)-FIND("-",MID(E62,FIND(" ",E62)+1,LEN(E62)))-1),"") -> 税收滞纳金、罚金、罚款 | L62: =IFERROR(MID(MID(E62,FIND(" ",E62)+1,LEN(E62)),FIND("-",MID(E62,FIND(" ",E62)+1,LEN(E62)),FIND("-",MID(E62,FIND(" ",E62)+1,LEN(E62)))+1)+1,LEN(E62)),"") | M62: =IFERROR(IF(H62="1002",1002,VLOOKUP(I62,亿企科目!A:H,6,0)),VLOOKUP(H62,亿企科目!A:G,6,0)) -> 6711 | N62: =IFERROR(IF(H62="1002","银行账户",IF(H62="1123","供应商",VLOOKUP(I62,亿企科目!A:H,8,0))),"") | O62: =IF(N62=0,IF(M62="1002",K62,""),_xlfn.TEXTAFTER(E62,"-",-1)) -> 税收滞纳金、罚金、罚款 | P62: =VLOOKUP(A62,账簿!B:C,2,0) -> 030006 | Q62: =VLOOKUP(P62,账簿!A:B,2,0) -> 昌邑市昌荣农业科技有限责任公司 | W62: =X62&AB62&AD62 -> 0300062026-04-145 | X62: =P62 -> 030006 | Y62: =X62 -> 030006 | Z62: =Q62 -> 昌邑市昌荣农业科技有限责任公司 | AA62: =LEFT(B62,7) -> 2026-04 | AB62: =B62 -> 2026-04-14 | AC62: 记 | AD62: =VALUE(_xlfn.TEXTAFTER(C62,"-")) -> 5 | AE62: =D62 -> 税收罚金 | AF62: 谭雅心 | AG62: 谭雅心 | AN62: =M62 -> 6711 | AP62: =D62 -> 税收罚金 | AQ62: CNY | AR62: =F62 -> 69.5 | AS62: =G62 | AT62: 01 | AU62: * | AV62: 1 | AW62: =AR62 -> 69.5 | AX62: =AS62 | BQ62: =IF(N62="项目",VLOOKUP(O62,项目!B:C,2,0),IF(K62="空项目",VLOOKUP(K62,项目!B:C,2,0),"")) | BR62: =IFERROR(VLOOKUP(BQ62,项目!A:B,2,0),"") | BU62: =IF(N62="供应商",VLOOKUP(O62,供应商!B:C,2,0),"") | BV62: =IFERROR(VLOOKUP(BU62,供应商!A:B,2,0),"") | BW62: =IF(N62="客户",VLOOKUP(O62,客户!B:C,2,0),"") | BX62: =IFERROR(VLOOKUP(BW62,客户!A:B,2,0),"") | CU62: =IF(N62="费用项目",VLOOKUP(O62,费用项目!B:C,2,0),"") | CV62: =IFERROR(VLOOKUP(CU62,费用项目!A:B,2,0),"") | CW62: =IF(N62="银行账户",VLOOKUP(O62,银行变二级!B:C,2,0),"") | CX62: =IFERROR(VLOOKUP(O62,银行变二级!A:B,2,0),"")
A63: 昌邑市昌荣农业科技有限责任公司 | B63: 2026-04-14 | C63: 记-005 | D63: 税收罚金 | E63: 100202 银行存款-潍坊银行0950 | G63: 69.5 | H63: =LEFT(E63,4) -> 1002 | I63: =IFERROR(LEFT(E63,FIND(" ",E63)-1),E63) -> 100202 | J63: =LEFT(MID(E63,FIND(" ",E63)+1,LEN(E63)),FIND("-",MID(E63,FIND(" ",E63)+1,LEN(E63))&"-")-1) -> 银行存款 | K63: =IFERROR(MID(MID(E63,FIND(" ",E63)+1,LEN(E63)),FIND("-",MID(E63,FIND(" ",E63)+1,LEN(E63)))+1,IFERROR(FIND("-",MID(E63,FIND(" ",E63)+1,LEN(E63)),FIND("-",MID(E63,FIND(" ",E63)+1,LEN(E63)))+1),LEN(MID(E63,FIND(" ",E63)+1,LEN(E63)))+1)-FIND("-",MID(E63,FIND(" ",E63)+1,LEN(E63)))-1),"") -> 潍坊银行0950 | L63: =IFERROR(MID(MID(E63,FIND(" ",E63)+1,LEN(E63)),FIND("-",MID(E63,FIND(" ",E63)+1,LEN(E63)),FIND("-",MID(E63,FIND(" ",E63)+1,LEN(E63)))+1)+1,LEN(E63)),"") | M63: =IFERROR(IF(H63="1002",1002,VLOOKUP(I63,亿企科目!A:H,6,0)),VLOOKUP(H63,亿企科目!A:G,6,0)) -> 1002 | N63: =IFERROR(IF(H63="1002","银行账户",IF(H63="1123","供应商",VLOOKUP(I63,亿企科目!A:H,8,0))),"") -> 银行账户 | O63: =IF(N63=0,IF(M63="1002",K63,""),_xlfn.TEXTAFTER(E63,"-",-1)) -> 潍坊银行0950 | P63: =VLOOKUP(A63,账簿!B:C,2,0) -> 030006 | Q63: =VLOOKUP(P63,账簿!A:B,2,0) -> 昌邑市昌荣农业科技有限责任公司 | W63: =X63&AB63&AD63 -> 0300062026-04-145 | X63: =P63 -> 030006 | Y63: =X63 -> 030006 | Z63: =Q63 -> 昌邑市昌荣农业科技有限责任公司 | AA63: =LEFT(B63,7) -> 2026-04 | AB63: =B63 -> 2026-04-14 | AC63: 记 | AD63: =VALUE(_xlfn.TEXTAFTER(C63,"-")) -> 5 | AE63: =D63 -> 税收罚金 | AF63: 谭雅心 | AG63: 谭雅心 | AN63: =M63 -> 1002 | AP63: =D63 -> 税收罚金 | AQ63: CNY | AR63: =F63 | AS63: =G63 -> 69.5 | AT63: 01 | AU63: * | AV63: 1 | AW63: =AR63 | AX63: =AS63 -> 69.5 | BQ63: =IF(N63="项目",VLOOKUP(O63,项目!B:C,2,0),IF(K63="空项目",VLOOKUP(K63,项目!B:C,2,0),"")) | BR63: =IFERROR(VLOOKUP(BQ63,项目!A:B,2,0),"") | BU63: =IF(N63="供应商",VLOOKUP(O63,供应商!B:C,2,0),"") | BV63: =IFERROR(VLOOKUP(BU63,供应商!A:B,2,0),"") | BW63: =IF(N63="客户",VLOOKUP(O63,客户!B:C,2,0),"") | BX63: =IFERROR(VLOOKUP(BW63,客户!A:B,2,0),"") | CU63: =IF(N63="费用项目",VLOOKUP(O63,费用项目!B:C,2,0),"") | CV63: =IFERROR(VLOOKUP(CU63,费用项目!A:B,2,0),"") | CW63: =IF(N63="银行账户",VLOOKUP(O63,银行变二级!B:C,2,0),"") -> 潍坊银行0950 | CX63: =IFERROR(VLOOKUP(O63,银行变二级!A:B,2,0),"") -> 潍坊银行0950
A64: 昌邑市昌荣农业科技有限责任公司 | B64: 2026-04-21 | C64: 记-006 | D64: 贷款还款,昌邑市昌荣农业科技有限责任公司 | E64: 6603 财务费用-利息支出 | F64: 476537.42 | H64: =LEFT(E64,4) -> 6603 | I64: =IFERROR(LEFT(E64,FIND(" ",E64)-1),E64) -> 6603 | J64: =LEFT(MID(E64,FIND(" ",E64)+1,LEN(E64)),FIND("-",MID(E64,FIND(" ",E64)+1,LEN(E64))&"-")-1) -> 财务费用 | K64: =IFERROR(MID(MID(E64,FIND(" ",E64)+1,LEN(E64)),FIND("-",MID(E64,FIND(" ",E64)+1,LEN(E64)))+1,IFERROR(FIND("-",MID(E64,FIND(" ",E64)+1,LEN(E64)),FIND("-",MID(E64,FIND(" ",E64)+1,LEN(E64)))+1),LEN(MID(E64,FIND(" ",E64)+1,LEN(E64)))+1)-FIND("-",MID(E64,FIND(" ",E64)+1,LEN(E64)))-1),"") -> 利息支出 | L64: =IFERROR(MID(MID(E64,FIND(" ",E64)+1,LEN(E64)),FIND("-",MID(E64,FIND(" ",E64)+1,LEN(E64)),FIND("-",MID(E64,FIND(" ",E64)+1,LEN(E64)))+1)+1,LEN(E64)),"") | M64: =IFERROR(IF(H64="1002",1002,VLOOKUP(I64,亿企科目!A:H,6,0)),VLOOKUP(H64,亿企科目!A:G,6,0)) -> 6603 | N64: =IFERROR(IF(H64="1002","银行账户",IF(H64="1123","供应商",VLOOKUP(I64,亿企科目!A:H,8,0))),"") -> 费用项目 | O64: =IF(N64=0,IF(M64="1002",K64,""),_xlfn.TEXTAFTER(E64,"-",-1)) -> 利息支出 | P64: =VLOOKUP(A64,账簿!B:C,2,0) -> 030006 | Q64: =VLOOKUP(P64,账簿!A:B,2,0) -> 昌邑市昌荣农业科技有限责任公司 | W64: =X64&AB64&AD64 -> 0300062026-04-216 | X64: =P64 -> 030006 | Y64: =X64 -> 030006 | Z64: =Q64 -> 昌邑市昌荣农业科技有限责任公司 | AA64: =LEFT(B64,7) -> 2026-04 | AB64: =B64 -> 2026-04-21 | AC64: 记 | AD64: =VALUE(_xlfn.TEXTAFTER(C64,"-")) -> 6 | AE64: =D64 -> 贷款还款,昌邑市昌荣农业科技有限责任公司 | AF64: 谭雅心 | AG64: 谭雅心 | AN64: =M64 -> 6603 | AP64: =D64 -> 贷款还款,昌邑市昌荣农业科技有限责任公司 | AQ64: CNY | AR64: =F64 -> 476537.42 | AS64: =G64 | AT64: 01 | AU64: * | AV64: 1 | AW64: =AR64 -> 476537.42 | AX64: =AS64 | BQ64: =IF(N64="项目",VLOOKUP(O64,项目!B:C,2,0),IF(K64="空项目",VLOOKUP(K64,项目!B:C,2,0),"")) | BR64: =IFERROR(VLOOKUP(BQ64,项目!A:B,2,0),"") | BU64: =IF(N64="供应商",VLOOKUP(O64,供应商!B:C,2,0),"") | BV64: =IFERROR(VLOOKUP(BU64,供应商!A:B,2,0),"") | BW64: =IF(N64="客户",VLOOKUP(O64,客户!B:C,2,0),"") | BX64: =IFERROR(VLOOKUP(BW64,客户!A:B,2,0),"") | CU64: =IF(N64="费用项目",VLOOKUP(O64,费用项目!B:C,2,0),"") -> 660302 | CV64: =IFERROR(VLOOKUP(CU64,费用项目!A:B,2,0),"") -> 利息支出 | CW64: =IF(N64="银行账户",VLOOKUP(O64,银行变二级!B:C,2,0),"") | CX64: =IFERROR(VLOOKUP(O64,银行变二级!A:B,2,0),"")
A65: 昌邑市昌荣农业科技有限责任公司 | B65: 2026-04-21 | C65: 记-006 | D65: 贷款还款,昌邑市昌荣农业科技有限责任公司 | E65: 100202 银行存款-潍坊银行0950 | G65: 476537.42 | H65: =LEFT(E65,4) -> 1002 | I65: =IFERROR(LEFT(E65,FIND(" ",E65)-1),E65) -> 100202 | J65: =LEFT(MID(E65,FIND(" ",E65)+1,LEN(E65)),FIND("-",MID(E65,FIND(" ",E65)+1,LEN(E65))&"-")-1) -> 银行存款 | K65: =IFERROR(MID(MID(E65,FIND(" ",E65)+1,LEN(E65)),FIND("-",MID(E65,FIND(" ",E65)+1,LEN(E65)))+1,IFERROR(FIND("-",MID(E65,FIND(" ",E65)+1,LEN(E65)),FIND("-",MID(E65,FIND(" ",E65)+1,LEN(E65)))+1),LEN(MID(E65,FIND(" ",E65)+1,LEN(E65)))+1)-FIND("-",MID(E65,FIND(" ",E65)+1,LEN(E65)))-1),"") -> 潍坊银行0950 | L65: =IFERROR(MID(MID(E65,FIND(" ",E65)+1,LEN(E65)),FIND("-",MID(E65,FIND(" ",E65)+1,LEN(E65)),FIND("-",MID(E65,FIND(" ",E65)+1,LEN(E65)))+1)+1,LEN(E65)),"") | M65: =IFERROR(IF(H65="1002",1002,VLOOKUP(I65,亿企科目!A:H,6,0)),VLOOKUP(H65,亿企科目!A:G,6,0)) -> 1002 | N65: =IFERROR(IF(H65="1002","银行账户",IF(H65="1123","供应商",VLOOKUP(I65,亿企科目!A:H,8,0))),"") -> 银行账户 | O65: =IF(N65=0,IF(M65="1002",K65,""),_xlfn.TEXTAFTER(E65,"-",-1)) -> 潍坊银行0950 | P65: =VLOOKUP(A65,账簿!B:C,2,0) -> 030006 | Q65: =VLOOKUP(P65,账簿!A:B,2,0) -> 昌邑市昌荣农业科技有限责任公司 | W65: =X65&AB65&AD65 -> 0300062026-04-216 | X65: =P65 -> 030006 | Y65: =X65 -> 030006 | Z65: =Q65 -> 昌邑市昌荣农业科技有限责任公司 | AA65: =LEFT(B65,7) -> 2026-04 | AB65: =B65 -> 2026-04-21 | AC65: 记 | AD65: =VALUE(_xlfn.TEXTAFTER(C65,"-")) -> 6 | AE65: =D65 -> 贷款还款,昌邑市昌荣农业科技有限责任公司 | AF65: 谭雅心 | AG65: 谭雅心 | AN65: =M65 -> 1002 | AP65: =D65 -> 贷款还款,昌邑市昌荣农业科技有限责任公司 | AQ65: CNY | AR65: =F65 | AS65: =G65 -> 476537.42 | AT65: 01 | AU65: * | AV65: 1 | AW65: =AR65 | AX65: =AS65 -> 476537.42 | BQ65: =IF(N65="项目",VLOOKUP(O65,项目!B:C,2,0),IF(K65="空项目",VLOOKUP(K65,项目!B:C,2,0),"")) | BR65: =IFERROR(VLOOKUP(BQ65,项目!A:B,2,0),"") | BU65: =IF(N65="供应商",VLOOKUP(O65,供应商!B:C,2,0),"") | BV65: =IFERROR(VLOOKUP(BU65,供应商!A:B,2,0),"") | BW65: =IF(N65="客户",VLOOKUP(O65,客户!B:C,2,0),"") | BX65: =IFERROR(VLOOKUP(BW65,客户!A:B,2,0),"") | CU65: =IF(N65="费用项目",VLOOKUP(O65,费用项目!B:C,2,0),"") | CV65: =IFERROR(VLOOKUP(CU65,费用项目!A:B,2,0),"") | CW65: =IF(N65="银行账户",VLOOKUP(O65,银行变二级!B:C,2,0),"") -> 潍坊银行0950 | CX65: =IFERROR(VLOOKUP(O65,银行变二级!A:B,2,0),"") -> 潍坊银行0950
A66: 昌邑市昌荣农业科技有限责任公司 | B66: 2026-04-21 | C66: 记-007 | D66: 汇款,昌邑市国有资产经营投资有限公司 | E66: 100202 银行存款-潍坊银行0950 | F66: 490000 | H66: =LEFT(E66,4) -> 1002 | I66: =IFERROR(LEFT(E66,FIND(" ",E66)-1),E66) -> 100202 | J66: =LEFT(MID(E66,FIND(" ",E66)+1,LEN(E66)),FIND("-",MID(E66,FIND(" ",E66)+1,LEN(E66))&"-")-1) -> 银行存款 | K66: =IFERROR(MID(MID(E66,FIND(" ",E66)+1,LEN(E66)),FIND("-",MID(E66,FIND(" ",E66)+1,LEN(E66)))+1,IFERROR(FIND("-",MID(E66,FIND(" ",E66)+1,LEN(E66)),FIND("-",MID(E66,FIND(" ",E66)+1,LEN(E66)))+1),LEN(MID(E66,FIND(" ",E66)+1,LEN(E66)))+1)-FIND("-",MID(E66,FIND(" ",E66)+1,LEN(E66)))-1),"") -> 潍坊银行0950 | L66: =IFERROR(MID(MID(E66,FIND(" ",E66)+1,LEN(E66)),FIND("-",MID(E66,FIND(" ",E66)+1,LEN(E66)),FIND("-",MID(E66,FIND(" ",E66)+1,LEN(E66)))+1)+1,LEN(E66)),"") | M66: =IFERROR(IF(H66="1002",1002,VLOOKUP(I66,亿企科目!A:H,6,0)),VLOOKUP(H66,亿企科目!A:G,6,0)) -> 1002 | N66: =IFERROR(IF(H66="1002","银行账户",IF(H66="1123","供应商",VLOOKUP(I66,亿企科目!A:H,8,0))),"") -> 银行账户 | O66: =IF(N66=0,IF(M66="1002",K66,""),_xlfn.TEXTAFTER(E66,"-",-1)) -> 潍坊银行0950 | P66: =VLOOKUP(A66,账簿!B:C,2,0) -> 030006 | Q66: =VLOOKUP(P66,账簿!A:B,2,0) -> 昌邑市昌荣农业科技有限责任公司 | W66: =X66&AB66&AD66 -> 0300062026-04-217 | X66: =P66 -> 030006 | Y66: =X66 -> 030006 | Z66: =Q66 -> 昌邑市昌荣农业科技有限责任公司 | AA66: =LEFT(B66,7) -> 2026-04 | AB66: =B66 -> 2026-04-21 | AC66: 记 | AD66: =VALUE(_xlfn.TEXTAFTER(C66,"-")) -> 7 | AE66: =D66 -> 汇款,昌邑市国有资产经营投资有限公司 | AF66: 谭雅心 | AG66: 谭雅心 | AN66: =M66 -> 1002 | AP66: =D66 -> 汇款,昌邑市国有资产经营投资有限公司 | AQ66: CNY | AR66: =F66 -> 490000 | AS66: =G66 | AT66: 01 | AU66: * | AV66: 1 | AW66: =AR66 -> 490000 | AX66: =AS66 | BQ66: =IF(N66="项目",VLOOKUP(O66,项目!B:C,2,0),IF(K66="空项目",VLOOKUP(K66,项目!B:C,2,0),"")) | BR66: =IFERROR(VLOOKUP(BQ66,项目!A:B,2,0),"") | BU66: =IF(N66="供应商",VLOOKUP(O66,供应商!B:C,2,0),"") | BV66: =IFERROR(VLOOKUP(BU66,供应商!A:B,2,0),"") | BW66: =IF(N66="客户",VLOOKUP(O66,客户!B:C,2,0),"") | BX66: =IFERROR(VLOOKUP(BW66,客户!A:B,2,0),"") | CU66: =IF(N66="费用项目",VLOOKUP(O66,费用项目!B:C,2,0),"") | CV66: =IFERROR(VLOOKUP(CU66,费用项目!A:B,2,0),"") | CW66: =IF(N66="银行账户",VLOOKUP(O66,银行变二级!B:C,2,0),"") -> 潍坊银行0950 | CX66: =IFERROR(VLOOKUP(O66,银行变二级!A:B,2,0),"") -> 潍坊银行0950
A67: 昌邑市昌荣农业科技有限责任公司 | B67: 2026-04-21 | C67: 记-007 | D67: 汇款,昌邑市国有资产经营投资有限公司 | E67: 122108 其他应收款-单位-昌邑市国有资产经营投资有限公司 | G67: 490000 | H67: =LEFT(E67,4) -> 1221 | I67: =IFERROR(LEFT(E67,FIND(" ",E67)-1),E67) -> 122108 | J67: =LEFT(MID(E67,FIND(" ",E67)+1,LEN(E67)),FIND("-",MID(E67,FIND(" ",E67)+1,LEN(E67))&"-")-1) -> 其他应收款 | K67: =IFERROR(MID(MID(E67,FIND(" ",E67)+1,LEN(E67)),FIND("-",MID(E67,FIND(" ",E67)+1,LEN(E67)))+1,IFERROR(FIND("-",MID(E67,FIND(" ",E67)+1,LEN(E67)),FIND("-",MID(E67,FIND(" ",E67)+1,LEN(E67)))+1),LEN(MID(E67,FIND(" ",E67)+1,LEN(E67)))+1)-FIND("-",MID(E67,FIND(" ",E67)+1,LEN(E67)))-1),"") -> 单位 | L67: =IFERROR(MID(MID(E67,FIND(" ",E67)+1,LEN(E67)),FIND("-",MID(E67,FIND(" ",E67)+1,LEN(E67)),FIND("-",MID(E67,FIND(" ",E67)+1,LEN(E67)))+1)+1,LEN(E67)),"") -> 昌邑市国有资产经营投资有限公司 | M67: =IFERROR(IF(H67="1002",1002,VLOOKUP(I67,亿企科目!A:H,6,0)),VLOOKUP(H67,亿企科目!A:G,6,0)) -> 122102 | N67: =IFERROR(IF(H67="1002","银行账户",IF(H67="1123","供应商",VLOOKUP(I67,亿企科目!A:H,8,0))),"") -> 客户 | O67: =IF(N67=0,IF(M67="1002",K67,""),_xlfn.TEXTAFTER(E67,"-",-1)) -> 昌邑市国有资产经营投资有限公司 | P67: =VLOOKUP(A67,账簿!B:C,2,0) -> 030006 | Q67: =VLOOKUP(P67,账簿!A:B,2,0) -> 昌邑市昌荣农业科技有限责任公司 | W67: =X67&AB67&AD67 -> 0300062026-04-217 | X67: =P67 -> 030006 | Y67: =X67 -> 030006 | Z67: =Q67 -> 昌邑市昌荣农业科技有限责任公司 | AA67: =LEFT(B67,7) -> 2026-04 | AB67: =B67 -> 2026-04-21 | AC67: 记 | AD67: =VALUE(_xlfn.TEXTAFTER(C67,"-")) -> 7 | AE67: =D67 -> 汇款,昌邑市国有资产经营投资有限公司 | AF67: 谭雅心 | AG67: 谭雅心 | AN67: =M67 -> 122102 | AP67: =D67 -> 汇款,昌邑市国有资产经营投资有限公司 | AQ67: CNY | AR67: =F67 | AS67: =G67 -> 490000 | AT67: 01 | AU67: * | AV67: 1 | AW67: =AR67 | AX67: =AS67 -> 490000 | BQ67: =IF(N67="项目",VLOOKUP(O67,项目!B:C,2,0),IF(K67="空项目",VLOOKUP(K67,项目!B:C,2,0),"")) | BR67: =IFERROR(VLOOKUP(BQ67,项目!A:B,2,0),"") | BU67: =IF(N67="供应商",VLOOKUP(O67,供应商!B:C,2,0),"") | BV67: =IFERROR(VLOOKUP(BU67,供应商!A:B,2,0),"") | BW67: =IF(N67="客户",VLOOKUP(O67,客户!B:C,2,0),"") -> 003 | BX67: =IFERROR(VLOOKUP(BW67,客户!A:B,2,0),"") -> 昌邑市国有资产经营投资有限公司 | CU67: =IF(N67="费用项目",VLOOKUP(O67,费用项目!B:C,2,0),"") | CV67: =IFERROR(VLOOKUP(CU67,费用项目!A:B,2,0),"") | CW67: =IF(N67="银行账户",VLOOKUP(O67,银行变二级!B:C,2,0),"") | CX67: =IFERROR(VLOOKUP(O67,银行变二级!A:B,2,0),"")
A68: 昌邑市昌荣农业科技有限责任公司 | B68: 2026-04-30 | C68: 记-008 | D68: 调整四方协议 | E68: 224102 其他应付款-单位-山东佳德贸易有限公司 | F68: 96000000 | H68: =LEFT(E68,4) -> 2241 | I68: =IFERROR(LEFT(E68,FIND(" ",E68)-1),E68) -> 224102 | J68: =LEFT(MID(E68,FIND(" ",E68)+1,LEN(E68)),FIND("-",MID(E68,FIND(" ",E68)+1,LEN(E68))&"-")-1) -> 其他应付款 | K68: =IFERROR(MID(MID(E68,FIND(" ",E68)+1,LEN(E68)),FIND("-",MID(E68,FIND(" ",E68)+1,LEN(E68)))+1,IFERROR(FIND("-",MID(E68,FIND(" ",E68)+1,LEN(E68)),FIND("-",MID(E68,FIND(" ",E68)+1,LEN(E68)))+1),LEN(MID(E68,FIND(" ",E68)+1,LEN(E68)))+1)-FIND("-",MID(E68,FIND(" ",E68)+1,LEN(E68)))-1),"") -> 单位 | L68: =IFERROR(MID(MID(E68,FIND(" ",E68)+1,LEN(E68)),FIND("-",MID(E68,FIND(" ",E68)+1,LEN(E68)),FIND("-",MID(E68,FIND(" ",E68)+1,LEN(E68)))+1)+1,LEN(E68)),"") -> 山东佳德贸易有限公司 | M68: =IFERROR(IF(H68="1002",1002,VLOOKUP(I68,亿企科目!A:H,6,0)),VLOOKUP(H68,亿企科目!A:G,6,0)) -> 224102 | N68: =IFERROR(IF(H68="1002","银行账户",IF(H68="1123","供应商",VLOOKUP(I68,亿企科目!A:H,8,0))),"") -> 供应商 | O68: =IF(N68=0,IF(M68="1002",K68,""),_xlfn.TEXTAFTER(E68,"-",-1)) -> 山东佳德贸易有限公司 | P68: =VLOOKUP(A68,账簿!B:C,2,0) -> 030006 | Q68: =VLOOKUP(P68,账簿!A:B,2,0) -> 昌邑市昌荣农业科技有限责任公司 | W68: =X68&AB68&AD68 -> 0300062026-04-308 | X68: =P68 -> 030006 | Y68: =X68 -> 030006 | Z68: =Q68 -> 昌邑市昌荣农业科技有限责任公司 | AA68: =LEFT(B68,7) -> 2026-04 | AB68: =B68 -> 2026-04-30 | AC68: 记 | AD68: =VALUE(_xlfn.TEXTAFTER(C68,"-")) -> 8 | AE68: =D68 -> 调整四方协议 | AF68: 谭雅心 | AG68: 谭雅心 | AN68: =M68 -> 224102 | AP68: =D68 -> 调整四方协议 | AQ68: CNY | AR68: =F68 -> 96000000 | AS68: =G68 | AT68: 01 | AU68: * | AV68: 1 | AW68: =AR68 -> 96000000 | AX68: =AS68 | BQ68: =IF(N68="项目",VLOOKUP(O68,项目!B:C,2,0),IF(K68="空项目",VLOOKUP(K68,项目!B:C,2,0),"")) | BR68: =IFERROR(VLOOKUP(BQ68,项目!A:B,2,0),"") | BU68: =IF(N68="供应商",VLOOKUP(O68,供应商!B:C,2,0),"") -> 0015321 | BV68: =IFERROR(VLOOKUP(BU68,供应商!A:B,2,0),"") -> 山东佳德贸易有限公司 | BW68: =IF(N68="客户",VLOOKUP(O68,客户!B:C,2,0),"") | BX68: =IFERROR(VLOOKUP(BW68,客户!A:B,2,0),"") | CU68: =IF(N68="费用项目",VLOOKUP(O68,费用项目!B:C,2,0),"") | CV68: =IFERROR(VLOOKUP(CU68,费用项目!A:B,2,0),"") | CW68: =IF(N68="银行账户",VLOOKUP(O68,银行变二级!B:C,2,0),"") | CX68: =IFERROR(VLOOKUP(O68,银行变二级!A:B,2,0),"")
A69: 昌邑市昌荣农业科技有限责任公司 | B69: 2026-04-30 | C69: 记-008 | D69: 调整四方协议 | E69: 122108 其他应收款-单位-昌邑市昌盛管网建设投资有限公司 | G69: 96000000 | H69: =LEFT(E69,4) -> 1221 | I69: =IFERROR(LEFT(E69,FIND(" ",E69)-1),E69) -> 122108 | J69: =LEFT(MID(E69,FIND(" ",E69)+1,LEN(E69)),FIND("-",MID(E69,FIND(" ",E69)+1,LEN(E69))&"-")-1) -> 其他应收款 | K69: =IFERROR(MID(MID(E69,FIND(" ",E69)+1,LEN(E69)),FIND("-",MID(E69,FIND(" ",E69)+1,LEN(E69)))+1,IFERROR(FIND("-",MID(E69,FIND(" ",E69)+1,LEN(E69)),FIND("-",MID(E69,FIND(" ",E69)+1,LEN(E69)))+1),LEN(MID(E69,FIND(" ",E69)+1,LEN(E69)))+1)-FIND("-",MID(E69,FIND(" ",E69)+1,LEN(E69)))-1),"") -> 单位 | L69: =IFERROR(MID(MID(E69,FIND(" ",E69)+1,LEN(E69)),FIND("-",MID(E69,FIND(" ",E69)+1,LEN(E69)),FIND("-",MID(E69,FIND(" ",E69)+1,LEN(E69)))+1)+1,LEN(E69)),"") -> 昌邑市昌盛管网建设投资有限公司 | M69: =IFERROR(IF(H69="1002",1002,VLOOKUP(I69,亿企科目!A:H,6,0)),VLOOKUP(H69,亿企科目!A:G,6,0)) -> 122102 | N69: =IFERROR(IF(H69="1002","银行账户",IF(H69="1123","供应商",VLOOKUP(I69,亿企科目!A:H,8,0))),"") -> 客户 | O69: =IF(N69=0,IF(M69="1002",K69,""),_xlfn.TEXTAFTER(E69,"-",-1)) -> 昌邑市昌盛管网建设投资有限公司 | P69: =VLOOKUP(A69,账簿!B:C,2,0) -> 030006 | Q69: =VLOOKUP(P69,账簿!A:B,2,0) -> 昌邑市昌荣农业科技有限责任公司 | W69: =X69&AB69&AD69 -> 0300062026-04-308 | X69: =P69 -> 030006 | Y69: =X69 -> 030006 | Z69: =Q69 -> 昌邑市昌荣农业科技有限责任公司 | AA69: =LEFT(B69,7) -> 2026-04 | AB69: =B69 -> 2026-04-30 | AC69: 记 | AD69: =VALUE(_xlfn.TEXTAFTER(C69,"-")) -> 8 | AE69: =D69 -> 调整四方协议 | AF69: 谭雅心 | AG69: 谭雅心 | AN69: =M69 -> 122102 | AP69: =D69 -> 调整四方协议 | AQ69: CNY | AR69: =F69 | AS69: =G69 -> 96000000 | AT69: 01 | AU69: * | AV69: 1 | AW69: =AR69 | AX69: =AS69 -> 96000000 | BQ69: =IF(N69="项目",VLOOKUP(O69,项目!B:C,2,0),IF(K69="空项目",VLOOKUP(K69,项目!B:C,2,0),"")) | BR69: =IFERROR(VLOOKUP(BQ69,项目!A:B,2,0),"") | BU69: =IF(N69="供应商",VLOOKUP(O69,供应商!B:C,2,0),"") | BV69: =IFERROR(VLOOKUP(BU69,供应商!A:B,2,0),"") | BW69: =IF(N69="客户",VLOOKUP(O69,客户!B:C,2,0),"") -> 001001001 | BX69: =IFERROR(VLOOKUP(BW69,客户!A:B,2,0),"") -> 昌邑市昌盛管网建设投资有限公司 | CU69: =IF(N69="费用项目",VLOOKUP(O69,费用项目!B:C,2,0),"") | CV69: =IFERROR(VLOOKUP(CU69,费用项目!A:B,2,0),"") | CW69: =IF(N69="银行账户",VLOOKUP(O69,银行变二级!B:C,2,0),"") | CX69: =IFERROR(VLOOKUP(O69,银行变二级!A:B,2,0),"")
A70: 昌邑市昌荣农业科技有限责任公司 | B70: 2026-04-30 | C70: 记-009 | D70: 调整四方协议 | E70: 224102 其他应付款-单位-山东盛汇经贸有限公司 | F70: 93000000 | H70: =LEFT(E70,4) -> 2241 | I70: =IFERROR(LEFT(E70,FIND(" ",E70)-1),E70) -> 224102 | J70: =LEFT(MID(E70,FIND(" ",E70)+1,LEN(E70)),FIND("-",MID(E70,FIND(" ",E70)+1,LEN(E70))&"-")-1) -> 其他应付款 | K70: =IFERROR(MID(MID(E70,FIND(" ",E70)+1,LEN(E70)),FIND("-",MID(E70,FIND(" ",E70)+1,LEN(E70)))+1,IFERROR(FIND("-",MID(E70,FIND(" ",E70)+1,LEN(E70)),FIND("-",MID(E70,FIND(" ",E70)+1,LEN(E70)))+1),LEN(MID(E70,FIND(" ",E70)+1,LEN(E70)))+1)-FIND("-",MID(E70,FIND(" ",E70)+1,LEN(E70)))-1),"") -> 单位 | L70: =IFERROR(MID(MID(E70,FIND(" ",E70)+1,LEN(E70)),FIND("-",MID(E70,FIND(" ",E70)+1,LEN(E70)),FIND("-",MID(E70,FIND(" ",E70)+1,LEN(E70)))+1)+1,LEN(E70)),"") -> 山东盛汇经贸有限公司 | M70: =IFERROR(IF(H70="1002",1002,VLOOKUP(I70,亿企科目!A:H,6,0)),VLOOKUP(H70,亿企科目!A:G,6,0)) -> 224102 | N70: =IFERROR(IF(H70="1002","银行账户",IF(H70="1123","供应商",VLOOKUP(I70,亿企科目!A:H,8,0))),"") -> 供应商 | O70: =IF(N70=0,IF(M70="1002",K70,""),_xlfn.TEXTAFTER(E70,"-",-1)) -> 山东盛汇经贸有限公司 | P70: =VLOOKUP(A70,账簿!B:C,2,0) -> 030006 | Q70: =VLOOKUP(P70,账簿!A:B,2,0) -> 昌邑市昌荣农业科技有限责任公司 | W70: =X70&AB70&AD70 -> 0300062026-04-309 | X70: =P70 -> 030006 | Y70: =X70 -> 030006 | Z70: =Q70 -> 昌邑市昌荣农业科技有限责任公司 | AA70: =LEFT(B70,7) -> 2026-04 | AB70: =B70 -> 2026-04-30 | AC70: 记 | AD70: =VALUE(_xlfn.TEXTAFTER(C70,"-")) -> 9 | AE70: =D70 -> 调整四方协议 | AF70: 谭雅心 | AG70: 谭雅心 | AN70: =M70 -> 224102 | AP70: =D70 -> 调整四方协议 | AQ70: CNY | AR70: =F70 -> 93000000 | AS70: =G70 | AT70: 01 | AU70: * | AV70: 1 | AW70: =AR70 -> 93000000 | AX70: =AS70 | BQ70: =IF(N70="项目",VLOOKUP(O70,项目!B:C,2,0),IF(K70="空项目",VLOOKUP(K70,项目!B:C,2,0),"")) | BR70: =IFERROR(VLOOKUP(BQ70,项目!A:B,2,0),"") | BU70: =IF(N70="供应商",VLOOKUP(O70,供应商!B:C,2,0),"") -> 001001007 | BV70: =IFERROR(VLOOKUP(BU70,供应商!A:B,2,0),"") -> 山东盛汇经贸有限公司 | BW70: =IF(N70="客户",VLOOKUP(O70,客户!B:C,2,0),"") | BX70: =IFERROR(VLOOKUP(BW70,客户!A:B,2,0),"") | CU70: =IF(N70="费用项目",VLOOKUP(O70,费用项目!B:C,2,0),"") | CV70: =IFERROR(VLOOKUP(CU70,费用项目!A:B,2,0),"") | CW70: =IF(N70="银行账户",VLOOKUP(O70,银行变二级!B:C,2,0),"") | CX70: =IFERROR(VLOOKUP(O70,银行变二级!A:B,2,0),"")
A71: 昌邑市昌荣农业科技有限责任公司 | B71: 2026-04-30 | C71: 记-009 | D71: 调整四方协议 | E71: 122108 其他应收款-单位-昌邑市城投生态环保有限公司 | G71: 93000000 | H71: =LEFT(E71,4) -> 1221 | I71: =IFERROR(LEFT(E71,FIND(" ",E71)-1),E71) -> 122108 | J71: =LEFT(MID(E71,FIND(" ",E71)+1,LEN(E71)),FIND("-",MID(E71,FIND(" ",E71)+1,LEN(E71))&"-")-1) -> 其他应收款 | K71: =IFERROR(MID(MID(E71,FIND(" ",E71)+1,LEN(E71)),FIND("-",MID(E71,FIND(" ",E71)+1,LEN(E71)))+1,IFERROR(FIND("-",MID(E71,FIND(" ",E71)+1,LEN(E71)),FIND("-",MID(E71,FIND(" ",E71)+1,LEN(E71)))+1),LEN(MID(E71,FIND(" ",E71)+1,LEN(E71)))+1)-FIND("-",MID(E71,FIND(" ",E71)+1,LEN(E71)))-1),"") -> 单位 | L71: =IFERROR(MID(MID(E71,FIND(" ",E71)+1,LEN(E71)),FIND("-",MID(E71,FIND(" ",E71)+1,LEN(E71)),FIND("-",MID(E71,FIND(" ",E71)+1,LEN(E71)))+1)+1,LEN(E71)),"") -> 昌邑市城投生态环保有限公司 | M71: =IFERROR(IF(H71="1002",1002,VLOOKUP(I71,亿企科目!A:H,6,0)),VLOOKUP(H71,亿企科目!A:G,6,0)) -> 122102 | N71: =IFERROR(IF(H71="1002","银行账户",IF(H71="1123","供应商",VLOOKUP(I71,亿企科目!A:H,8,0))),"") -> 客户 | O71: =IF(N71=0,IF(M71="1002",K71,""),_xlfn.TEXTAFTER(E71,"-",-1)) -> 昌邑市城投生态环保有限公司 | P71: =VLOOKUP(A71,账簿!B:C,2,0) -> 030006 | Q71: =VLOOKUP(P71,账簿!A:B,2,0) -> 昌邑市昌荣农业科技有限责任公司 | W71: =X71&AB71&AD71 -> 0300062026-04-309 | X71: =P71 -> 030006 | Y71: =X71 -> 030006 | Z71: =Q71 -> 昌邑市昌荣农业科技有限责任公司 | AA71: =LEFT(B71,7) -> 2026-04 | AB71: =B71 -> 2026-04-30 | AC71: 记 | AD71: =VALUE(_xlfn.TEXTAFTER(C71,"-")) -> 9 | AE71: =D71 -> 调整四方协议 | AF71: 谭雅心 | AG71: 谭雅心 | AN71: =M71 -> 122102 | AP71: =D71 -> 调整四方协议 | AQ71: CNY | AR71: =F71 | AS71: =G71 -> 93000000 | AT71: 01 | AU71: * | AV71: 1 | AW71: =AR71 | AX71: =AS71 -> 93000000 | BQ71: =IF(N71="项目",VLOOKUP(O71,项目!B:C,2,0),IF(K71="空项目",VLOOKUP(K71,项目!B:C,2,0),"")) | BR71: =IFERROR(VLOOKUP(BQ71,项目!A:B,2,0),"") | BU71: =IF(N71="供应商",VLOOKUP(O71,供应商!B:C,2,0),"") | BV71: =IFERROR(VLOOKUP(BU71,供应商!A:B,2,0),"") | BW71: =IF(N71="客户",VLOOKUP(O71,客户!B:C,2,0),"") -> 002003 | BX71: =IFERROR(VLOOKUP(BW71,客户!A:B,2,0),"") -> 昌邑市城投生态环保有限公司 | CU71: =IF(N71="费用项目",VLOOKUP(O71,费用项目!B:C,2,0),"") | CV71: =IFERROR(VLOOKUP(CU71,费用项目!A:B,2,0),"") | CW71: =IF(N71="银行账户",VLOOKUP(O71,银行变二级!B:C,2,0),"") | CX71: =IFERROR(VLOOKUP(O71,银行变二级!A:B,2,0),"")
A72: 昌邑市昌荣农业科技有限责任公司 | B72: 2026-04-30 | C72: 记-010 | D72: 调整四方协议 | E72: 224102 其他应付款-单位-昌邑市盛汇农业科技有限公司 | F72: 9500000 | H72: =LEFT(E72,4) -> 2241 | I72: =IFERROR(LEFT(E72,FIND(" ",E72)-1),E72) -> 224102 | J72: =LEFT(MID(E72,FIND(" ",E72)+1,LEN(E72)),FIND("-",MID(E72,FIND(" ",E72)+1,LEN(E72))&"-")-1) -> 其他应付款 | K72: =IFERROR(MID(MID(E72,FIND(" ",E72)+1,LEN(E72)),FIND("-",MID(E72,FIND(" ",E72)+1,LEN(E72)))+1,IFERROR(FIND("-",MID(E72,FIND(" ",E72)+1,LEN(E72)),FIND("-",MID(E72,FIND(" ",E72)+1,LEN(E72)))+1),LEN(MID(E72,FIND(" ",E72)+1,LEN(E72)))+1)-FIND("-",MID(E72,FIND(" ",E72)+1,LEN(E72)))-1),"") -> 单位 | L72: =IFERROR(MID(MID(E72,FIND(" ",E72)+1,LEN(E72)),FIND("-",MID(E72,FIND(" ",E72)+1,LEN(E72)),FIND("-",MID(E72,FIND(" ",E72)+1,LEN(E72)))+1)+1,LEN(E72)),"") -> 昌邑市盛汇农业科技有限公司 | M72: =IFERROR(IF(H72="1002",1002,VLOOKUP(I72,亿企科目!A:H,6,0)),VLOOKUP(H72,亿企科目!A:G,6,0)) -> 224102 | N72: =IFERROR(IF(H72="1002","银行账户",IF(H72="1123","供应商",VLOOKUP(I72,亿企科目!A:H,8,0))),"") -> 供应商 | O72: =IF(N72=0,IF(M72="1002",K72,""),_xlfn.TEXTAFTER(E72,"-",-1)) -> 昌邑市盛汇农业科技有限公司 | P72: =VLOOKUP(A72,账簿!B:C,2,0) -> 030006 | Q72: =VLOOKUP(P72,账簿!A:B,2,0) -> 昌邑市昌荣农业科技有限责任公司 | W72: =X72&AB72&AD72 -> 0300062026-04-3010 | X72: =P72 -> 030006 | Y72: =X72 -> 030006 | Z72: =Q72 -> 昌邑市昌荣农业科技有限责任公司 | AA72: =LEFT(B72,7) -> 2026-04 | AB72: =B72 -> 2026-04-30 | AC72: 记 | AD72: =VALUE(_xlfn.TEXTAFTER(C72,"-")) -> 10 | AE72: =D72 -> 调整四方协议 | AF72: 谭雅心 | AG72: 谭雅心 | AN72: =M72 -> 224102 | AP72: =D72 -> 调整四方协议 | AQ72: CNY | AR72: =F72 -> 9500000 | AS72: =G72 | AT72: 01 | AU72: * | AV72: 1 | AW72: =AR72 -> 9500000 | AX72: =AS72 | BQ72: =IF(N72="项目",VLOOKUP(O72,项目!B:C,2,0),IF(K72="空项目",VLOOKUP(K72,项目!B:C,2,0),"")) | BR72: =IFERROR(VLOOKUP(BQ72,项目!A:B,2,0),"") | BU72: =IF(N72="供应商",VLOOKUP(O72,供应商!B:C,2,0),"") -> 003017 | BV72: =IFERROR(VLOOKUP(BU72,供应商!A:B,2,0),"") -> 昌邑市盛汇农业科技有限公司 | BW72: =IF(N72="客户",VLOOKUP(O72,客户!B:C,2,0),"") | BX72: =IFERROR(VLOOKUP(BW72,客户!A:B,2,0),"") | CU72: =IF(N72="费用项目",VLOOKUP(O72,费用项目!B:C,2,0),"") | CV72: =IFERROR(VLOOKUP(CU72,费用项目!A:B,2,0),"") | CW72: =IF(N72="银行账户",VLOOKUP(O72,银行变二级!B:C,2,0),"") | CX72: =IFERROR(VLOOKUP(O72,银行变二级!A:B,2,0),"")
A73: 昌邑市昌荣农业科技有限责任公司 | B73: 2026-04-30 | C73: 记-010 | D73: 调整四方协议 | E73: 122108 其他应收款-单位-昌邑市惠合智能产业园投资有限公司 | G73: 9500000 | H73: =LEFT(E73,4) -> 1221 | I73: =IFERROR(LEFT(E73,FIND(" ",E73)-1),E73) -> 122108 | J73: =LEFT(MID(E73,FIND(" ",E73)+1,LEN(E73)),FIND("-",MID(E73,FIND(" ",E73)+1,LEN(E73))&"-")-1) -> 其他应收款 | K73: =IFERROR(MID(MID(E73,FIND(" ",E73)+1,LEN(E73)),FIND("-",MID(E73,FIND(" ",E73)+1,LEN(E73)))+1,IFERROR(FIND("-",MID(E73,FIND(" ",E73)+1,LEN(E73)),FIND("-",MID(E73,FIND(" ",E73)+1,LEN(E73)))+1),LEN(MID(E73,FIND(" ",E73)+1,LEN(E73)))+1)-FIND("-",MID(E73,FIND(" ",E73)+1,LEN(E73)))-1),"") -> 单位 | L73: =IFERROR(MID(MID(E73,FIND(" ",E73)+1,LEN(E73)),FIND("-",MID(E73,FIND(" ",E73)+1,LEN(E73)),FIND("-",MID(E73,FIND(" ",E73)+1,LEN(E73)))+1)+1,LEN(E73)),"") -> 昌邑市惠合智能产业园投资有限公司 | M73: =IFERROR(IF(H73="1002",1002,VLOOKUP(I73,亿企科目!A:H,6,0)),VLOOKUP(H73,亿企科目!A:G,6,0)) -> 122102 | N73: =IFERROR(IF(H73="1002","银行账户",IF(H73="1123","供应商",VLOOKUP(I73,亿企科目!A:H,8,0))),"") -> 客户 | O73: =IF(N73=0,IF(M73="1002",K73,""),_xlfn.TEXTAFTER(E73,"-",-1)) -> 昌邑市惠合智能产业园投资有限公司 | P73: =VLOOKUP(A73,账簿!B:C,2,0) -> 030006 | Q73: =VLOOKUP(P73,账簿!A:B,2,0) -> 昌邑市昌荣农业科技有限责任公司 | W73: =X73&AB73&AD73 -> 0300062026-04-3010 | X73: =P73 -> 030006 | Y73: =X73 -> 030006 | Z73: =Q73 -> 昌邑市昌荣农业科技有限责任公司 | AA73: =LEFT(B73,7) -> 2026-04 | AB73: =B73 -> 2026-04-30 | AC73: 记 | AD73: =VALUE(_xlfn.TEXTAFTER(C73,"-")) -> 10 | AE73: =D73 -> 调整四方协议 | AF73: 谭雅心 | AG73: 谭雅心 | AN73: =M73 -> 122102 | AP73: =D73 -> 调整四方协议 | AQ73: CNY | AR73: =F73 | AS73: =G73 -> 9500000 | AT73: 01 | AU73: * | AV73: 1 | AW73: =AR73 | AX73: =AS73 -> 9500000 | BQ73: =IF(N73="项目",VLOOKUP(O73,项目!B:C,2,0),IF(K73="空项目",VLOOKUP(K73,项目!B:C,2,0),"")) | BR73: =IFERROR(VLOOKUP(BQ73,项目!A:B,2,0),"") | BU73: =IF(N73="供应商",VLOOKUP(O73,供应商!B:C,2,0),"") | BV73: =IFERROR(VLOOKUP(BU73,供应商!A:B,2,0),"") | BW73: =IF(N73="客户",VLOOKUP(O73,客户!B:C,2,0),"") -> 001001004 | BX73: =IFERROR(VLOOKUP(BW73,客户!A:B,2,0),"") -> 昌邑市惠合智能产业园投资有限公司 | CU73: =IF(N73="费用项目",VLOOKUP(O73,费用项目!B:C,2,0),"") | CV73: =IFERROR(VLOOKUP(CU73,费用项目!A:B,2,0),"") | CW73: =IF(N73="银行账户",VLOOKUP(O73,银行变二级!B:C,2,0),"") | CX73: =IFERROR(VLOOKUP(O73,银行变二级!A:B,2,0),"")
A74: 昌邑市昌荣农业科技有限责任公司 | B74: 2026-04-30 | C74: 记-011 | D74: 结转本月损益 | E74: 4103 本年利润 | F74: 476606.92 | H74: =LEFT(E74,4) -> 4103 | I74: =IFERROR(LEFT(E74,FIND(" ",E74)-1),E74) -> 4103 | J74: =LEFT(MID(E74,FIND(" ",E74)+1,LEN(E74)),FIND("-",MID(E74,FIND(" ",E74)+1,LEN(E74))&"-")-1) -> 本年利润 | K74: =IFERROR(MID(MID(E74,FIND(" ",E74)+1,LEN(E74)),FIND("-",MID(E74,FIND(" ",E74)+1,LEN(E74)))+1,IFERROR(FIND("-",MID(E74,FIND(" ",E74)+1,LEN(E74)),FIND("-",MID(E74,FIND(" ",E74)+1,LEN(E74)))+1),LEN(MID(E74,FIND(" ",E74)+1,LEN(E74)))+1)-FIND("-",MID(E74,FIND(" ",E74)+1,LEN(E74)))-1),"") | L74: =IFERROR(MID(MID(E74,FIND(" ",E74)+1,LEN(E74)),FIND("-",MID(E74,FIND(" ",E74)+1,LEN(E74)),FIND("-",MID(E74,FIND(" ",E74)+1,LEN(E74)))+1)+1,LEN(E74)),"") | M74: =IFERROR(IF(H74="1002",1002,VLOOKUP(I74,亿企科目!A:H,6,0)),VLOOKUP(H74,亿企科目!A:G,6,0)) -> 4103 | N74: =IFERROR(IF(H74="1002","银行账户",IF(H74="1123","供应商",VLOOKUP(I74,亿企科目!A:H,8,0))),"") -> 0 | O74: =IF(N74=0,IF(M74="1002",K74,""),_xlfn.TEXTAFTER(E74,"-",-1)) | P74: =VLOOKUP(A74,账簿!B:C,2,0) -> 030006 | Q74: =VLOOKUP(P74,账簿!A:B,2,0) -> 昌邑市昌荣农业科技有限责任公司 | W74: =X74&AB74&AD74 -> 0300062026-04-3011 | X74: =P74 -> 030006 | Y74: =X74 -> 030006 | Z74: =Q74 -> 昌邑市昌荣农业科技有限责任公司 | AA74: =LEFT(B74,7) -> 2026-04 | AB74: =B74 -> 2026-04-30 | AC74: 记 | AD74: =VALUE(_xlfn.TEXTAFTER(C74,"-")) -> 11 | AE74: =D74 -> 结转本月损益 | AF74: 谭雅心 | AG74: 谭雅心 | AN74: =M74 -> 4103 | AP74: =D74 -> 结转本月损益 | AQ74: CNY | AR74: =F74 -> 476606.92 | AS74: =G74 | AT74: 01 | AU74: * | AV74: 1 | AW74: =AR74 -> 476606.92 | AX74: =AS74 | BQ74: =IF(N74="项目",VLOOKUP(O74,项目!B:C,2,0),IF(K74="空项目",VLOOKUP(K74,项目!B:C,2,0),"")) | BR74: =IFERROR(VLOOKUP(BQ74,项目!A:B,2,0),"") | BU74: =IF(N74="供应商",VLOOKUP(O74,供应商!B:C,2,0),"") | BV74: =IFERROR(VLOOKUP(BU74,供应商!A:B,2,0),"") | BW74: =IF(N74="客户",VLOOKUP(O74,客户!B:C,2,0),"") | BX74: =IFERROR(VLOOKUP(BW74,客户!A:B,2,0),"") | CU74: =IF(N74="费用项目",VLOOKUP(O74,费用项目!B:C,2,0),"") | CV74: =IFERROR(VLOOKUP(CU74,费用项目!A:B,2,0),"") | CW74: =IF(N74="银行账户",VLOOKUP(O74,银行变二级!B:C,2,0),"") | CX74: =IFERROR(VLOOKUP(O74,银行变二级!A:B,2,0),"")
A75: 昌邑市昌荣农业科技有限责任公司 | B75: 2026-04-30 | C75: 记-011 | D75: 结转本月损益 | E75: 6603 财务费用-利息支出 | G75: 476537.42 | H75: =LEFT(E75,4) -> 6603 | I75: =IFERROR(LEFT(E75,FIND(" ",E75)-1),E75) -> 6603 | J75: =LEFT(MID(E75,FIND(" ",E75)+1,LEN(E75)),FIND("-",MID(E75,FIND(" ",E75)+1,LEN(E75))&"-")-1) -> 财务费用 | K75: =IFERROR(MID(MID(E75,FIND(" ",E75)+1,LEN(E75)),FIND("-",MID(E75,FIND(" ",E75)+1,LEN(E75)))+1,IFERROR(FIND("-",MID(E75,FIND(" ",E75)+1,LEN(E75)),FIND("-",MID(E75,FIND(" ",E75)+1,LEN(E75)))+1),LEN(MID(E75,FIND(" ",E75)+1,LEN(E75)))+1)-FIND("-",MID(E75,FIND(" ",E75)+1,LEN(E75)))-1),"") -> 利息支出 | L75: =IFERROR(MID(MID(E75,FIND(" ",E75)+1,LEN(E75)),FIND("-",MID(E75,FIND(" ",E75)+1,LEN(E75)),FIND("-",MID(E75,FIND(" ",E75)+1,LEN(E75)))+1)+1,LEN(E75)),"") | M75: =IFERROR(IF(H75="1002",1002,VLOOKUP(I75,亿企科目!A:H,6,0)),VLOOKUP(H75,亿企科目!A:G,6,0)) -> 6603 | N75: =IFERROR(IF(H75="1002","银行账户",IF(H75="1123","供应商",VLOOKUP(I75,亿企科目!A:H,8,0))),"") -> 费用项目 | O75: =IF(N75=0,IF(M75="1002",K75,""),_xlfn.TEXTAFTER(E75,"-",-1)) -> 利息支出 | P75: =VLOOKUP(A75,账簿!B:C,2,0) -> 030006 | Q75: =VLOOKUP(P75,账簿!A:B,2,0) -> 昌邑市昌荣农业科技有限责任公司 | W75: =X75&AB75&AD75 -> 0300062026-04-3011 | X75: =P75 -> 030006 | Y75: =X75 -> 030006 | Z75: =Q75 -> 昌邑市昌荣农业科技有限责任公司 | AA75: =LEFT(B75,7) -> 2026-04 | AB75: =B75 -> 2026-04-30 | AC75: 记 | AD75: =VALUE(_xlfn.TEXTAFTER(C75,"-")) -> 11 | AE75: =D75 -> 结转本月损益 | AF75: 谭雅心 | AG75: 谭雅心 | AN75: =M75 -> 6603 | AP75: =D75 -> 结转本月损益 | AQ75: CNY | AR75: =F75 | AS75: =G75 -> 476537.42 | AT75: 01 | AU75: * | AV75: 1 | AW75: =AR75 | AX75: =AS75 -> 476537.42 | BQ75: =IF(N75="项目",VLOOKUP(O75,项目!B:C,2,0),IF(K75="空项目",VLOOKUP(K75,项目!B:C,2,0),"")) | BR75: =IFERROR(VLOOKUP(BQ75,项目!A:B,2,0),"") | BU75: =IF(N75="供应商",VLOOKUP(O75,供应商!B:C,2,0),"") | BV75: =IFERROR(VLOOKUP(BU75,供应商!A:B,2,0),"") | BW75: =IF(N75="客户",VLOOKUP(O75,客户!B:C,2,0),"") | BX75: =IFERROR(VLOOKUP(BW75,客户!A:B,2,0),"") | CU75: =IF(N75="费用项目",VLOOKUP(O75,费用项目!B:C,2,0),"") -> 660302 | CV75: =IFERROR(VLOOKUP(CU75,费用项目!A:B,2,0),"") -> 利息支出 | CW75: =IF(N75="银行账户",VLOOKUP(O75,银行变二级!B:C,2,0),"") | CX75: =IFERROR(VLOOKUP(O75,银行变二级!A:B,2,0),"")
A76: 昌邑市昌荣农业科技有限责任公司 | B76: 2026-04-30 | C76: 记-011 | D76: 结转本月损益 | E76: 671101 营业外支出-税收滞纳金、罚金、罚款 | G76: 69.5 | H76: =LEFT(E76,4) -> 6711 | I76: =IFERROR(LEFT(E76,FIND(" ",E76)-1),E76) -> 671101 | J76: =LEFT(MID(E76,FIND(" ",E76)+1,LEN(E76)),FIND("-",MID(E76,FIND(" ",E76)+1,LEN(E76))&"-")-1) -> 营业外支出 | K76: =IFERROR(MID(MID(E76,FIND(" ",E76)+1,LEN(E76)),FIND("-",MID(E76,FIND(" ",E76)+1,LEN(E76)))+1,IFERROR(FIND("-",MID(E76,FIND(" ",E76)+1,LEN(E76)),FIND("-",MID(E76,FIND(" ",E76)+1,LEN(E76)))+1),LEN(MID(E76,FIND(" ",E76)+1,LEN(E76)))+1)-FIND("-",MID(E76,FIND(" ",E76)+1,LEN(E76)))-1),"") -> 税收滞纳金、罚金、罚款 | L76: =IFERROR(MID(MID(E76,FIND(" ",E76)+1,LEN(E76)),FIND("-",MID(E76,FIND(" ",E76)+1,LEN(E76)),FIND("-",MID(E76,FIND(" ",E76)+1,LEN(E76)))+1)+1,LEN(E76)),"") | M76: =IFERROR(IF(H76="1002",1002,VLOOKUP(I76,亿企科目!A:H,6,0)),VLOOKUP(H76,亿企科目!A:G,6,0)) -> 6711 | N76: =IFERROR(IF(H76="1002","银行账户",IF(H76="1123","供应商",VLOOKUP(I76,亿企科目!A:H,8,0))),"") | O76: =IF(N76=0,IF(M76="1002",K76,""),_xlfn.TEXTAFTER(E76,"-",-1)) -> 税收滞纳金、罚金、罚款 | P76: =VLOOKUP(A76,账簿!B:C,2,0) -> 030006 | Q76: =VLOOKUP(P76,账簿!A:B,2,0) -> 昌邑市昌荣农业科技有限责任公司 | W76: =X76&AB76&AD76 -> 0300062026-04-3011 | X76: =P76 -> 030006 | Y76: =X76 -> 030006 | Z76: =Q76 -> 昌邑市昌荣农业科技有限责任公司 | AA76: =LEFT(B76,7) -> 2026-04 | AB76: =B76 -> 2026-04-30 | AC76: 记 | AD76: =VALUE(_xlfn.TEXTAFTER(C76,"-")) -> 11 | AE76: =D76 -> 结转本月损益 | AF76: 谭雅心 | AG76: 谭雅心 | AN76: =M76 -> 6711 | AP76: =D76 -> 结转本月损益 | AQ76: CNY | AR76: =F76 | AS76: =G76 -> 69.5 | AT76: 01 | AU76: * | AV76: 1 | AW76: =AR76 | AX76: =AS76 -> 69.5 | BQ76: =IF(N76="项目",VLOOKUP(O76,项目!B:C,2,0),IF(K76="空项目",VLOOKUP(K76,项目!B:C,2,0),"")) | BR76: =IFERROR(VLOOKUP(BQ76,项目!A:B,2,0),"") | BU76: =IF(N76="供应商",VLOOKUP(O76,供应商!B:C,2,0),"") | BV76: =IFERROR(VLOOKUP(BU76,供应商!A:B,2,0),"") | BW76: =IF(N76="客户",VLOOKUP(O76,客户!B:C,2,0),"") | BX76: =IFERROR(VLOOKUP(BW76,客户!A:B,2,0),"") | CU76: =IF(N76="费用项目",VLOOKUP(O76,费用项目!B:C,2,0),"") | CV76: =IFERROR(VLOOKUP(CU76,费用项目!A:B,2,0),"") | CW76: =IF(N76="银行账户",VLOOKUP(O76,银行变二级!B:C,2,0),"") | CX76: =IFERROR(VLOOKUP(O76,银行变二级!A:B,2,0),"")
A77: 昌邑市昌盛水务发展有限责任公司 | B77: 2026-04-23 | C77: 记-001 | D77: 支取定期,昌邑市昌盛水务发展有限责任公司 | E77: 100202 银行存款-建行5022 | F77: 1.0050361e+08 | H77: =LEFT(E77,4) -> 1002 | I77: =IFERROR(LEFT(E77,FIND(" ",E77)-1),E77) -> 100202 | J77: =LEFT(MID(E77,FIND(" ",E77)+1,LEN(E77)),FIND("-",MID(E77,FIND(" ",E77)+1,LEN(E77))&"-")-1) -> 银行存款 | K77: =IFERROR(MID(MID(E77,FIND(" ",E77)+1,LEN(E77)),FIND("-",MID(E77,FIND(" ",E77)+1,LEN(E77)))+1,IFERROR(FIND("-",MID(E77,FIND(" ",E77)+1,LEN(E77)),FIND("-",MID(E77,FIND(" ",E77)+1,LEN(E77)))+1),LEN(MID(E77,FIND(" ",E77)+1,LEN(E77)))+1)-FIND("-",MID(E77,FIND(" ",E77)+1,LEN(E77)))-1),"") -> 建行5022 | L77: =IFERROR(MID(MID(E77,FIND(" ",E77)+1,LEN(E77)),FIND("-",MID(E77,FIND(" ",E77)+1,LEN(E77)),FIND("-",MID(E77,FIND(" ",E77)+1,LEN(E77)))+1)+1,LEN(E77)),"") | M77: =IFERROR(IF(H77="1002",1002,VLOOKUP(I77,亿企科目!A:H,6,0)),VLOOKUP(H77,亿企科目!A:G,6,0)) -> 1002 | N77: =IFERROR(IF(H77="1002","银行账户",IF(H77="1123","供应商",VLOOKUP(I77,亿企科目!A:H,8,0))),"") -> 银行账户 | O77: =IF(N77=0,IF(M77="1002",K77,""),_xlfn.TEXTAFTER(E77,"-",-1)) -> 建行5022 | P77: =VLOOKUP(A77,账簿!B:C,2,0) -> 003009 | Q77: =VLOOKUP(P77,账簿!A:B,2,0) -> 昌邑市昌盛水务发展有限责任公司 | W77: =X77&AB77&AD77 -> 0030092026-04-231 | X77: =P77 -> 003009 | Y77: =X77 -> 003009 | Z77: =Q77 -> 昌邑市昌盛水务发展有限责任公司 | AA77: =LEFT(B77,7) -> 2026-04 | AB77: =B77 -> 2026-04-23 | AC77: 记 | AD77: =VALUE(_xlfn.TEXTAFTER(C77,"-")) -> 1 | AE77: =D77 -> 支取定期,昌邑市昌盛水务发展有限责任公司 | AF77: 谭雅心 | AG77: 谭雅心 | AN77: =M77 -> 1002 | AP77: =D77 -> 支取定期,昌邑市昌盛水务发展有限责任公司 | AQ77: CNY | AR77: =F77 -> 1.0050361e+08 | AS77: =G77 | AT77: 01 | AU77: * | AV77: 1 | AW77: =AR77 -> 1.0050361e+08 | AX77: =AS77 | BQ77: =IF(N77="项目",VLOOKUP(O77,项目!B:C,2,0),IF(K77="空项目",VLOOKUP(K77,项目!B:C,2,0),"")) | BR77: =IFERROR(VLOOKUP(BQ77,项目!A:B,2,0),"") | BU77: =IF(N77="供应商",VLOOKUP(O77,供应商!B:C,2,0),"") | BV77: =IFERROR(VLOOKUP(BU77,供应商!A:B,2,0),"") | BW77: =IF(N77="客户",VLOOKUP(O77,客户!B:C,2,0),"") | BX77: =IFERROR(VLOOKUP(BW77,客户!A:B,2,0),"") | CU77: =IF(N77="费用项目",VLOOKUP(O77,费用项目!B:C,2,0),"") | CV77: =IFERROR(VLOOKUP(CU77,费用项目!A:B,2,0),"") | CW77: =IF(N77="银行账户",VLOOKUP(O77,银行变二级!B:C,2,0),"") -> 建行5022 | CX77: =IFERROR(VLOOKUP(O77,银行变二级!A:B,2,0),"") -> 建行5022
A78: 昌邑市昌盛水务发展有限责任公司 | B78: 2026-04-23 | C78: 记-001 | D78: 支取定期,昌邑市昌盛水务发展有限责任公司 | E78: 100203 银行存款-建行定期户0029 | G78: 1.0050361e+08 | H78: =LEFT(E78,4) -> 1002 | I78: =IFERROR(LEFT(E78,FIND(" ",E78)-1),E78) -> 100203 | J78: =LEFT(MID(E78,FIND(" ",E78)+1,LEN(E78)),FIND("-",MID(E78,FIND(" ",E78)+1,LEN(E78))&"-")-1) -> 银行存款 | K78: =IFERROR(MID(MID(E78,FIND(" ",E78)+1,LEN(E78)),FIND("-",MID(E78,FIND(" ",E78)+1,LEN(E78)))+1,IFERROR(FIND("-",MID(E78,FIND(" ",E78)+1,LEN(E78)),FIND("-",MID(E78,FIND(" ",E78)+1,LEN(E78)))+1),LEN(MID(E78,FIND(" ",E78)+1,LEN(E78)))+1)-FIND("-",MID(E78,FIND(" ",E78)+1,LEN(E78)))-1),"") -> 建行定期户0029 | L78: =IFERROR(MID(MID(E78,FIND(" ",E78)+1,LEN(E78)),FIND("-",MID(E78,FIND(" ",E78)+1,LEN(E78)),FIND("-",MID(E78,FIND(" ",E78)+1,LEN(E78)))+1)+1,LEN(E78)),"") | M78: =IFERROR(IF(H78="1002",1002,VLOOKUP(I78,亿企科目!A:H,6,0)),VLOOKUP(H78,亿企科目!A:G,6,0)) -> 1002 | N78: =IFERROR(IF(H78="1002","银行账户",IF(H78="1123","供应商",VLOOKUP(I78,亿企科目!A:H,8,0))),"") -> 银行账户 | O78: =IF(N78=0,IF(M78="1002",K78,""),_xlfn.TEXTAFTER(E78,"-",-1)) -> 建行定期户0029 | P78: =VLOOKUP(A78,账簿!B:C,2,0) -> 003009 | Q78: =VLOOKUP(P78,账簿!A:B,2,0) -> 昌邑市昌盛水务发展有限责任公司 | W78: =X78&AB78&AD78 -> 0030092026-04-231 | X78: =P78 -> 003009 | Y78: =X78 -> 003009 | Z78: =Q78 -> 昌邑市昌盛水务发展有限责任公司 | AA78: =LEFT(B78,7) -> 2026-04 | AB78: =B78 -> 2026-04-23 | AC78: 记 | AD78: =VALUE(_xlfn.TEXTAFTER(C78,"-")) -> 1 | AE78: =D78 -> 支取定期,昌邑市昌盛水务发展有限责任公司 | AF78: 谭雅心 | AG78: 谭雅心 | AN78: =M78 -> 1002 | AP78: =D78 -> 支取定期,昌邑市昌盛水务发展有限责任公司 | AQ78: CNY | AR78: =F78 | AS78: =G78 -> 1.0050361e+08 | AT78: 01 | AU78: * | AV78: 1 | AW78: =AR78 | AX78: =AS78 -> 1.0050361e+08 | BQ78: =IF(N78="项目",VLOOKUP(O78,项目!B:C,2,0),IF(K78="空项目",VLOOKUP(K78,项目!B:C,2,0),"")) | BR78: =IFERROR(VLOOKUP(BQ78,项目!A:B,2,0),"") | BU78: =IF(N78="供应商",VLOOKUP(O78,供应商!B:C,2,0),"") | BV78: =IFERROR(VLOOKUP(BU78,供应商!A:B,2,0),"") | BW78: =IF(N78="客户",VLOOKUP(O78,客户!B:C,2,0),"") | BX78: =IFERROR(VLOOKUP(BW78,客户!A:B,2,0),"") | CU78: =IF(N78="费用项目",VLOOKUP(O78,费用项目!B:C,2,0),"") | CV78: =IFERROR(VLOOKUP(CU78,费用项目!A:B,2,0),"") | CW78: =IF(N78="银行账户",VLOOKUP(O78,银行变二级!B:C,2,0),"") -> 建行定期户0029 | CX78: =IFERROR(VLOOKUP(O78,银行变二级!A:B,2,0),"") -> 建行定期户0029
A79: 昌邑市昌盛水务发展有限责任公司 | B79: 2026-04-23 | C79: 记-002 | D79: 手续费 | E79: 6603 财务费用-手续费 | F79: 2000 | H79: =LEFT(E79,4) -> 6603 | I79: =IFERROR(LEFT(E79,FIND(" ",E79)-1),E79) -> 6603 | J79: =LEFT(MID(E79,FIND(" ",E79)+1,LEN(E79)),FIND("-",MID(E79,FIND(" ",E79)+1,LEN(E79))&"-")-1) -> 财务费用 | K79: =IFERROR(MID(MID(E79,FIND(" ",E79)+1,LEN(E79)),FIND("-",MID(E79,FIND(" ",E79)+1,LEN(E79)))+1,IFERROR(FIND("-",MID(E79,FIND(" ",E79)+1,LEN(E79)),FIND("-",MID(E79,FIND(" ",E79)+1,LEN(E79)))+1),LEN(MID(E79,FIND(" ",E79)+1,LEN(E79)))+1)-FIND("-",MID(E79,FIND(" ",E79)+1,LEN(E79)))-1),"") -> 手续费 | L79: =IFERROR(MID(MID(E79,FIND(" ",E79)+1,LEN(E79)),FIND("-",MID(E79,FIND(" ",E79)+1,LEN(E79)),FIND("-",MID(E79,FIND(" ",E79)+1,LEN(E79)))+1)+1,LEN(E79)),"") | M79: =IFERROR(IF(H79="1002",1002,VLOOKUP(I79,亿企科目!A:H,6,0)),VLOOKUP(H79,亿企科目!A:G,6,0)) -> 6603 | N79: =IFERROR(IF(H79="1002","银行账户",IF(H79="1123","供应商",VLOOKUP(I79,亿企科目!A:H,8,0))),"") -> 费用项目 | O79: =IF(N79=0,IF(M79="1002",K79,""),_xlfn.TEXTAFTER(E79,"-",-1)) -> 手续费 | P79: =VLOOKUP(A79,账簿!B:C,2,0) -> 003009 | Q79: =VLOOKUP(P79,账簿!A:B,2,0) -> 昌邑市昌盛水务发展有限责任公司 | W79: =X79&AB79&AD79 -> 0030092026-04-232 | X79: =P79 -> 003009 | Y79: =X79 -> 003009 | Z79: =Q79 -> 昌邑市昌盛水务发展有限责任公司 | AA79: =LEFT(B79,7) -> 2026-04 | AB79: =B79 -> 2026-04-23 | AC79: 记 | AD79: =VALUE(_xlfn.TEXTAFTER(C79,"-")) -> 2 | AE79: =D79 -> 手续费 | AF79: 谭雅心 | AG79: 谭雅心 | AN79: =M79 -> 6603 | AP79: =D79 -> 手续费 | AQ79: CNY | AR79: =F79 -> 2000 | AS79: =G79 | AT79: 01 | AU79: * | AV79: 1 | AW79: =AR79 -> 2000 | AX79: =AS79 | BQ79: =IF(N79="项目",VLOOKUP(O79,项目!B:C,2,0),IF(K79="空项目",VLOOKUP(K79,项目!B:C,2,0),"")) | BR79: =IFERROR(VLOOKUP(BQ79,项目!A:B,2,0),"") | BU79: =IF(N79="供应商",VLOOKUP(O79,供应商!B:C,2,0),"") | BV79: =IFERROR(VLOOKUP(BU79,供应商!A:B,2,0),"") | BW79: =IF(N79="客户",VLOOKUP(O79,客户!B:C,2,0),"") | BX79: =IFERROR(VLOOKUP(BW79,客户!A:B,2,0),"") | CU79: =IF(N79="费用项目",VLOOKUP(O79,费用项目!B:C,2,0),"") -> 660304 | CV79: =IFERROR(VLOOKUP(CU79,费用项目!A:B,2,0),"") -> 手续费 | CW79: =IF(N79="银行账户",VLOOKUP(O79,银行变二级!B:C,2,0),"") | CX79: =IFERROR(VLOOKUP(O79,银行变二级!A:B,2,0),"")
A80: 昌邑市昌盛水务发展有限责任公司 | B80: 2026-04-23 | C80: 记-002 | D80: 手续费 | E80: 100202 银行存款-建行5022 | G80: 2000 | H80: =LEFT(E80,4) -> 1002 | I80: =IFERROR(LEFT(E80,FIND(" ",E80)-1),E80) -> 100202 | J80: =LEFT(MID(E80,FIND(" ",E80)+1,LEN(E80)),FIND("-",MID(E80,FIND(" ",E80)+1,LEN(E80))&"-")-1) -> 银行存款 | K80: =IFERROR(MID(MID(E80,FIND(" ",E80)+1,LEN(E80)),FIND("-",MID(E80,FIND(" ",E80)+1,LEN(E80)))+1,IFERROR(FIND("-",MID(E80,FIND(" ",E80)+1,LEN(E80)),FIND("-",MID(E80,FIND(" ",E80)+1,LEN(E80)))+1),LEN(MID(E80,FIND(" ",E80)+1,LEN(E80)))+1)-FIND("-",MID(E80,FIND(" ",E80)+1,LEN(E80)))-1),"") -> 建行5022 | L80: =IFERROR(MID(MID(E80,FIND(" ",E80)+1,LEN(E80)),FIND("-",MID(E80,FIND(" ",E80)+1,LEN(E80)),FIND("-",MID(E80,FIND(" ",E80)+1,LEN(E80)))+1)+1,LEN(E80)),"") | M80: =IFERROR(IF(H80="1002",1002,VLOOKUP(I80,亿企科目!A:H,6,0)),VLOOKUP(H80,亿企科目!A:G,6,0)) -> 1002 | N80: =IFERROR(IF(H80="1002","银行账户",IF(H80="1123","供应商",VLOOKUP(I80,亿企科目!A:H,8,0))),"") -> 银行账户 | O80: =IF(N80=0,IF(M80="1002",K80,""),_xlfn.TEXTAFTER(E80,"-",-1)) -> 建行5022 | P80: =VLOOKUP(A80,账簿!B:C,2,0) -> 003009 | Q80: =VLOOKUP(P80,账簿!A:B,2,0) -> 昌邑市昌盛水务发展有限责任公司 | W80: =X80&AB80&AD80 -> 0030092026-04-232 | X80: =P80 -> 003009 | Y80: =X80 -> 003009 | Z80: =Q80 -> 昌邑市昌盛水务发展有限责任公司 | AA80: =LEFT(B80,7) -> 2026-04 | AB80: =B80 -> 2026-04-23 | AC80: 记 | AD80: =VALUE(_xlfn.TEXTAFTER(C80,"-")) -> 2 | AE80: =D80 -> 手续费 | AF80: 谭雅心 | AG80: 谭雅心 | AN80: =M80 -> 1002 | AP80: =D80 -> 手续费 | AQ80: CNY | AR80: =F80 | AS80: =G80 -> 2000 | AT80: 01 | AU80: * | AV80: 1 | AW80: =AR80 | AX80: =AS80 -> 2000 | BQ80: =IF(N80="项目",VLOOKUP(O80,项目!B:C,2,0),IF(K80="空项目",VLOOKUP(K80,项目!B:C,2,0),"")) | BR80: =IFERROR(VLOOKUP(BQ80,项目!A:B,2,0),"") | BU80: =IF(N80="供应商",VLOOKUP(O80,供应商!B:C,2,0),"") | BV80: =IFERROR(VLOOKUP(BU80,供应商!A:B,2,0),"") | BW80: =IF(N80="客户",VLOOKUP(O80,客户!B:C,2,0),"") | BX80: =IFERROR(VLOOKUP(BW80,客户!A:B,2,0),"") | CU80: =IF(N80="费用项目",VLOOKUP(O80,费用项目!B:C,2,0),"") | CV80: =IFERROR(VLOOKUP(CU80,费用项目!A:B,2,0),"") | CW80: =IF(N80="银行账户",VLOOKUP(O80,银行变二级!B:C,2,0),"") -> 建行5022 | CX80: =IFERROR(VLOOKUP(O80,银行变二级!A:B,2,0),"") -> 建行5022
A81: 昌邑市昌盛水务发展有限责任公司 | B81: 2026-04-23 | C81: 记-003 | D81: 转账,转账,昌邑市城投农业科技有限公司 | E81: 122108 其他应收款-单位-昌邑市城投农业科技有限公司 | F81: 100000000 | H81: =LEFT(E81,4) -> 1221 | I81: =IFERROR(LEFT(E81,FIND(" ",E81)-1),E81) -> 122108 | J81: =LEFT(MID(E81,FIND(" ",E81)+1,LEN(E81)),FIND("-",MID(E81,FIND(" ",E81)+1,LEN(E81))&"-")-1) -> 其他应收款 | K81: =IFERROR(MID(MID(E81,FIND(" ",E81)+1,LEN(E81)),FIND("-",MID(E81,FIND(" ",E81)+1,LEN(E81)))+1,IFERROR(FIND("-",MID(E81,FIND(" ",E81)+1,LEN(E81)),FIND("-",MID(E81,FIND(" ",E81)+1,LEN(E81)))+1),LEN(MID(E81,FIND(" ",E81)+1,LEN(E81)))+1)-FIND("-",MID(E81,FIND(" ",E81)+1,LEN(E81)))-1),"") -> 单位 | L81: =IFERROR(MID(MID(E81,FIND(" ",E81)+1,LEN(E81)),FIND("-",MID(E81,FIND(" ",E81)+1,LEN(E81)),FIND("-",MID(E81,FIND(" ",E81)+1,LEN(E81)))+1)+1,LEN(E81)),"") -> 昌邑市城投农业科技有限公司 | M81: =IFERROR(IF(H81="1002",1002,VLOOKUP(I81,亿企科目!A:H,6,0)),VLOOKUP(H81,亿企科目!A:G,6,0)) -> 122102 | N81: =IFERROR(IF(H81="1002","银行账户",IF(H81="1123","供应商",VLOOKUP(I81,亿企科目!A:H,8,0))),"") -> 客户 | O81: =IF(N81=0,IF(M81="1002",K81,""),_xlfn.TEXTAFTER(E81,"-",-1)) -> 昌邑市城投农业科技有限公司 | P81: =VLOOKUP(A81,账簿!B:C,2,0) -> 003009 | Q81: =VLOOKUP(P81,账簿!A:B,2,0) -> 昌邑市昌盛水务发展有限责任公司 | W81: =X81&AB81&AD81 -> 0030092026-04-233 | X81: =P81 -> 003009 | Y81: =X81 -> 003009 | Z81: =Q81 -> 昌邑市昌盛水务发展有限责任公司 | AA81: =LEFT(B81,7) -> 2026-04 | AB81: =B81 -> 2026-04-23 | AC81: 记 | AD81: =VALUE(_xlfn.TEXTAFTER(C81,"-")) -> 3 | AE81: =D81 -> 转账,转账,昌邑市城投农业科技有限公司 | AF81: 谭雅心 | AG81: 谭雅心 | AN81: =M81 -> 122102 | AP81: =D81 -> 转账,转账,昌邑市城投农业科技有限公司 | AQ81: CNY | AR81: =F81 -> 100000000 | AS81: =G81 | AT81: 01 | AU81: * | AV81: 1 | AW81: =AR81 -> 100000000 | AX81: =AS81 | BQ81: =IF(N81="项目",VLOOKUP(O81,项目!B:C,2,0),IF(K81="空项目",VLOOKUP(K81,项目!B:C,2,0),"")) | BR81: =IFERROR(VLOOKUP(BQ81,项目!A:B,2,0),"") | BU81: =IF(N81="供应商",VLOOKUP(O81,供应商!B:C,2,0),"") | BV81: =IFERROR(VLOOKUP(BU81,供应商!A:B,2,0),"") | BW81: =IF(N81="客户",VLOOKUP(O81,客户!B:C,2,0),"") -> 003003 | BX81: =IFERROR(VLOOKUP(BW81,客户!A:B,2,0),"") -> 昌邑市城投农业科技有限公司 | CU81: =IF(N81="费用项目",VLOOKUP(O81,费用项目!B:C,2,0),"") | CV81: =IFERROR(VLOOKUP(CU81,费用项目!A:B,2,0),"") | CW81: =IF(N81="银行账户",VLOOKUP(O81,银行变二级!B:C,2,0),"") | CX81: =IFERROR(VLOOKUP(O81,银行变二级!A:B,2,0),"")
A82: 昌邑市昌盛水务发展有限责任公司 | B82: 2026-04-23 | C82: 记-003 | D82: 转账,转账,昌邑市城投农业科技有限公司 | E82: 100202 银行存款-建行5022 | G82: 100000000 | H82: =LEFT(E82,4) -> 1002 | I82: =IFERROR(LEFT(E82,FIND(" ",E82)-1),E82) -> 100202 | J82: =LEFT(MID(E82,FIND(" ",E82)+1,LEN(E82)),FIND("-",MID(E82,FIND(" ",E82)+1,LEN(E82))&"-")-1) -> 银行存款 | K82: =IFERROR(MID(MID(E82,FIND(" ",E82)+1,LEN(E82)),FIND("-",MID(E82,FIND(" ",E82)+1,LEN(E82)))+1,IFERROR(FIND("-",MID(E82,FIND(" ",E82)+1,LEN(E82)),FIND("-",MID(E82,FIND(" ",E82)+1,LEN(E82)))+1),LEN(MID(E82,FIND(" ",E82)+1,LEN(E82)))+1)-FIND("-",MID(E82,FIND(" ",E82)+1,LEN(E82)))-1),"") -> 建行5022 | L82: =IFERROR(MID(MID(E82,FIND(" ",E82)+1,LEN(E82)),FIND("-",MID(E82,FIND(" ",E82)+1,LEN(E82)),FIND("-",MID(E82,FIND(" ",E82)+1,LEN(E82)))+1)+1,LEN(E82)),"") | M82: =IFERROR(IF(H82="1002",1002,VLOOKUP(I82,亿企科目!A:H,6,0)),VLOOKUP(H82,亿企科目!A:G,6,0)) -> 1002 | N82: =IFERROR(IF(H82="1002","银行账户",IF(H82="1123","供应商",VLOOKUP(I82,亿企科目!A:H,8,0))),"") -> 银行账户 | O82: =IF(N82=0,IF(M82="1002",K82,""),_xlfn.TEXTAFTER(E82,"-",-1)) -> 建行5022 | P82: =VLOOKUP(A82,账簿!B:C,2,0) -> 003009 | Q82: =VLOOKUP(P82,账簿!A:B,2,0) -> 昌邑市昌盛水务发展有限责任公司 | W82: =X82&AB82&AD82 -> 0030092026-04-233 | X82: =P82 -> 003009 | Y82: =X82 -> 003009 | Z82: =Q82 -> 昌邑市昌盛水务发展有限责任公司 | AA82: =LEFT(B82,7) -> 2026-04 | AB82: =B82 -> 2026-04-23 | AC82: 记 | AD82: =VALUE(_xlfn.TEXTAFTER(C82,"-")) -> 3 | AE82: =D82 -> 转账,转账,昌邑市城投农业科技有限公司 | AF82: 谭雅心 | AG82: 谭雅心 | AN82: =M82 -> 1002 | AP82: =D82 -> 转账,转账,昌邑市城投农业科技有限公司 | AQ82: CNY | AR82: =F82 | AS82: =G82 -> 100000000 | AT82: 01 | AU82: * | AV82: 1 | AW82: =AR82 | AX82: =AS82 -> 100000000 | BQ82: =IF(N82="项目",VLOOKUP(O82,项目!B:C,2,0),IF(K82="空项目",VLOOKUP(K82,项目!B:C,2,0),"")) | BR82: =IFERROR(VLOOKUP(BQ82,项目!A:B,2,0),"") | BU82: =IF(N82="供应商",VLOOKUP(O82,供应商!B:C,2,0),"") | BV82: =IFERROR(VLOOKUP(BU82,供应商!A:B,2,0),"") | BW82: =IF(N82="客户",VLOOKUP(O82,客户!B:C,2,0),"") | BX82: =IFERROR(VLOOKUP(BW82,客户!A:B,2,0),"") | CU82: =IF(N82="费用项目",VLOOKUP(O82,费用项目!B:C,2,0),"") | CV82: =IFERROR(VLOOKUP(CU82,费用项目!A:B,2,0),"") | CW82: =IF(N82="银行账户",VLOOKUP(O82,银行变二级!B:C,2,0),"") -> 建行5022 | CX82: =IFERROR(VLOOKUP(O82,银行变二级!A:B,2,0),"") -> 建行5022
A83: 昌邑市昌盛水务发展有限责任公司 | B83: 2026-04-30 | C83: 记-004 | D83: 结转本月损益 | E83: 4103 本年利润 | F83: 2000 | H83: =LEFT(E83,4) -> 4103 | I83: =IFERROR(LEFT(E83,FIND(" ",E83)-1),E83) -> 4103 | J83: =LEFT(MID(E83,FIND(" ",E83)+1,LEN(E83)),FIND("-",MID(E83,FIND(" ",E83)+1,LEN(E83))&"-")-1) -> 本年利润 | K83: =IFERROR(MID(MID(E83,FIND(" ",E83)+1,LEN(E83)),FIND("-",MID(E83,FIND(" ",E83)+1,LEN(E83)))+1,IFERROR(FIND("-",MID(E83,FIND(" ",E83)+1,LEN(E83)),FIND("-",MID(E83,FIND(" ",E83)+1,LEN(E83)))+1),LEN(MID(E83,FIND(" ",E83)+1,LEN(E83)))+1)-FIND("-",MID(E83,FIND(" ",E83)+1,LEN(E83)))-1),"") | L83: =IFERROR(MID(MID(E83,FIND(" ",E83)+1,LEN(E83)),FIND("-",MID(E83,FIND(" ",E83)+1,LEN(E83)),FIND("-",MID(E83,FIND(" ",E83)+1,LEN(E83)))+1)+1,LEN(E83)),"") | M83: =IFERROR(IF(H83="1002",1002,VLOOKUP(I83,亿企科目!A:H,6,0)),VLOOKUP(H83,亿企科目!A:G,6,0)) -> 4103 | N83: =IFERROR(IF(H83="1002","银行账户",IF(H83="1123","供应商",VLOOKUP(I83,亿企科目!A:H,8,0))),"") -> 0 | O83: =IF(N83=0,IF(M83="1002",K83,""),_xlfn.TEXTAFTER(E83,"-",-1)) | P83: =VLOOKUP(A83,账簿!B:C,2,0) -> 003009 | Q83: =VLOOKUP(P83,账簿!A:B,2,0) -> 昌邑市昌盛水务发展有限责任公司 | W83: =X83&AB83&AD83 -> 0030092026-04-304 | X83: =P83 -> 003009 | Y83: =X83 -> 003009 | Z83: =Q83 -> 昌邑市昌盛水务发展有限责任公司 | AA83: =LEFT(B83,7) -> 2026-04 | AB83: =B83 -> 2026-04-30 | AC83: 记 | AD83: =VALUE(_xlfn.TEXTAFTER(C83,"-")) -> 4 | AE83: =D83 -> 结转本月损益 | AF83: 谭雅心 | AG83: 谭雅心 | AN83: =M83 -> 4103 | AP83: =D83 -> 结转本月损益 | AQ83: CNY | AR83: =F83 -> 2000 | AS83: =G83 | AT83: 01 | AU83: * | AV83: 1 | AW83: =AR83 -> 2000 | AX83: =AS83 | BQ83: =IF(N83="项目",VLOOKUP(O83,项目!B:C,2,0),IF(K83="空项目",VLOOKUP(K83,项目!B:C,2,0),"")) | BR83: =IFERROR(VLOOKUP(BQ83,项目!A:B,2,0),"") | BU83: =IF(N83="供应商",VLOOKUP(O83,供应商!B:C,2,0),"") | BV83: =IFERROR(VLOOKUP(BU83,供应商!A:B,2,0),"") | BW83: =IF(N83="客户",VLOOKUP(O83,客户!B:C,2,0),"") | BX83: =IFERROR(VLOOKUP(BW83,客户!A:B,2,0),"") | CU83: =IF(N83="费用项目",VLOOKUP(O83,费用项目!B:C,2,0),"") | CV83: =IFERROR(VLOOKUP(CU83,费用项目!A:B,2,0),"") | CW83: =IF(N83="银行账户",VLOOKUP(O83,银行变二级!B:C,2,0),"") | CX83: =IFERROR(VLOOKUP(O83,银行变二级!A:B,2,0),"")
A84: 昌邑市昌盛水务发展有限责任公司 | B84: 2026-04-30 | C84: 记-004 | D84: 结转本月损益 | E84: 6603 财务费用-手续费 | G84: 2000 | H84: =LEFT(E84,4) -> 6603 | I84: =IFERROR(LEFT(E84,FIND(" ",E84)-1),E84) -> 6603 | J84: =LEFT(MID(E84,FIND(" ",E84)+1,LEN(E84)),FIND("-",MID(E84,FIND(" ",E84)+1,LEN(E84))&"-")-1) -> 财务费用 | K84: =IFERROR(MID(MID(E84,FIND(" ",E84)+1,LEN(E84)),FIND("-",MID(E84,FIND(" ",E84)+1,LEN(E84)))+1,IFERROR(FIND("-",MID(E84,FIND(" ",E84)+1,LEN(E84)),FIND("-",MID(E84,FIND(" ",E84)+1,LEN(E84)))+1),LEN(MID(E84,FIND(" ",E84)+1,LEN(E84)))+1)-FIND("-",MID(E84,FIND(" ",E84)+1,LEN(E84)))-1),"") -> 手续费 | L84: =IFERROR(MID(MID(E84,FIND(" ",E84)+1,LEN(E84)),FIND("-",MID(E84,FIND(" ",E84)+1,LEN(E84)),FIND("-",MID(E84,FIND(" ",E84)+1,LEN(E84)))+1)+1,LEN(E84)),"") | M84: =IFERROR(IF(H84="1002",1002,VLOOKUP(I84,亿企科目!A:H,6,0)),VLOOKUP(H84,亿企科目!A:G,6,0)) -> 6603 | N84: =IFERROR(IF(H84="1002","银行账户",IF(H84="1123","供应商",VLOOKUP(I84,亿企科目!A:H,8,0))),"") -> 费用项目 | O84: =IF(N84=0,IF(M84="1002",K84,""),_xlfn.TEXTAFTER(E84,"-",-1)) -> 手续费 | P84: =VLOOKUP(A84,账簿!B:C,2,0) -> 003009 | Q84: =VLOOKUP(P84,账簿!A:B,2,0) -> 昌邑市昌盛水务发展有限责任公司 | W84: =X84&AB84&AD84 -> 0030092026-04-304 | X84: =P84 -> 003009 | Y84: =X84 -> 003009 | Z84: =Q84 -> 昌邑市昌盛水务发展有限责任公司 | AA84: =LEFT(B84,7) -> 2026-04 | AB84: =B84 -> 2026-04-30 | AC84: 记 | AD84: =VALUE(_xlfn.TEXTAFTER(C84,"-")) -> 4 | AE84: =D84 -> 结转本月损益 | AF84: 谭雅心 | AG84: 谭雅心 | AN84: =M84 -> 6603 | AP84: =D84 -> 结转本月损益 | AQ84: CNY | AR84: =F84 | AS84: =G84 -> 2000 | AT84: 01 | AU84: * | AV84: 1 | AW84: =AR84 | AX84: =AS84 -> 2000 | BQ84: =IF(N84="项目",VLOOKUP(O84,项目!B:C,2,0),IF(K84="空项目",VLOOKUP(K84,项目!B:C,2,0),"")) | BR84: =IFERROR(VLOOKUP(BQ84,项目!A:B,2,0),"") | BU84: =IF(N84="供应商",VLOOKUP(O84,供应商!B:C,2,0),"") | BV84: =IFERROR(VLOOKUP(BU84,供应商!A:B,2,0),"") | BW84: =IF(N84="客户",VLOOKUP(O84,客户!B:C,2,0),"") | BX84: =IFERROR(VLOOKUP(BW84,客户!A:B,2,0),"") | CU84: =IF(N84="费用项目",VLOOKUP(O84,费用项目!B:C,2,0),"") -> 660304 | CV84: =IFERROR(VLOOKUP(CU84,费用项目!A:B,2,0),"") -> 手续费 | CW84: =IF(N84="银行账户",VLOOKUP(O84,银行变二级!B:C,2,0),"") | CX84: =IFERROR(VLOOKUP(O84,银行变二级!A:B,2,0),"")
A85: 昌邑市昌信农业综合开发有限公司 | B85: 2026-04-10 | C85: 记-001 | D85: 2026-04-10,电子银行年服务费-企业网银服务费 | E85: 6603 财务费用-手续费 | F85: 600 | H85: =LEFT(E85,4) -> 6603 | I85: =IFERROR(LEFT(E85,FIND(" ",E85)-1),E85) -> 6603 | J85: =LEFT(MID(E85,FIND(" ",E85)+1,LEN(E85)),FIND("-",MID(E85,FIND(" ",E85)+1,LEN(E85))&"-")-1) -> 财务费用 | K85: =IFERROR(MID(MID(E85,FIND(" ",E85)+1,LEN(E85)),FIND("-",MID(E85,FIND(" ",E85)+1,LEN(E85)))+1,IFERROR(FIND("-",MID(E85,FIND(" ",E85)+1,LEN(E85)),FIND("-",MID(E85,FIND(" ",E85)+1,LEN(E85)))+1),LEN(MID(E85,FIND(" ",E85)+1,LEN(E85)))+1)-FIND("-",MID(E85,FIND(" ",E85)+1,LEN(E85)))-1),"") -> 手续费 | L85: =IFERROR(MID(MID(E85,FIND(" ",E85)+1,LEN(E85)),FIND("-",MID(E85,FIND(" ",E85)+1,LEN(E85)),FIND("-",MID(E85,FIND(" ",E85)+1,LEN(E85)))+1)+1,LEN(E85)),"") | M85: =IFERROR(IF(H85="1002",1002,VLOOKUP(I85,亿企科目!A:H,6,0)),VLOOKUP(H85,亿企科目!A:G,6,0)) -> 6603 | N85: =IFERROR(IF(H85="1002","银行账户",IF(H85="1123","供应商",VLOOKUP(I85,亿企科目!A:H,8,0))),"") -> 费用项目 | O85: =IF(N85=0,IF(M85="1002",K85,""),_xlfn.TEXTAFTER(E85,"-",-1)) -> 手续费 | P85: =VLOOKUP(A85,账簿!B:C,2,0) -> 002001 | Q85: =VLOOKUP(P85,账簿!A:B,2,0) -> 昌邑市昌信农业综合开发有限公司 | W85: =X85&AB85&AD85 -> 0020012026-04-101 | X85: =P85 -> 002001 | Y85: =X85 -> 002001 | Z85: =Q85 -> 昌邑市昌信农业综合开发有限公司 | AA85: =LEFT(B85,7) -> 2026-04 | AB85: =B85 -> 2026-04-10 | AC85: 记 | AD85: =VALUE(_xlfn.TEXTAFTER(C85,"-")) -> 1 | AE85: =D85 -> 2026-04-10,电子银行年服务费-企业网银服务费 | AF85: 谭雅心 | AG85: 谭雅心 | AN85: =M85 -> 6603 | AP85: =D85 -> 2026-04-10,电子银行年服务费-企业网银服务费 | AQ85: CNY | AR85: =F85 -> 600 | AS85: =G85 | AT85: 01 | AU85: * | AV85: 1 | AW85: =AR85 -> 600 | AX85: =AS85 | BQ85: =IF(N85="项目",VLOOKUP(O85,项目!B:C,2,0),IF(K85="空项目",VLOOKUP(K85,项目!B:C,2,0),"")) | BR85: =IFERROR(VLOOKUP(BQ85,项目!A:B,2,0),"") | BU85: =IF(N85="供应商",VLOOKUP(O85,供应商!B:C,2,0),"") | BV85: =IFERROR(VLOOKUP(BU85,供应商!A:B,2,0),"") | BW85: =IF(N85="客户",VLOOKUP(O85,客户!B:C,2,0),"") | BX85: =IFERROR(VLOOKUP(BW85,客户!A:B,2,0),"") | CU85: =IF(N85="费用项目",VLOOKUP(O85,费用项目!B:C,2,0),"") -> 660304 | CV85: =IFERROR(VLOOKUP(CU85,费用项目!A:B,2,0),"") -> 手续费 | CW85: =IF(N85="银行账户",VLOOKUP(O85,银行变二级!B:C,2,0),"") | CX85: =IFERROR(VLOOKUP(O85,银行变二级!A:B,2,0),"")
A86: 昌邑市昌信农业综合开发有限公司 | B86: 2026-04-10 | C86: 记-001 | D86: 2026-04-10,电子银行年服务费-企业网银服务费 | E86: 100207 银行存款-昌邑建行2334 | G86: 600 | H86: =LEFT(E86,4) -> 1002 | I86: =IFERROR(LEFT(E86,FIND(" ",E86)-1),E86) -> 100207 | J86: =LEFT(MID(E86,FIND(" ",E86)+1,LEN(E86)),FIND("-",MID(E86,FIND(" ",E86)+1,LEN(E86))&"-")-1) -> 银行存款 | K86: =IFERROR(MID(MID(E86,FIND(" ",E86)+1,LEN(E86)),FIND("-",MID(E86,FIND(" ",E86)+1,LEN(E86)))+1,IFERROR(FIND("-",MID(E86,FIND(" ",E86)+1,LEN(E86)),FIND("-",MID(E86,FIND(" ",E86)+1,LEN(E86)))+1),LEN(MID(E86,FIND(" ",E86)+1,LEN(E86)))+1)-FIND("-",MID(E86,FIND(" ",E86)+1,LEN(E86)))-1),"") -> 昌邑建行2334 | L86: =IFERROR(MID(MID(E86,FIND(" ",E86)+1,LEN(E86)),FIND("-",MID(E86,FIND(" ",E86)+1,LEN(E86)),FIND("-",MID(E86,FIND(" ",E86)+1,LEN(E86)))+1)+1,LEN(E86)),"") | M86: =IFERROR(IF(H86="1002",1002,VLOOKUP(I86,亿企科目!A:H,6,0)),VLOOKUP(H86,亿企科目!A:G,6,0)) -> 1002 | N86: =IFERROR(IF(H86="1002","银行账户",IF(H86="1123","供应商",VLOOKUP(I86,亿企科目!A:H,8,0))),"") -> 银行账户 | O86: =IF(N86=0,IF(M86="1002",K86,""),_xlfn.TEXTAFTER(E86,"-",-1)) -> 昌邑建行2334 | P86: =VLOOKUP(A86,账簿!B:C,2,0) -> 002001 | Q86: =VLOOKUP(P86,账簿!A:B,2,0) -> 昌邑市昌信农业综合开发有限公司 | W86: =X86&AB86&AD86 -> 0020012026-04-101 | X86: =P86 -> 002001 | Y86: =X86 -> 002001 | Z86: =Q86 -> 昌邑市昌信农业综合开发有限公司 | AA86: =LEFT(B86,7) -> 2026-04 | AB86: =B86 -> 2026-04-10 | AC86: 记 | AD86: =VALUE(_xlfn.TEXTAFTER(C86,"-")) -> 1 | AE86: =D86 -> 2026-04-10,电子银行年服务费-企业网银服务费 | AF86: 谭雅心 | AG86: 谭雅心 | AN86: =M86 -> 1002 | AP86: =D86 -> 2026-04-10,电子银行年服务费-企业网银服务费 | AQ86: CNY | AR86: =F86 | AS86: =G86 -> 600 | AT86: 01 | AU86: * | AV86: 1 | AW86: =AR86 | AX86: =AS86 -> 600 | BQ86: =IF(N86="项目",VLOOKUP(O86,项目!B:C,2,0),IF(K86="空项目",VLOOKUP(K86,项目!B:C,2,0),"")) | BR86: =IFERROR(VLOOKUP(BQ86,项目!A:B,2,0),"") | BU86: =IF(N86="供应商",VLOOKUP(O86,供应商!B:C,2,0),"") | BV86: =IFERROR(VLOOKUP(BU86,供应商!A:B,2,0),"") | BW86: =IF(N86="客户",VLOOKUP(O86,客户!B:C,2,0),"") | BX86: =IFERROR(VLOOKUP(BW86,客户!A:B,2,0),"") | CU86: =IF(N86="费用项目",VLOOKUP(O86,费用项目!B:C,2,0),"") | CV86: =IFERROR(VLOOKUP(CU86,费用项目!A:B,2,0),"") | CW86: =IF(N86="银行账户",VLOOKUP(O86,银行变二级!B:C,2,0),"") -> 昌邑建行2334 | CX86: =IFERROR(VLOOKUP(O86,银行变二级!A:B,2,0),"") -> 昌邑建行2334
A87: 昌邑市昌信农业综合开发有限公司 | B87: 2026-04-21 | C87: 记-002 | D87: 2026-04-21,普通汇兑,昌邑市城市建设发展投资集团有限公司 | E87: 100204 银行存款-昌邑农发行经营收入户3341 | F87: 400000 | H87: =LEFT(E87,4) -> 1002 | I87: =IFERROR(LEFT(E87,FIND(" ",E87)-1),E87) -> 100204 | J87: =LEFT(MID(E87,FIND(" ",E87)+1,LEN(E87)),FIND("-",MID(E87,FIND(" ",E87)+1,LEN(E87))&"-")-1) -> 银行存款 | K87: =IFERROR(MID(MID(E87,FIND(" ",E87)+1,LEN(E87)),FIND("-",MID(E87,FIND(" ",E87)+1,LEN(E87)))+1,IFERROR(FIND("-",MID(E87,FIND(" ",E87)+1,LEN(E87)),FIND("-",MID(E87,FIND(" ",E87)+1,LEN(E87)))+1),LEN(MID(E87,FIND(" ",E87)+1,LEN(E87)))+1)-FIND("-",MID(E87,FIND(" ",E87)+1,LEN(E87)))-1),"") -> 昌邑农发行经营收入户3341 | L87: =IFERROR(MID(MID(E87,FIND(" ",E87)+1,LEN(E87)),FIND("-",MID(E87,FIND(" ",E87)+1,LEN(E87)),FIND("-",MID(E87,FIND(" ",E87)+1,LEN(E87)))+1)+1,LEN(E87)),"") | M87: =IFERROR(IF(H87="1002",1002,VLOOKUP(I87,亿企科目!A:H,6,0)),VLOOKUP(H87,亿企科目!A:G,6,0)) -> 1002 | N87: =IFERROR(IF(H87="1002","银行账户",IF(H87="1123","供应商",VLOOKUP(I87,亿企科目!A:H,8,0))),"") -> 银行账户 | O87: =IF(N87=0,IF(M87="1002",K87,""),_xlfn.TEXTAFTER(E87,"-",-1)) -> 昌邑农发行经营收入户3341 | P87: =VLOOKUP(A87,账簿!B:C,2,0) -> 002001 | Q87: =VLOOKUP(P87,账簿!A:B,2,0) -> 昌邑市昌信农业综合开发有限公司 | W87: =X87&AB87&AD87 -> 0020012026-04-212 | X87: =P87 -> 002001 | Y87: =X87 -> 002001 | Z87: =Q87 -> 昌邑市昌信农业综合开发有限公司 | AA87: =LEFT(B87,7) -> 2026-04 | AB87: =B87 -> 2026-04-21 | AC87: 记 | AD87: =VALUE(_xlfn.TEXTAFTER(C87,"-")) -> 2 | AE87: =D87 -> 2026-04-21,普通汇兑,昌邑市城市建设发展投资集团有限公司 | AF87: 谭雅心 | AG87: 谭雅心 | AN87: =M87 -> 1002 | AP87: =D87 -> 2026-04-21,普通汇兑,昌邑市城市建设发展投资集团有限公司 | AQ87: CNY | AR87: =F87 -> 400000 | AS87: =G87 | AT87: 01 | AU87: * | AV87: 1 | AW87: =AR87 -> 400000 | AX87: =AS87 | BQ87: =IF(N87="项目",VLOOKUP(O87,项目!B:C,2,0),IF(K87="空项目",VLOOKUP(K87,项目!B:C,2,0),"")) | BR87: =IFERROR(VLOOKUP(BQ87,项目!A:B,2,0),"") | BU87: =IF(N87="供应商",VLOOKUP(O87,供应商!B:C,2,0),"") | BV87: =IFERROR(VLOOKUP(BU87,供应商!A:B,2,0),"") | BW87: =IF(N87="客户",VLOOKUP(O87,客户!B:C,2,0),"") | BX87: =IFERROR(VLOOKUP(BW87,客户!A:B,2,0),"") | CU87: =IF(N87="费用项目",VLOOKUP(O87,费用项目!B:C,2,0),"") | CV87: =IFERROR(VLOOKUP(CU87,费用项目!A:B,2,0),"") | CW87: =IF(N87="银行账户",VLOOKUP(O87,银行变二级!B:C,2,0),"") -> 昌邑农发行经营收入户3341 | CX87: =IFERROR(VLOOKUP(O87,银行变二级!A:B,2,0),"") -> 昌邑农发行经营收入户3341
A88: 昌邑市昌信农业综合开发有限公司 | B88: 2026-04-21 | C88: 记-002 | D88: 2026-04-21,普通汇兑,昌邑市城市建设发展投资集团有限公司 | E88: 122108 其他应收款-单位-昌邑市城市建设发展投资集团有限公司 | G88: 400000 | H88: =LEFT(E88,4) -> 1221 | I88: =IFERROR(LEFT(E88,FIND(" ",E88)-1),E88) -> 122108 | J88: =LEFT(MID(E88,FIND(" ",E88)+1,LEN(E88)),FIND("-",MID(E88,FIND(" ",E88)+1,LEN(E88))&"-")-1) -> 其他应收款 | K88: =IFERROR(MID(MID(E88,FIND(" ",E88)+1,LEN(E88)),FIND("-",MID(E88,FIND(" ",E88)+1,LEN(E88)))+1,IFERROR(FIND("-",MID(E88,FIND(" ",E88)+1,LEN(E88)),FIND("-",MID(E88,FIND(" ",E88)+1,LEN(E88)))+1),LEN(MID(E88,FIND(" ",E88)+1,LEN(E88)))+1)-FIND("-",MID(E88,FIND(" ",E88)+1,LEN(E88)))-1),"") -> 单位 | L88: =IFERROR(MID(MID(E88,FIND(" ",E88)+1,LEN(E88)),FIND("-",MID(E88,FIND(" ",E88)+1,LEN(E88)),FIND("-",MID(E88,FIND(" ",E88)+1,LEN(E88)))+1)+1,LEN(E88)),"") -> 昌邑市城市建设发展投资集团有限公司 | M88: =IFERROR(IF(H88="1002",1002,VLOOKUP(I88,亿企科目!A:H,6,0)),VLOOKUP(H88,亿企科目!A:G,6,0)) -> 122102 | N88: =IFERROR(IF(H88="1002","银行账户",IF(H88="1123","供应商",VLOOKUP(I88,亿企科目!A:H,8,0))),"") -> 客户 | O88: =IF(N88=0,IF(M88="1002",K88,""),_xlfn.TEXTAFTER(E88,"-",-1)) -> 昌邑市城市建设发展投资集团有限公司 | P88: =VLOOKUP(A88,账簿!B:C,2,0) -> 002001 | Q88: =VLOOKUP(P88,账簿!A:B,2,0) -> 昌邑市昌信农业综合开发有限公司 | W88: =X88&AB88&AD88 -> 0020012026-04-212 | X88: =P88 -> 002001 | Y88: =X88 -> 002001 | Z88: =Q88 -> 昌邑市昌信农业综合开发有限公司 | AA88: =LEFT(B88,7) -> 2026-04 | AB88: =B88 -> 2026-04-21 | AC88: 记 | AD88: =VALUE(_xlfn.TEXTAFTER(C88,"-")) -> 2 | AE88: =D88 -> 2026-04-21,普通汇兑,昌邑市城市建设发展投资集团有限公司 | AF88: 谭雅心 | AG88: 谭雅心 | AN88: =M88 -> 122102 | AP88: =D88 -> 2026-04-21,普通汇兑,昌邑市城市建设发展投资集团有限公司 | AQ88: CNY | AR88: =F88 | AS88: =G88 -> 400000 | AT88: 01 | AU88: * | AV88: 1 | AW88: =AR88 | AX88: =AS88 -> 400000 | BQ88: =IF(N88="项目",VLOOKUP(O88,项目!B:C,2,0),IF(K88="空项目",VLOOKUP(K88,项目!B:C,2,0),"")) | BR88: =IFERROR(VLOOKUP(BQ88,项目!A:B,2,0),"") | BU88: =IF(N88="供应商",VLOOKUP(O88,供应商!B:C,2,0),"") | BV88: =IFERROR(VLOOKUP(BU88,供应商!A:B,2,0),"") | BW88: =IF(N88="客户",VLOOKUP(O88,客户!B:C,2,0),"") -> 002 | BX88: =IFERROR(VLOOKUP(BW88,客户!A:B,2,0),"") -> 昌邑市城市建设发展投资集团有限公司 | CU88: =IF(N88="费用项目",VLOOKUP(O88,费用项目!B:C,2,0),"") | CV88: =IFERROR(VLOOKUP(CU88,费用项目!A:B,2,0),"") | CW88: =IF(N88="银行账户",VLOOKUP(O88,银行变二级!B:C,2,0),"") | CX88: =IFERROR(VLOOKUP(O88,银行变二级!A:B,2,0),"")
A89: 昌邑市昌信农业综合开发有限公司 | B89: 2026-04-21 | C89: 记-003 | D89: 2026-04-21,归还贷款 | E89: 6603 财务费用-利息支出 | F89: 156033.33 | H89: =LEFT(E89,4) -> 6603 | I89: =IFERROR(LEFT(E89,FIND(" ",E89)-1),E89) -> 6603 | J89: =LEFT(MID(E89,FIND(" ",E89)+1,LEN(E89)),FIND("-",MID(E89,FIND(" ",E89)+1,LEN(E89))&"-")-1) -> 财务费用 | K89: =IFERROR(MID(MID(E89,FIND(" ",E89)+1,LEN(E89)),FIND("-",MID(E89,FIND(" ",E89)+1,LEN(E89)))+1,IFERROR(FIND("-",MID(E89,FIND(" ",E89)+1,LEN(E89)),FIND("-",MID(E89,FIND(" ",E89)+1,LEN(E89)))+1),LEN(MID(E89,FIND(" ",E89)+1,LEN(E89)))+1)-FIND("-",MID(E89,FIND(" ",E89)+1,LEN(E89)))-1),"") -> 利息支出 | L89: =IFERROR(MID(MID(E89,FIND(" ",E89)+1,LEN(E89)),FIND("-",MID(E89,FIND(" ",E89)+1,LEN(E89)),FIND("-",MID(E89,FIND(" ",E89)+1,LEN(E89)))+1)+1,LEN(E89)),"") | M89: =IFERROR(IF(H89="1002",1002,VLOOKUP(I89,亿企科目!A:H,6,0)),VLOOKUP(H89,亿企科目!A:G,6,0)) -> 6603 | N89: =IFERROR(IF(H89="1002","银行账户",IF(H89="1123","供应商",VLOOKUP(I89,亿企科目!A:H,8,0))),"") -> 费用项目 | O89: =IF(N89=0,IF(M89="1002",K89,""),_xlfn.TEXTAFTER(E89,"-",-1)) -> 利息支出 | P89: =VLOOKUP(A89,账簿!B:C,2,0) -> 002001 | Q89: =VLOOKUP(P89,账簿!A:B,2,0) -> 昌邑市昌信农业综合开发有限公司 | W89: =X89&AB89&AD89 -> 0020012026-04-213 | X89: =P89 -> 002001 | Y89: =X89 -> 002001 | Z89: =Q89 -> 昌邑市昌信农业综合开发有限公司 | AA89: =LEFT(B89,7) -> 2026-04 | AB89: =B89 -> 2026-04-21 | AC89: 记 | AD89: =VALUE(_xlfn.TEXTAFTER(C89,"-")) -> 3 | AE89: =D89 -> 2026-04-21,归还贷款 | AF89: 谭雅心 | AG89: 谭雅心 | AN89: =M89 -> 6603 | AP89: =D89 -> 2026-04-21,归还贷款 | AQ89: CNY | AR89: =F89 -> 156033.33 | AS89: =G89 | AT89: 01 | AU89: * | AV89: 1 | AW89: =AR89 -> 156033.33 | AX89: =AS89 | BQ89: =IF(N89="项目",VLOOKUP(O89,项目!B:C,2,0),IF(K89="空项目",VLOOKUP(K89,项目!B:C,2,0),"")) | BR89: =IFERROR(VLOOKUP(BQ89,项目!A:B,2,0),"") | BU89: =IF(N89="供应商",VLOOKUP(O89,供应商!B:C,2,0),"") | BV89: =IFERROR(VLOOKUP(BU89,供应商!A:B,2,0),"") | BW89: =IF(N89="客户",VLOOKUP(O89,客户!B:C,2,0),"") | BX89: =IFERROR(VLOOKUP(BW89,客户!A:B,2,0),"") | CU89: =IF(N89="费用项目",VLOOKUP(O89,费用项目!B:C,2,0),"") -> 660302 | CV89: =IFERROR(VLOOKUP(CU89,费用项目!A:B,2,0),"") -> 利息支出 | CW89: =IF(N89="银行账户",VLOOKUP(O89,银行变二级!B:C,2,0),"") | CX89: =IFERROR(VLOOKUP(O89,银行变二级!A:B,2,0),"")
A90: 昌邑市昌信农业综合开发有限公司 | B90: 2026-04-21 | C90: 记-003 | D90: 2026-04-21,归还贷款 | E90: 100204 银行存款-昌邑农发行经营收入户3341 | G90: 156033.33 | H90: =LEFT(E90,4) -> 1002 | I90: =IFERROR(LEFT(E90,FIND(" ",E90)-1),E90) -> 100204 | J90: =LEFT(MID(E90,FIND(" ",E90)+1,LEN(E90)),FIND("-",MID(E90,FIND(" ",E90)+1,LEN(E90))&"-")-1) -> 银行存款 | K90: =IFERROR(MID(MID(E90,FIND(" ",E90)+1,LEN(E90)),FIND("-",MID(E90,FIND(" ",E90)+1,LEN(E90)))+1,IFERROR(FIND("-",MID(E90,FIND(" ",E90)+1,LEN(E90)),FIND("-",MID(E90,FIND(" ",E90)+1,LEN(E90)))+1),LEN(MID(E90,FIND(" ",E90)+1,LEN(E90)))+1)-FIND("-",MID(E90,FIND(" ",E90)+1,LEN(E90)))-1),"") -> 昌邑农发行经营收入户3341 | L90: =IFERROR(MID(MID(E90,FIND(" ",E90)+1,LEN(E90)),FIND("-",MID(E90,FIND(" ",E90)+1,LEN(E90)),FIND("-",MID(E90,FIND(" ",E90)+1,LEN(E90)))+1)+1,LEN(E90)),"") | M90: =IFERROR(IF(H90="1002",1002,VLOOKUP(I90,亿企科目!A:H,6,0)),VLOOKUP(H90,亿企科目!A:G,6,0)) -> 1002 | N90: =IFERROR(IF(H90="1002","银行账户",IF(H90="1123","供应商",VLOOKUP(I90,亿企科目!A:H,8,0))),"") -> 银行账户 | O90: =IF(N90=0,IF(M90="1002",K90,""),_xlfn.TEXTAFTER(E90,"-",-1)) -> 昌邑农发行经营收入户3341 | P90: =VLOOKUP(A90,账簿!B:C,2,0) -> 002001 | Q90: =VLOOKUP(P90,账簿!A:B,2,0) -> 昌邑市昌信农业综合开发有限公司 | W90: =X90&AB90&AD90 -> 0020012026-04-213 | X90: =P90 -> 002001 | Y90: =X90 -> 002001 | Z90: =Q90 -> 昌邑市昌信农业综合开发有限公司 | AA90: =LEFT(B90,7) -> 2026-04 | AB90: =B90 -> 2026-04-21 | AC90: 记 | AD90: =VALUE(_xlfn.TEXTAFTER(C90,"-")) -> 3 | AE90: =D90 -> 2026-04-21,归还贷款 | AF90: 谭雅心 | AG90: 谭雅心 | AN90: =M90 -> 1002 | AP90: =D90 -> 2026-04-21,归还贷款 | AQ90: CNY | AR90: =F90 | AS90: =G90 -> 156033.33 | AT90: 01 | AU90: * | AV90: 1 | AW90: =AR90 | AX90: =AS90 -> 156033.33 | BQ90: =IF(N90="项目",VLOOKUP(O90,项目!B:C,2,0),IF(K90="空项目",VLOOKUP(K90,项目!B:C,2,0),"")) | BR90: =IFERROR(VLOOKUP(BQ90,项目!A:B,2,0),"") | BU90: =IF(N90="供应商",VLOOKUP(O90,供应商!B:C,2,0),"") | BV90: =IFERROR(VLOOKUP(BU90,供应商!A:B,2,0),"") | BW90: =IF(N90="客户",VLOOKUP(O90,客户!B:C,2,0),"") | BX90: =IFERROR(VLOOKUP(BW90,客户!A:B,2,0),"") | CU90: =IF(N90="费用项目",VLOOKUP(O90,费用项目!B:C,2,0),"") | CV90: =IFERROR(VLOOKUP(CU90,费用项目!A:B,2,0),"") | CW90: =IF(N90="银行账户",VLOOKUP(O90,银行变二级!B:C,2,0),"") -> 昌邑农发行经营收入户3341 | CX90: =IFERROR(VLOOKUP(O90,银行变二级!A:B,2,0),"") -> 昌邑农发行经营收入户3341
A91: 昌邑市昌信农业综合开发有限公司 | B91: 2026-04-21 | C91: 记-004 | D91: 2026-04-21,归还贷款 | E91: 6603 财务费用-利息支出 | F91: 234050 | H91: =LEFT(E91,4) -> 6603 | I91: =IFERROR(LEFT(E91,FIND(" ",E91)-1),E91) -> 6603 | J91: =LEFT(MID(E91,FIND(" ",E91)+1,LEN(E91)),FIND("-",MID(E91,FIND(" ",E91)+1,LEN(E91))&"-")-1) -> 财务费用 | K91: =IFERROR(MID(MID(E91,FIND(" ",E91)+1,LEN(E91)),FIND("-",MID(E91,FIND(" ",E91)+1,LEN(E91)))+1,IFERROR(FIND("-",MID(E91,FIND(" ",E91)+1,LEN(E91)),FIND("-",MID(E91,FIND(" ",E91)+1,LEN(E91)))+1),LEN(MID(E91,FIND(" ",E91)+1,LEN(E91)))+1)-FIND("-",MID(E91,FIND(" ",E91)+1,LEN(E91)))-1),"") -> 利息支出 | L91: =IFERROR(MID(MID(E91,FIND(" ",E91)+1,LEN(E91)),FIND("-",MID(E91,FIND(" ",E91)+1,LEN(E91)),FIND("-",MID(E91,FIND(" ",E91)+1,LEN(E91)))+1)+1,LEN(E91)),"") | M91: =IFERROR(IF(H91="1002",1002,VLOOKUP(I91,亿企科目!A:H,6,0)),VLOOKUP(H91,亿企科目!A:G,6,0)) -> 6603 | N91: =IFERROR(IF(H91="1002","银行账户",IF(H91="1123","供应商",VLOOKUP(I91,亿企科目!A:H,8,0))),"") -> 费用项目 | O91: =IF(N91=0,IF(M91="1002",K91,""),_xlfn.TEXTAFTER(E91,"-",-1)) -> 利息支出 | P91: =VLOOKUP(A91,账簿!B:C,2,0) -> 002001 | Q91: =VLOOKUP(P91,账簿!A:B,2,0) -> 昌邑市昌信农业综合开发有限公司 | W91: =X91&AB91&AD91 -> 0020012026-04-214 | X91: =P91 -> 002001 | Y91: =X91 -> 002001 | Z91: =Q91 -> 昌邑市昌信农业综合开发有限公司 | AA91: =LEFT(B91,7) -> 2026-04 | AB91: =B91 -> 2026-04-21 | AC91: 记 | AD91: =VALUE(_xlfn.TEXTAFTER(C91,"-")) -> 4 | AE91: =D91 -> 2026-04-21,归还贷款 | AF91: 谭雅心 | AG91: 谭雅心 | AN91: =M91 -> 6603 | AP91: =D91 -> 2026-04-21,归还贷款 | AQ91: CNY | AR91: =F91 -> 234050 | AS91: =G91 | AT91: 01 | AU91: * | AV91: 1 | AW91: =AR91 -> 234050 | AX91: =AS91 | BQ91: =IF(N91="项目",VLOOKUP(O91,项目!B:C,2,0),IF(K91="空项目",VLOOKUP(K91,项目!B:C,2,0),"")) | BR91: =IFERROR(VLOOKUP(BQ91,项目!A:B,2,0),"") | BU91: =IF(N91="供应商",VLOOKUP(O91,供应商!B:C,2,0),"") | BV91: =IFERROR(VLOOKUP(BU91,供应商!A:B,2,0),"") | BW91: =IF(N91="客户",VLOOKUP(O91,客户!B:C,2,0),"") | BX91: =IFERROR(VLOOKUP(BW91,客户!A:B,2,0),"") | CU91: =IF(N91="费用项目",VLOOKUP(O91,费用项目!B:C,2,0),"") -> 660302 | CV91: =IFERROR(VLOOKUP(CU91,费用项目!A:B,2,0),"") -> 利息支出 | CW91: =IF(N91="银行账户",VLOOKUP(O91,银行变二级!B:C,2,0),"") | CX91: =IFERROR(VLOOKUP(O91,银行变二级!A:B,2,0),"")
A92: 昌邑市昌信农业综合开发有限公司 | B92: 2026-04-21 | C92: 记-004 | D92: 2026-04-21,归还贷款 | E92: 100204 银行存款-昌邑农发行经营收入户3341 | G92: 234050 | H92: =LEFT(E92,4) -> 1002 | I92: =IFERROR(LEFT(E92,FIND(" ",E92)-1),E92) -> 100204 | J92: =LEFT(MID(E92,FIND(" ",E92)+1,LEN(E92)),FIND("-",MID(E92,FIND(" ",E92)+1,LEN(E92))&"-")-1) -> 银行存款 | K92: =IFERROR(MID(MID(E92,FIND(" ",E92)+1,LEN(E92)),FIND("-",MID(E92,FIND(" ",E92)+1,LEN(E92)))+1,IFERROR(FIND("-",MID(E92,FIND(" ",E92)+1,LEN(E92)),FIND("-",MID(E92,FIND(" ",E92)+1,LEN(E92)))+1),LEN(MID(E92,FIND(" ",E92)+1,LEN(E92)))+1)-FIND("-",MID(E92,FIND(" ",E92)+1,LEN(E92)))-1),"") -> 昌邑农发行经营收入户3341 | L92: =IFERROR(MID(MID(E92,FIND(" ",E92)+1,LEN(E92)),FIND("-",MID(E92,FIND(" ",E92)+1,LEN(E92)),FIND("-",MID(E92,FIND(" ",E92)+1,LEN(E92)))+1)+1,LEN(E92)),"") | M92: =IFERROR(IF(H92="1002",1002,VLOOKUP(I92,亿企科目!A:H,6,0)),VLOOKUP(H92,亿企科目!A:G,6,0)) -> 1002 | N92: =IFERROR(IF(H92="1002","银行账户",IF(H92="1123","供应商",VLOOKUP(I92,亿企科目!A:H,8,0))),"") -> 银行账户 | O92: =IF(N92=0,IF(M92="1002",K92,""),_xlfn.TEXTAFTER(E92,"-",-1)) -> 昌邑农发行经营收入户3341 | P92: =VLOOKUP(A92,账簿!B:C,2,0) -> 002001 | Q92: =VLOOKUP(P92,账簿!A:B,2,0) -> 昌邑市昌信农业综合开发有限公司 | W92: =X92&AB92&AD92 -> 0020012026-04-214 | X92: =P92 -> 002001 | Y92: =X92 -> 002001 | Z92: =Q92 -> 昌邑市昌信农业综合开发有限公司 | AA92: =LEFT(B92,7) -> 2026-04 | AB92: =B92 -> 2026-04-21 | AC92: 记 | AD92: =VALUE(_xlfn.TEXTAFTER(C92,"-")) -> 4 | AE92: =D92 -> 2026-04-21,归还贷款 | AF92: 谭雅心 | AG92: 谭雅心 | AN92: =M92 -> 1002 | AP92: =D92 -> 2026-04-21,归还贷款 | AQ92: CNY | AR92: =F92 | AS92: =G92 -> 234050 | AT92: 01 | AU92: * | AV92: 1 | AW92: =AR92 | AX92: =AS92 -> 234050 | BQ92: =IF(N92="项目",VLOOKUP(O92,项目!B:C,2,0),IF(K92="空项目",VLOOKUP(K92,项目!B:C,2,0),"")) | BR92: =IFERROR(VLOOKUP(BQ92,项目!A:B,2,0),"") | BU92: =IF(N92="供应商",VLOOKUP(O92,供应商!B:C,2,0),"") | BV92: =IFERROR(VLOOKUP(BU92,供应商!A:B,2,0),"") | BW92: =IF(N92="客户",VLOOKUP(O92,客户!B:C,2,0),"") | BX92: =IFERROR(VLOOKUP(BW92,客户!A:B,2,0),"") | CU92: =IF(N92="费用项目",VLOOKUP(O92,费用项目!B:C,2,0),"") | CV92: =IFERROR(VLOOKUP(CU92,费用项目!A:B,2,0),"") | CW92: =IF(N92="银行账户",VLOOKUP(O92,银行变二级!B:C,2,0),"") -> 昌邑农发行经营收入户3341 | CX92: =IFERROR(VLOOKUP(O92,银行变二级!A:B,2,0),"") -> 昌邑农发行经营收入户3341
